Workbook

Sheet Summary
A1: Phase | B1: Cases | C1: Run | D1: PASS | E1: FAIL | F1: BLOCKED | G1: Not run | H1: % Run | I1: % Pass | J1: P1 cases | K1: P1 FAIL | L1: GATE
A2: Phase 01 Foundation & Access | B2: 177 | C2: =COUNTIF('Phase 01 Foundation & Access'!$G$2:$G$178,"PASS")+COUNTIF('Phase 01 Foundation & Access'!$G$2:$G$178,"FAIL")+COUNTIF('Phase 01 Foundation & Access'!$G$2:$G$178,"BLOCKED") | D2: =COUNTIF('Phase 01 Foundation & Access'!$G$2:$G$178,"PASS") | E2: =COUNTIF('Phase 01 Foundation & Access'!$G$2:$G$178,"FAIL") | F2: =COUNTIF('Phase 01 Foundation & Access'!$G$2:$G$178,"BLOCKED") | G2: =177-(COUNTIF('Phase 01 Foundation & Access'!$G$2:$G$178,"PASS")+COUNTIF('Phase 01 Foundation & Access'!$G$2:$G$178,"FAIL")+COUNTIF('Phase 01 Foundation & Access'!$G$2:$G$178,"BLOCKED")) | H2: =IF(177=0,0,(COUNTIF('Phase 01 Foundation & Access'!$G$2:$G$178,"PASS")+COUNTIF('Phase 01 Foundation & Access'!$G$2:$G$178,"FAIL")+COUNTIF('Phase 01 Foundation & Access'!$G$2:$G$178,"BLOCKED"))/177) | I2: =IF((COUNTIF('Phase 01 Foundation & Access'!$G$2:$G$178,"PASS")+COUNTIF('Phase 01 Foundation & Access'!$G$2:$G$178,"FAIL")+COUNTIF('Phase 01 Foundation & Access'!$G$2:$G$178,"BLOCKED"))=0,0,COUNTIF('Phase 01 Foundation & Access'!$G$2:$G$178,"PASS")/(COUNTIF('Phase 01 Foundation & Access'!$G$2:$G$178,"PASS")+COUNTIF('Phase 01 Foundation & Access'!$G$2:$G$178,"FAIL")+COUNTIF('Phase 01 Foundation & Access'!$G$2:$G$178,"BLOCKED"))) | J2: =COUNTIF('Phase 01 Foundation & Access'!$C$2:$C$178,"P1") | K2: =COUNTIFS('Phase 01 Foundation & Access'!$C$2:$C$178,"P1",'Phase 01 Foundation & Access'!$G$2:$G$178,"FAIL") | L2: =IF(COUNTIFS('Phase 01 Foundation & Access'!$C$2:$C$178,"P1",'Phase 01 Foundation & Access'!$G$2:$G$178,"FAIL")>0,"BLOCKED - open P1",IF((COUNTIF('Phase 01 Foundation & Access'!$G$2:$G$178,"PASS")+COUNTIF('Phase 01 Foundation & Access'!$G$2:$G$178,"FAIL")+COUNTIF('Phase 01 Foundation & Access'!$G$2:$G$178,"BLOCKED"))<177,"IN PROGRESS",IF(COUNTIF('Phase 01 Foundation & Access'!$G$2:$G$178,"FAIL")>0,"BLOCKED - open defects","PASSED")))
A3: Phase 02 Settings & Masters | B3: 1056 | C3: =COUNTIF('Phase 02 Settings & Masters'!$G$2:$G$1057,"PASS")+COUNTIF('Phase 02 Settings & Masters'!$G$2:$G$1057,"FAIL")+COUNTIF('Phase 02 Settings & Masters'!$G$2:$G$1057,"BLOCKED") | D3: =COUNTIF('Phase 02 Settings & Masters'!$G$2:$G$1057,"PASS") | E3: =COUNTIF('Phase 02 Settings & Masters'!$G$2:$G$1057,"FAIL") | F3: =COUNTIF('Phase 02 Settings & Masters'!$G$2:$G$1057,"BLOCKED") | G3: =1056-(COUNTIF('Phase 02 Settings & Masters'!$G$2:$G$1057,"PASS")+COUNTIF('Phase 02 Settings & Masters'!$G$2:$G$1057,"FAIL")+COUNTIF('Phase 02 Settings & Masters'!$G$2:$G$1057,"BLOCKED")) | H3: =IF(1056=0,0,(COUNTIF('Phase 02 Settings & Masters'!$G$2:$G$1057,"PASS")+COUNTIF('Phase 02 Settings & Masters'!$G$2:$G$1057,"FAIL")+COUNTIF('Phase 02 Settings & Masters'!$G$2:$G$1057,"BLOCKED"))/1056) | I3: =IF((COUNTIF('Phase 02 Settings & Masters'!$G$2:$G$1057,"PASS")+COUNTIF('Phase 02 Settings & Masters'!$G$2:$G$1057,"FAIL")+COUNTIF('Phase 02 Settings & Masters'!$G$2:$G$1057,"BLOCKED"))=0,0,COUNTIF('Phase 02 Settings & Masters'!$G$2:$G$1057,"PASS")/(COUNTIF('Phase 02 Settings & Masters'!$G$2:$G$1057,"PASS")+COUNTIF('Phase 02 Settings & Masters'!$G$2:$G$1057,"FAIL")+COUNTIF('Phase 02 Settings & Masters'!$G$2:$G$1057,"BLOCKED"))) | J3: =COUNTIF('Phase 02 Settings & Masters'!$C$2:$C$1057,"P1") | K3: =COUNTIFS('Phase 02 Settings & Masters'!$C$2:$C$1057,"P1",'Phase 02 Settings & Masters'!$G$2:$G$1057,"FAIL") | L3: =IF(COUNTIFS('Phase 02 Settings & Masters'!$C$2:$C$1057,"P1",'Phase 02 Settings & Masters'!$G$2:$G$1057,"FAIL")>0,"BLOCKED - open P1",IF((COUNTIF('Phase 02 Settings & Masters'!$G$2:$G$1057,"PASS")+COUNTIF('Phase 02 Settings & Masters'!$G$2:$G$1057,"FAIL")+COUNTIF('Phase 02 Settings & Masters'!$G$2:$G$1057,"BLOCKED"))<1056,"IN PROGRESS",IF(COUNTIF('Phase 02 Settings & Masters'!$G$2:$G$1057,"FAIL")>0,"BLOCKED - open defects","PASSED")))
A4: Phase 03 Patient & Records | B4: 100 | C4: =COUNTIF('Phase 03 Patient & Records'!$G$2:$G$101,"PASS")+COUNTIF('Phase 03 Patient & Records'!$G$2:$G$101,"FAIL")+COUNTIF('Phase 03 Patient & Records'!$G$2:$G$101,"BLOCKED") | D4: =COUNTIF('Phase 03 Patient & Records'!$G$2:$G$101,"PASS") | E4: =COUNTIF('Phase 03 Patient & Records'!$G$2:$G$101,"FAIL") | F4: =COUNTIF('Phase 03 Patient & Records'!$G$2:$G$101,"BLOCKED") | G4: =100-(COUNTIF('Phase 03 Patient & Records'!$G$2:$G$101,"PASS")+COUNTIF('Phase 03 Patient & Records'!$G$2:$G$101,"FAIL")+COUNTIF('Phase 03 Patient & Records'!$G$2:$G$101,"BLOCKED")) | H4: =IF(100=0,0,(COUNTIF('Phase 03 Patient & Records'!$G$2:$G$101,"PASS")+COUNTIF('Phase 03 Patient & Records'!$G$2:$G$101,"FAIL")+COUNTIF('Phase 03 Patient & Records'!$G$2:$G$101,"BLOCKED"))/100) | I4: =IF((COUNTIF('Phase 03 Patient & Records'!$G$2:$G$101,"PASS")+COUNTIF('Phase 03 Patient & Records'!$G$2:$G$101,"FAIL")+COUNTIF('Phase 03 Patient & Records'!$G$2:$G$101,"BLOCKED"))=0,0,COUNTIF('Phase 03 Patient & Records'!$G$2:$G$101,"PASS")/(COUNTIF('Phase 03 Patient & Records'!$G$2:$G$101,"PASS")+COUNTIF('Phase 03 Patient & Records'!$G$2:$G$101,"FAIL")+COUNTIF('Phase 03 Patient & Records'!$G$2:$G$101,"BLOCKED"))) | J4: =COUNTIF('Phase 03 Patient & Records'!$C$2:$C$101,"P1") | K4: =COUNTIFS('Phase 03 Patient & Records'!$C$2:$C$101,"P1",'Phase 03 Patient & Records'!$G$2:$G$101,"FAIL") | L4: =IF(COUNTIFS('Phase 03 Patient & Records'!$C$2:$C$101,"P1",'Phase 03 Patient & Records'!$G$2:$G$101,"FAIL")>0,"BLOCKED - open P1",IF((COUNTIF('Phase 03 Patient & Records'!$G$2:$G$101,"PASS")+COUNTIF('Phase 03 Patient & Records'!$G$2:$G$101,"FAIL")+COUNTIF('Phase 03 Patient & Records'!$G$2:$G$101,"BLOCKED"))<100,"IN PROGRESS",IF(COUNTIF('Phase 03 Patient & Records'!$G$2:$G$101,"FAIL")>0,"BLOCKED - open defects","PASSED")))
A5: Phase 04 OPD Journey | B5: 260 | C5: =COUNTIF('Phase 04 OPD Journey'!$G$2:$G$261,"PASS")+COUNTIF('Phase 04 OPD Journey'!$G$2:$G$261,"FAIL")+COUNTIF('Phase 04 OPD Journey'!$G$2:$G$261,"BLOCKED") | D5: =COUNTIF('Phase 04 OPD Journey'!$G$2:$G$261,"PASS") | E5: =COUNTIF('Phase 04 OPD Journey'!$G$2:$G$261,"FAIL") | F5: =COUNTIF('Phase 04 OPD Journey'!$G$2:$G$261,"BLOCKED") | G5: =260-(COUNTIF('Phase 04 OPD Journey'!$G$2:$G$261,"PASS")+COUNTIF('Phase 04 OPD Journey'!$G$2:$G$261,"FAIL")+COUNTIF('Phase 04 OPD Journey'!$G$2:$G$261,"BLOCKED")) | H5: =IF(260=0,0,(COUNTIF('Phase 04 OPD Journey'!$G$2:$G$261,"PASS")+COUNTIF('Phase 04 OPD Journey'!$G$2:$G$261,"FAIL")+COUNTIF('Phase 04 OPD Journey'!$G$2:$G$261,"BLOCKED"))/260) | I5: =IF((COUNTIF('Phase 04 OPD Journey'!$G$2:$G$261,"PASS")+COUNTIF('Phase 04 OPD Journey'!$G$2:$G$261,"FAIL")+COUNTIF('Phase 04 OPD Journey'!$G$2:$G$261,"BLOCKED"))=0,0,COUNTIF('Phase 04 OPD Journey'!$G$2:$G$261,"PASS")/(COUNTIF('Phase 04 OPD Journey'!$G$2:$G$261,"PASS")+COUNTIF('Phase 04 OPD Journey'!$G$2:$G$261,"FAIL")+COUNTIF('Phase 04 OPD Journey'!$G$2:$G$261,"BLOCKED"))) | J5: =COUNTIF('Phase 04 OPD Journey'!$C$2:$C$261,"P1") | K5: =COUNTIFS('Phase 04 OPD Journey'!$C$2:$C$261,"P1",'Phase 04 OPD Journey'!$G$2:$G$261,"FAIL") | L5: =IF(COUNTIFS('Phase 04 OPD Journey'!$C$2:$C$261,"P1",'Phase 04 OPD Journey'!$G$2:$G$261,"FAIL")>0,"BLOCKED - open P1",IF((COUNTIF('Phase 04 OPD Journey'!$G$2:$G$261,"PASS")+COUNTIF('Phase 04 OPD Journey'!$G$2:$G$261,"FAIL")+COUNTIF('Phase 04 OPD Journey'!$G$2:$G$261,"BLOCKED"))<260,"IN PROGRESS",IF(COUNTIF('Phase 04 OPD Journey'!$G$2:$G$261,"FAIL")>0,"BLOCKED - open defects","PASSED")))
A6: Phase 05 Lab & Radiology | B6: 24 | C6: =COUNTIF('Phase 05 Lab & Radiology'!$G$2:$G$25,"PASS")+COUNTIF('Phase 05 Lab & Radiology'!$G$2:$G$25,"FAIL")+COUNTIF('Phase 05 Lab & Radiology'!$G$2:$G$25,"BLOCKED") | D6: =COUNTIF('Phase 05 Lab & Radiology'!$G$2:$G$25,"PASS") | E6: =COUNTIF('Phase 05 Lab & Radiology'!$G$2:$G$25,"FAIL") | F6: =COUNTIF('Phase 05 Lab & Radiology'!$G$2:$G$25,"BLOCKED") | G6: =24-(COUNTIF('Phase 05 Lab & Radiology'!$G$2:$G$25,"PASS")+COUNTIF('Phase 05 Lab & Radiology'!$G$2:$G$25,"FAIL")+COUNTIF('Phase 05 Lab & Radiology'!$G$2:$G$25,"BLOCKED")) | H6: =IF(24=0,0,(COUNTIF('Phase 05 Lab & Radiology'!$G$2:$G$25,"PASS")+COUNTIF('Phase 05 Lab & Radiology'!$G$2:$G$25,"FAIL")+COUNTIF('Phase 05 Lab & Radiology'!$G$2:$G$25,"BLOCKED"))/24) | I6: =IF((COUNTIF('Phase 05 Lab & Radiology'!$G$2:$G$25,"PASS")+COUNTIF('Phase 05 Lab & Radiology'!$G$2:$G$25,"FAIL")+COUNTIF('Phase 05 Lab & Radiology'!$G$2:$G$25,"BLOCKED"))=0,0,COUNTIF('Phase 05 Lab & Radiology'!$G$2:$G$25,"PASS")/(COUNTIF('Phase 05 Lab & Radiology'!$G$2:$G$25,"PASS")+COUNTIF('Phase 05 Lab & Radiology'!$G$2:$G$25,"FAIL")+COUNTIF('Phase 05 Lab & Radiology'!$G$2:$G$25,"BLOCKED"))) | J6: =COUNTIF('Phase 05 Lab & Radiology'!$C$2:$C$25,"P1") | K6: =COUNTIFS('Phase 05 Lab & Radiology'!$C$2:$C$25,"P1",'Phase 05 Lab & Radiology'!$G$2:$G$25,"FAIL") | L6: =IF(COUNTIFS('Phase 05 Lab & Radiology'!$C$2:$C$25,"P1",'Phase 05 Lab & Radiology'!$G$2:$G$25,"FAIL")>0,"BLOCKED - open P1",IF((COUNTIF('Phase 05 Lab & Radiology'!$G$2:$G$25,"PASS")+COUNTIF('Phase 05 Lab & Radiology'!$G$2:$G$25,"FAIL")+COUNTIF('Phase 05 Lab & Radiology'!$G$2:$G$25,"BLOCKED"))<24,"IN PROGRESS",IF(COUNTIF('Phase 05 Lab & Radiology'!$G$2:$G$25,"FAIL")>0,"BLOCKED - open defects","PASSED")))
A8: TOTAL | B8: =SUM(B2:B6) | C8: =SUM(C2:C6) | D8: =SUM(D2:D6) | E8: =SUM(E2:E6) | F8: =SUM(F2:F6) | G8: =SUM(G2:G6) | H8: =IF(B8=0,0,C8/B8) | I8: =IF(C8=0,0,D8/C8) | J8: =SUM(J2:J6) | K8: =SUM(K2:K6) | L8: =IF(K8>0,"NOT READY - open P1","")
A10: A phase is DONE only when: every case has a Status, zero open P1 defects, and every P1 case has a passing Playwright spec.

Sheet Scenario Status
A1: Journey Scenario | B1: Phase | C1: Cases | D1: PASS | E1: FAIL | F1: Not run | G1: Scenario Verdict
A2: P1-Setup | B2: Phase 01 Foundation & Access | C2: =COUNTIF('Phase 01 Foundation & Access'!$O$2:$O$178,"P1-Setup") | D2: =COUNTIFS('Phase 01 Foundation & Access'!$O$2:$O$178,"P1-Setup",'Phase 01 Foundation & Access'!$G$2:$G$178,"PASS") | E2: =COUNTIFS('Phase 01 Foundation & Access'!$O$2:$O$178,"P1-Setup",'Phase 01 Foundation & Access'!$G$2:$G$178,"FAIL") | F2: =COUNTIF('Phase 01 Foundation & Access'!$O$2:$O$178,"P1-Setup")-COUNTIFS('Phase 01 Foundation & Access'!$O$2:$O$178,"P1-Setup",'Phase 01 Foundation & Access'!$G$2:$G$178,"PASS")-COUNTIFS('Phase 01 Foundation & Access'!$O$2:$O$178,"P1-Setup",'Phase 01 Foundation & Access'!$G$2:$G$178,"FAIL")-COUNTIFS('Phase 01 Foundation & Access'!$O$2:$O$178,"P1-Setup",'Phase 01 Foundation & Access'!$G$2:$G$178,"BLOCKED") | G2: =IF(COUNTIFS('Phase 01 Foundation & Access'!$O$2:$O$178,"P1-Setup",'Phase 01 Foundation & Access'!$G$2:$G$178,"FAIL")>0,"FAIL",IF(COUNTIFS('Phase 01 Foundation & Access'!$O$2:$O$178,"P1-Setup",'Phase 01 Foundation & Access'!$G$2:$G$178,"PASS")=COUNTIF('Phase 01 Foundation & Access'!$O$2:$O$178,"P1-Setup"),"PASS",IF(COUNTIFS('Phase 01 Foundation & Access'!$O$2:$O$178,"P1-Setup",'Phase 01 Foundation & Access'!$G$2:$G$178,"PASS")+COUNTIFS('Phase 01 Foundation & Access'!$O$2:$O$178,"P1-Setup",'Phase 01 Foundation & Access'!$G$2:$G$178,"BLOCKED")>0,"IN PROGRESS","NOT STARTED")))
A3: P2-Setup | B3: Phase 02 Settings & Masters | C3: =COUNTIF('Phase 02 Settings & Masters'!$O$2:$O$1057,"P2-Setup") | D3: =COUNTIFS('Phase 02 Settings & Masters'!$O$2:$O$1057,"P2-Setup",'Phase 02 Settings & Masters'!$G$2:$G$1057,"PASS") | E3: =COUNTIFS('Phase 02 Settings & Masters'!$O$2:$O$1057,"P2-Setup",'Phase 02 Settings & Masters'!$G$2:$G$1057,"FAIL") | F3: =COUNTIF('Phase 02 Settings & Masters'!$O$2:$O$1057,"P2-Setup")-COUNTIFS('Phase 02 Settings & Masters'!$O$2:$O$1057,"P2-Setup",'Phase 02 Settings & Masters'!$G$2:$G$1057,"PASS")-COUNTIFS('Phase 02 Settings & Masters'!$O$2:$O$1057,"P2-Setup",'Phase 02 Settings & Masters'!$G$2:$G$1057,"FAIL")-COUNTIFS('Phase 02 Settings & Masters'!$O$2:$O$1057,"P2-Setup",'Phase 02 Settings & Masters'!$G$2:$G$1057,"BLOCKED") | G3: =IF(COUNTIFS('Phase 02 Settings & Masters'!$O$2:$O$1057,"P2-Setup",'Phase 02 Settings & Masters'!$G$2:$G$1057,"FAIL")>0,"FAIL",IF(COUNTIFS('Phase 02 Settings & Masters'!$O$2:$O$1057,"P2-Setup",'Phase 02 Settings & Masters'!$G$2:$G$1057,"PASS")=COUNTIF('Phase 02 Settings & Masters'!$O$2:$O$1057,"P2-Setup"),"PASS",IF(COUNTIFS('Phase 02 Settings & Masters'!$O$2:$O$1057,"P2-Setup",'Phase 02 Settings & Masters'!$G$2:$G$1057,"PASS")+COUNTIFS('Phase 02 Settings & Masters'!$O$2:$O$1057,"P2-Setup",'Phase 02 Settings & Masters'!$G$2:$G$1057,"BLOCKED")>0,"IN PROGRESS","NOT STARTED")))
A4: P3-S01 | B4: Phase 03 Patient & Records | C4: =COUNTIF('Phase 03 Patient & Records'!$O$2:$O$101,"P3-S01") | D4: =COUNTIFS('Phase 03 Patient & Records'!$O$2:$O$101,"P3-S01",'Phase 03 Patient & Records'!$G$2:$G$101,"PASS") | E4: =COUNTIFS('Phase 03 Patient & Records'!$O$2:$O$101,"P3-S01",'Phase 03 Patient & Records'!$G$2:$G$101,"FAIL") | F4: =COUNTIF('Phase 03 Patient & Records'!$O$2:$O$101,"P3-S01")-COUNTIFS('Phase 03 Patient & Records'!$O$2:$O$101,"P3-S01",'Phase 03 Patient & Records'!$G$2:$G$101,"PASS")-COUNTIFS('Phase 03 Patient & Records'!$O$2:$O$101,"P3-S01",'Phase 03 Patient & Records'!$G$2:$G$101,"FAIL")-COUNTIFS('Phase 03 Patient & Records'!$O$2:$O$101,"P3-S01",'Phase 03 Patient & Records'!$G$2:$G$101,"BLOCKED") | G4: =IF(COUNTIFS('Phase 03 Patient & Records'!$O$2:$O$101,"P3-S01",'Phase 03 Patient & Records'!$G$2:$G$101,"FAIL")>0,"FAIL",IF(COUNTIFS('Phase 03 Patient & Records'!$O$2:$O$101,"P3-S01",'Phase 03 Patient & Records'!$G$2:$G$101,"PASS")=COUNTIF('Phase 03 Patient & Records'!$O$2:$O$101,"P3-S01"),"PASS",IF(COUNTIFS('Phase 03 Patient & Records'!$O$2:$O$101,"P3-S01",'Phase 03 Patient & Records'!$G$2:$G$101,"PASS")+COUNTIFS('Phase 03 Patient & Records'!$O$2:$O$101,"P3-S01",'Phase 03 Patient & Records'!$G$2:$G$101,"BLOCKED")>0,"IN PROGRESS","NOT STARTED")))
A5: P3-S02 | B5: Phase 03 Patient & Records | C5: =COUNTIF('Phase 03 Patient & Records'!$O$2:$O$101,"P3-S02") | D5: =COUNTIFS('Phase 03 Patient & Records'!$O$2:$O$101,"P3-S02",'Phase 03 Patient & Records'!$G$2:$G$101,"PASS") | E5: =COUNTIFS('Phase 03 Patient & Records'!$O$2:$O$101,"P3-S02",'Phase 03 Patient & Records'!$G$2:$G$101,"FAIL") | F5: =COUNTIF('Phase 03 Patient & Records'!$O$2:$O$101,"P3-S02")-COUNTIFS('Phase 03 Patient & Records'!$O$2:$O$101,"P3-S02",'Phase 03 Patient & Records'!$G$2:$G$101,"PASS")-COUNTIFS('Phase 03 Patient & Records'!$O$2:$O$101,"P3-S02",'Phase 03 Patient & Records'!$G$2:$G$101,"FAIL")-COUNTIFS('Phase 03 Patient & Records'!$O$2:$O$101,"P3-S02",'Phase 03 Patient & Records'!$G$2:$G$101,"BLOCKED") | G5: =IF(COUNTIFS('Phase 03 Patient & Records'!$O$2:$O$101,"P3-S02",'Phase 03 Patient & Records'!$G$2:$G$101,"FAIL")>0,"FAIL",IF(COUNTIFS('Phase 03 Patient & Records'!$O$2:$O$101,"P3-S02",'Phase 03 Patient & Records'!$G$2:$G$101,"PASS")=COUNTIF('Phase 03 Patient & Records'!$O$2:$O$101,"P3-S02"),"PASS",IF(COUNTIFS('Phase 03 Patient & Records'!$O$2:$O$101,"P3-S02",'Phase 03 Patient & Records'!$G$2:$G$101,"PASS")+COUNTIFS('Phase 03 Patient & Records'!$O$2:$O$101,"P3-S02",'Phase 03 Patient & Records'!$G$2:$G$101,"BLOCKED")>0,"IN PROGRESS","NOT STARTED")))
A6: P3-S03 | B6: Phase 03 Patient & Records | C6: =COUNTIF('Phase 03 Patient & Records'!$O$2:$O$101,"P3-S03") | D6: =COUNTIFS('Phase 03 Patient & Records'!$O$2:$O$101,"P3-S03",'Phase 03 Patient & Records'!$G$2:$G$101,"PASS") | E6: =COUNTIFS('Phase 03 Patient & Records'!$O$2:$O$101,"P3-S03",'Phase 03 Patient & Records'!$G$2:$G$101,"FAIL") | F6: =COUNTIF('Phase 03 Patient & Records'!$O$2:$O$101,"P3-S03")-COUNTIFS('Phase 03 Patient & Records'!$O$2:$O$101,"P3-S03",'Phase 03 Patient & Records'!$G$2:$G$101,"PASS")-COUNTIFS('Phase 03 Patient & Records'!$O$2:$O$101,"P3-S03",'Phase 03 Patient & Records'!$G$2:$G$101,"FAIL")-COUNTIFS('Phase 03 Patient & Records'!$O$2:$O$101,"P3-S03",'Phase 03 Patient & Records'!$G$2:$G$101,"BLOCKED") | G6: =IF(COUNTIFS('Phase 03 Patient & Records'!$O$2:$O$101,"P3-S03",'Phase 03 Patient & Records'!$G$2:$G$101,"FAIL")>0,"FAIL",IF(COUNTIFS('Phase 03 Patient & Records'!$O$2:$O$101,"P3-S03",'Phase 03 Patient & Records'!$G$2:$G$101,"PASS")=COUNTIF('Phase 03 Patient & Records'!$O$2:$O$101,"P3-S03"),"PASS",IF(COUNTIFS('Phase 03 Patient & Records'!$O$2:$O$101,"P3-S03",'Phase 03 Patient & Records'!$G$2:$G$101,"PASS")+COUNTIFS('Phase 03 Patient & Records'!$O$2:$O$101,"P3-S03",'Phase 03 Patient & Records'!$G$2:$G$101,"BLOCKED")>0,"IN PROGRESS","NOT STARTED")))
A7: P3-S04 | B7: Phase 03 Patient & Records | C7: =COUNTIF('Phase 03 Patient & Records'!$O$2:$O$101,"P3-S04") | D7: =COUNTIFS('Phase 03 Patient & Records'!$O$2:$O$101,"P3-S04",'Phase 03 Patient & Records'!$G$2:$G$101,"PASS") | E7: =COUNTIFS('Phase 03 Patient & Records'!$O$2:$O$101,"P3-S04",'Phase 03 Patient & Records'!$G$2:$G$101,"FAIL") | F7: =COUNTIF('Phase 03 Patient & Records'!$O$2:$O$101,"P3-S04")-COUNTIFS('Phase 03 Patient & Records'!$O$2:$O$101,"P3-S04",'Phase 03 Patient & Records'!$G$2:$G$101,"PASS")-COUNTIFS('Phase 03 Patient & Records'!$O$2:$O$101,"P3-S04",'Phase 03 Patient & Records'!$G$2:$G$101,"FAIL")-COUNTIFS('Phase 03 Patient & Records'!$O$2:$O$101,"P3-S04",'Phase 03 Patient & Records'!$G$2:$G$101,"BLOCKED") | G7: =IF(COUNTIFS('Phase 03 Patient & Records'!$O$2:$O$101,"P3-S04",'Phase 03 Patient & Records'!$G$2:$G$101,"FAIL")>0,"FAIL",IF(COUNTIFS('Phase 03 Patient & Records'!$O$2:$O$101,"P3-S04",'Phase 03 Patient & Records'!$G$2:$G$101,"PASS")=COUNTIF('Phase 03 Patient & Records'!$O$2:$O$101,"P3-S04"),"PASS",IF(COUNTIFS('Phase 03 Patient & Records'!$O$2:$O$101,"P3-S04",'Phase 03 Patient & Records'!$G$2:$G$101,"PASS")+COUNTIFS('Phase 03 Patient & Records'!$O$2:$O$101,"P3-S04",'Phase 03 Patient & Records'!$G$2:$G$101,"BLOCKED")>0,"IN PROGRESS","NOT STARTED")))
A8: P3-S05 | B8: Phase 03 Patient & Records | C8: =COUNTIF('Phase 03 Patient & Records'!$O$2:$O$101,"P3-S05") | D8: =COUNTIFS('Phase 03 Patient & Records'!$O$2:$O$101,"P3-S05",'Phase 03 Patient & Records'!$G$2:$G$101,"PASS") | E8: =COUNTIFS('Phase 03 Patient & Records'!$O$2:$O$101,"P3-S05",'Phase 03 Patient & Records'!$G$2:$G$101,"FAIL") | F8: =COUNTIF('Phase 03 Patient & Records'!$O$2:$O$101,"P3-S05")-COUNTIFS('Phase 03 Patient & Records'!$O$2:$O$101,"P3-S05",'Phase 03 Patient & Records'!$G$2:$G$101,"PASS")-COUNTIFS('Phase 03 Patient & Records'!$O$2:$O$101,"P3-S05",'Phase 03 Patient & Records'!$G$2:$G$101,"FAIL")-COUNTIFS('Phase 03 Patient & Records'!$O$2:$O$101,"P3-S05",'Phase 03 Patient & Records'!$G$2:$G$101,"BLOCKED") | G8: =IF(COUNTIFS('Phase 03 Patient & Records'!$O$2:$O$101,"P3-S05",'Phase 03 Patient & Records'!$G$2:$G$101,"FAIL")>0,"FAIL",IF(COUNTIFS('Phase 03 Patient & Records'!$O$2:$O$101,"P3-S05",'Phase 03 Patient & Records'!$G$2:$G$101,"PASS")=COUNTIF('Phase 03 Patient & Records'!$O$2:$O$101,"P3-S05"),"PASS",IF(COUNTIFS('Phase 03 Patient & Records'!$O$2:$O$101,"P3-S05",'Phase 03 Patient & Records'!$G$2:$G$101,"PASS")+COUNTIFS('Phase 03 Patient & Records'!$O$2:$O$101,"P3-S05",'Phase 03 Patient & Records'!$G$2:$G$101,"BLOCKED")>0,"IN PROGRESS","NOT STARTED")))
A9: P3-S06 | B9: Phase 03 Patient & Records | C9: =COUNTIF('Phase 03 Patient & Records'!$O$2:$O$101,"P3-S06") | D9: =COUNTIFS('Phase 03 Patient & Records'!$O$2:$O$101,"P3-S06",'Phase 03 Patient & Records'!$G$2:$G$101,"PASS") | E9: =COUNTIFS('Phase 03 Patient & Records'!$O$2:$O$101,"P3-S06",'Phase 03 Patient & Records'!$G$2:$G$101,"FAIL") | F9: =COUNTIF('Phase 03 Patient & Records'!$O$2:$O$101,"P3-S06")-COUNTIFS('Phase 03 Patient & Records'!$O$2:$O$101,"P3-S06",'Phase 03 Patient & Records'!$G$2:$G$101,"PASS")-COUNTIFS('Phase 03 Patient & Records'!$O$2:$O$101,"P3-S06",'Phase 03 Patient & Records'!$G$2:$G$101,"FAIL")-COUNTIFS('Phase 03 Patient & Records'!$O$2:$O$101,"P3-S06",'Phase 03 Patient & Records'!$G$2:$G$101,"BLOCKED") | G9: =IF(COUNTIFS('Phase 03 Patient & Records'!$O$2:$O$101,"P3-S06",'Phase 03 Patient & Records'!$G$2:$G$101,"FAIL")>0,"FAIL",IF(COUNTIFS('Phase 03 Patient & Records'!$O$2:$O$101,"P3-S06",'Phase 03 Patient & Records'!$G$2:$G$101,"PASS")=COUNTIF('Phase 03 Patient & Records'!$O$2:$O$101,"P3-S06"),"PASS",IF(COUNTIFS('Phase 03 Patient & Records'!$O$2:$O$101,"P3-S06",'Phase 03 Patient & Records'!$G$2:$G$101,"PASS")+COUNTIFS('Phase 03 Patient & Records'!$O$2:$O$101,"P3-S06",'Phase 03 Patient & Records'!$G$2:$G$101,"BLOCKED")>0,"IN PROGRESS","NOT STARTED")))
A10: P3-S07 | B10: Phase 03 Patient & Records | C10: =COUNTIF('Phase 03 Patient & Records'!$O$2:$O$101,"P3-S07") | D10: =COUNTIFS('Phase 03 Patient & Records'!$O$2:$O$101,"P3-S07",'Phase 03 Patient & Records'!$G$2:$G$101,"PASS") | E10: =COUNTIFS('Phase 03 Patient & Records'!$O$2:$O$101,"P3-S07",'Phase 03 Patient & Records'!$G$2:$G$101,"FAIL") | F10: =COUNTIF('Phase 03 Patient & Records'!$O$2:$O$101,"P3-S07")-COUNTIFS('Phase 03 Patient & Records'!$O$2:$O$101,"P3-S07",'Phase 03 Patient & Records'!$G$2:$G$101,"PASS")-COUNTIFS('Phase 03 Patient & Records'!$O$2:$O$101,"P3-S07",'Phase 03 Patient & Records'!$G$2:$G$101,"FAIL")-COUNTIFS('Phase 03 Patient & Records'!$O$2:$O$101,"P3-S07",'Phase 03 Patient & Records'!$G$2:$G$101,"BLOCKED") | G10: =IF(COUNTIFS('Phase 03 Patient & Records'!$O$2:$O$101,"P3-S07",'Phase 03 Patient & Records'!$G$2:$G$101,"FAIL")>0,"FAIL",IF(COUNTIFS('Phase 03 Patient & Records'!$O$2:$O$101,"P3-S07",'Phase 03 Patient & Records'!$G$2:$G$101,"PASS")=COUNTIF('Phase 03 Patient & Records'!$O$2:$O$101,"P3-S07"),"PASS",IF(COUNTIFS('Phase 03 Patient & Records'!$O$2:$O$101,"P3-S07",'Phase 03 Patient & Records'!$G$2:$G$101,"PASS")+COUNTIFS('Phase 03 Patient & Records'!$O$2:$O$101,"P3-S07",'Phase 03 Patient & Records'!$G$2:$G$101,"BLOCKED")>0,"IN PROGRESS","NOT STARTED")))
A11: P3-S08 | B11: Phase 03 Patient & Records | C11: =COUNTIF('Phase 03 Patient & Records'!$O$2:$O$101,"P3-S08") | D11: =COUNTIFS('Phase 03 Patient & Records'!$O$2:$O$101,"P3-S08",'Phase 03 Patient & Records'!$G$2:$G$101,"PASS") | E11: =COUNTIFS('Phase 03 Patient & Records'!$O$2:$O$101,"P3-S08",'Phase 03 Patient & Records'!$G$2:$G$101,"FAIL") | F11: =COUNTIF('Phase 03 Patient & Records'!$O$2:$O$101,"P3-S08")-COUNTIFS('Phase 03 Patient & Records'!$O$2:$O$101,"P3-S08",'Phase 03 Patient & Records'!$G$2:$G$101,"PASS")-COUNTIFS('Phase 03 Patient & Records'!$O$2:$O$101,"P3-S08",'Phase 03 Patient & Records'!$G$2:$G$101,"FAIL")-COUNTIFS('Phase 03 Patient & Records'!$O$2:$O$101,"P3-S08",'Phase 03 Patient & Records'!$G$2:$G$101,"BLOCKED") | G11: =IF(COUNTIFS('Phase 03 Patient & Records'!$O$2:$O$101,"P3-S08",'Phase 03 Patient & Records'!$G$2:$G$101,"FAIL")>0,"FAIL",IF(COUNTIFS('Phase 03 Patient & Records'!$O$2:$O$101,"P3-S08",'Phase 03 Patient & Records'!$G$2:$G$101,"PASS")=COUNTIF('Phase 03 Patient & Records'!$O$2:$O$101,"P3-S08"),"PASS",IF(COUNTIFS('Phase 03 Patient & Records'!$O$2:$O$101,"P3-S08",'Phase 03 Patient & Records'!$G$2:$G$101,"PASS")+COUNTIFS('Phase 03 Patient & Records'!$O$2:$O$101,"P3-S08",'Phase 03 Patient & Records'!$G$2:$G$101,"BLOCKED")>0,"IN PROGRESS","NOT STARTED")))
A12: P3-S09 | B12: Phase 03 Patient & Records | C12: =COUNTIF('Phase 03 Patient & Records'!$O$2:$O$101,"P3-S09") | D12: =COUNTIFS('Phase 03 Patient & Records'!$O$2:$O$101,"P3-S09",'Phase 03 Patient & Records'!$G$2:$G$101,"PASS") | E12: =COUNTIFS('Phase 03 Patient & Records'!$O$2:$O$101,"P3-S09",'Phase 03 Patient & Records'!$G$2:$G$101,"FAIL") | F12: =COUNTIF('Phase 03 Patient & Records'!$O$2:$O$101,"P3-S09")-COUNTIFS('Phase 03 Patient & Records'!$O$2:$O$101,"P3-S09",'Phase 03 Patient & Records'!$G$2:$G$101,"PASS")-COUNTIFS('Phase 03 Patient & Records'!$O$2:$O$101,"P3-S09",'Phase 03 Patient & Records'!$G$2:$G$101,"FAIL")-COUNTIFS('Phase 03 Patient & Records'!$O$2:$O$101,"P3-S09",'Phase 03 Patient & Records'!$G$2:$G$101,"BLOCKED") | G12: =IF(COUNTIFS('Phase 03 Patient & Records'!$O$2:$O$101,"P3-S09",'Phase 03 Patient & Records'!$G$2:$G$101,"FAIL")>0,"FAIL",IF(COUNTIFS('Phase 03 Patient & Records'!$O$2:$O$101,"P3-S09",'Phase 03 Patient & Records'!$G$2:$G$101,"PASS")=COUNTIF('Phase 03 Patient & Records'!$O$2:$O$101,"P3-S09"),"PASS",IF(COUNTIFS('Phase 03 Patient & Records'!$O$2:$O$101,"P3-S09",'Phase 03 Patient & Records'!$G$2:$G$101,"PASS")+COUNTIFS('Phase 03 Patient & Records'!$O$2:$O$101,"P3-S09",'Phase 03 Patient & Records'!$G$2:$G$101,"BLOCKED")>0,"IN PROGRESS","NOT STARTED")))
A13: P3-S10 | B13: Phase 03 Patient & Records | C13: =COUNTIF('Phase 03 Patient & Records'!$O$2:$O$101,"P3-S10") | D13: =COUNTIFS('Phase 03 Patient & Records'!$O$2:$O$101,"P3-S10",'Phase 03 Patient & Records'!$G$2:$G$101,"PASS") | E13: =COUNTIFS('Phase 03 Patient & Records'!$O$2:$O$101,"P3-S10",'Phase 03 Patient & Records'!$G$2:$G$101,"FAIL") | F13: =COUNTIF('Phase 03 Patient & Records'!$O$2:$O$101,"P3-S10")-COUNTIFS('Phase 03 Patient & Records'!$O$2:$O$101,"P3-S10",'Phase 03 Patient & Records'!$G$2:$G$101,"PASS")-COUNTIFS('Phase 03 Patient & Records'!$O$2:$O$101,"P3-S10",'Phase 03 Patient & Records'!$G$2:$G$101,"FAIL")-COUNTIFS('Phase 03 Patient & Records'!$O$2:$O$101,"P3-S10",'Phase 03 Patient & Records'!$G$2:$G$101,"BLOCKED") | G13: =IF(COUNTIFS('Phase 03 Patient & Records'!$O$2:$O$101,"P3-S10",'Phase 03 Patient & Records'!$G$2:$G$101,"FAIL")>0,"FAIL",IF(COUNTIFS('Phase 03 Patient & Records'!$O$2:$O$101,"P3-S10",'Phase 03 Patient & Records'!$G$2:$G$101,"PASS")=COUNTIF('Phase 03 Patient & Records'!$O$2:$O$101,"P3-S10"),"PASS",IF(COUNTIFS('Phase 03 Patient & Records'!$O$2:$O$101,"P3-S10",'Phase 03 Patient & Records'!$G$2:$G$101,"PASS")+COUNTIFS('Phase 03 Patient & Records'!$O$2:$O$101,"P3-S10",'Phase 03 Patient & Records'!$G$2:$G$101,"BLOCKED")>0,"IN PROGRESS","NOT STARTED")))
A14: P3-S11 | B14: Phase 03 Patient & Records | C14: =COUNTIF('Phase 03 Patient & Records'!$O$2:$O$101,"P3-S11") | D14: =COUNTIFS('Phase 03 Patient & Records'!$O$2:$O$101,"P3-S11",'Phase 03 Patient & Records'!$G$2:$G$101,"PASS") | E14: =COUNTIFS('Phase 03 Patient & Records'!$O$2:$O$101,"P3-S11",'Phase 03 Patient & Records'!$G$2:$G$101,"FAIL") | F14: =COUNTIF('Phase 03 Patient & Records'!$O$2:$O$101,"P3-S11")-COUNTIFS('Phase 03 Patient & Records'!$O$2:$O$101,"P3-S11",'Phase 03 Patient & Records'!$G$2:$G$101,"PASS")-COUNTIFS('Phase 03 Patient & Records'!$O$2:$O$101,"P3-S11",'Phase 03 Patient & Records'!$G$2:$G$101,"FAIL")-COUNTIFS('Phase 03 Patient & Records'!$O$2:$O$101,"P3-S11",'Phase 03 Patient & Records'!$G$2:$G$101,"BLOCKED") | G14: =IF(COUNTIFS('Phase 03 Patient & Records'!$O$2:$O$101,"P3-S11",'Phase 03 Patient & Records'!$G$2:$G$101,"FAIL")>0,"FAIL",IF(COUNTIFS('Phase 03 Patient & Records'!$O$2:$O$101,"P3-S11",'Phase 03 Patient & Records'!$G$2:$G$101,"PASS")=COUNTIF('Phase 03 Patient & Records'!$O$2:$O$101,"P3-S11"),"PASS",IF(COUNTIFS('Phase 03 Patient & Records'!$O$2:$O$101,"P3-S11",'Phase 03 Patient & Records'!$G$2:$G$101,"PASS")+COUNTIFS('Phase 03 Patient & Records'!$O$2:$O$101,"P3-S11",'Phase 03 Patient & Records'!$G$2:$G$101,"BLOCKED")>0,"IN PROGRESS","NOT STARTED")))
A15: P3-S12 | B15: Phase 03 Patient & Records | C15: =COUNTIF('Phase 03 Patient & Records'!$O$2:$O$101,"P3-S12") | D15: =COUNTIFS('Phase 03 Patient & Records'!$O$2:$O$101,"P3-S12",'Phase 03 Patient & Records'!$G$2:$G$101,"PASS") | E15: =COUNTIFS('Phase 03 Patient & Records'!$O$2:$O$101,"P3-S12",'Phase 03 Patient & Records'!$G$2:$G$101,"FAIL") | F15: =COUNTIF('Phase 03 Patient & Records'!$O$2:$O$101,"P3-S12")-COUNTIFS('Phase 03 Patient & Records'!$O$2:$O$101,"P3-S12",'Phase 03 Patient & Records'!$G$2:$G$101,"PASS")-COUNTIFS('Phase 03 Patient & Records'!$O$2:$O$101,"P3-S12",'Phase 03 Patient & Records'!$G$2:$G$101,"FAIL")-COUNTIFS('Phase 03 Patient & Records'!$O$2:$O$101,"P3-S12",'Phase 03 Patient & Records'!$G$2:$G$101,"BLOCKED") | G15: =IF(COUNTIFS('Phase 03 Patient & Records'!$O$2:$O$101,"P3-S12",'Phase 03 Patient & Records'!$G$2:$G$101,"FAIL")>0,"FAIL",IF(COUNTIFS('Phase 03 Patient & Records'!$O$2:$O$101,"P3-S12",'Phase 03 Patient & Records'!$G$2:$G$101,"PASS")=COUNTIF('Phase 03 Patient & Records'!$O$2:$O$101,"P3-S12"),"PASS",IF(COUNTIFS('Phase 03 Patient & Records'!$O$2:$O$101,"P3-S12",'Phase 03 Patient & Records'!$G$2:$G$101,"PASS")+COUNTIFS('Phase 03 Patient & Records'!$O$2:$O$101,"P3-S12",'Phase 03 Patient & Records'!$G$2:$G$101,"BLOCKED")>0,"IN PROGRESS","NOT STARTED")))
A16: P4-S01 | B16: Phase 04 OPD Journey | C16: =COUNTIF('Phase 04 OPD Journey'!$O$2:$O$261,"P4-S01") | D16: =COUNTIFS('Phase 04 OPD Journey'!$O$2:$O$261,"P4-S01",'Phase 04 OPD Journey'!$G$2:$G$261,"PASS") | E16: =COUNTIFS('Phase 04 OPD Journey'!$O$2:$O$261,"P4-S01",'Phase 04 OPD Journey'!$G$2:$G$261,"FAIL") | F16: =COUNTIF('Phase 04 OPD Journey'!$O$2:$O$261,"P4-S01")-COUNTIFS('Phase 04 OPD Journey'!$O$2:$O$261,"P4-S01",'Phase 04 OPD Journey'!$G$2:$G$261,"PASS")-COUNTIFS('Phase 04 OPD Journey'!$O$2:$O$261,"P4-S01",'Phase 04 OPD Journey'!$G$2:$G$261,"FAIL")-COUNTIFS('Phase 04 OPD Journey'!$O$2:$O$261,"P4-S01",'Phase 04 OPD Journey'!$G$2:$G$261,"BLOCKED") | G16: =IF(COUNTIFS('Phase 04 OPD Journey'!$O$2:$O$261,"P4-S01",'Phase 04 OPD Journey'!$G$2:$G$261,"FAIL")>0,"FAIL",IF(COUNTIFS('Phase 04 OPD Journey'!$O$2:$O$261,"P4-S01",'Phase 04 OPD Journey'!$G$2:$G$261,"PASS")=COUNTIF('Phase 04 OPD Journey'!$O$2:$O$261,"P4-S01"),"PASS",IF(COUNTIFS('Phase 04 OPD Journey'!$O$2:$O$261,"P4-S01",'Phase 04 OPD Journey'!$G$2:$G$261,"PASS")+COUNTIFS('Phase 04 OPD Journey'!$O$2:$O$261,"P4-S01",'Phase 04 OPD Journey'!$G$2:$G$261,"BLOCKED")>0,"IN PROGRESS","NOT STARTED")))
A17: P4-S02 | B17: Phase 04 OPD Journey | C17: =COUNTIF('Phase 04 OPD Journey'!$O$2:$O$261,"P4-S02") | D17: =COUNTIFS('Phase 04 OPD Journey'!$O$2:$O$261,"P4-S02",'Phase 04 OPD Journey'!$G$2:$G$261,"PASS") | E17: =COUNTIFS('Phase 04 OPD Journey'!$O$2:$O$261,"P4-S02",'Phase 04 OPD Journey'!$G$2:$G$261,"FAIL") | F17: =COUNTIF('Phase 04 OPD Journey'!$O$2:$O$261,"P4-S02")-COUNTIFS('Phase 04 OPD Journey'!$O$2:$O$261,"P4-S02",'Phase 04 OPD Journey'!$G$2:$G$261,"PASS")-COUNTIFS('Phase 04 OPD Journey'!$O$2:$O$261,"P4-S02",'Phase 04 OPD Journey'!$G$2:$G$261,"FAIL")-COUNTIFS('Phase 04 OPD Journey'!$O$2:$O$261,"P4-S02",'Phase 04 OPD Journey'!$G$2:$G$261,"BLOCKED") | G17: =IF(COUNTIFS('Phase 04 OPD Journey'!$O$2:$O$261,"P4-S02",'Phase 04 OPD Journey'!$G$2:$G$261,"FAIL")>0,"FAIL",IF(COUNTIFS('Phase 04 OPD Journey'!$O$2:$O$261,"P4-S02",'Phase 04 OPD Journey'!$G$2:$G$261,"PASS")=COUNTIF('Phase 04 OPD Journey'!$O$2:$O$261,"P4-S02"),"PASS",IF(COUNTIFS('Phase 04 OPD Journey'!$O$2:$O$261,"P4-S02",'Phase 04 OPD Journey'!$G$2:$G$261,"PASS")+COUNTIFS('Phase 04 OPD Journey'!$O$2:$O$261,"P4-S02",'Phase 04 OPD Journey'!$G$2:$G$261,"BLOCKED")>0,"IN PROGRESS","NOT STARTED")))
A18: P4-S03 | B18: Phase 04 OPD Journey | C18: =COUNTIF('Phase 04 OPD Journey'!$O$2:$O$261,"P4-S03") | D18: =COUNTIFS('Phase 04 OPD Journey'!$O$2:$O$261,"P4-S03",'Phase 04 OPD Journey'!$G$2:$G$261,"PASS") | E18: =COUNTIFS('Phase 04 OPD Journey'!$O$2:$O$261,"P4-S03",'Phase 04 OPD Journey'!$G$2:$G$261,"FAIL") | F18: =COUNTIF('Phase 04 OPD Journey'!$O$2:$O$261,"P4-S03")-COUNTIFS('Phase 04 OPD Journey'!$O$2:$O$261,"P4-S03",'Phase 04 OPD Journey'!$G$2:$G$261,"PASS")-COUNTIFS('Phase 04 OPD Journey'!$O$2:$O$261,"P4-S03",'Phase 04 OPD Journey'!$G$2:$G$261,"FAIL")-COUNTIFS('Phase 04 OPD Journey'!$O$2:$O$261,"P4-S03",'Phase 04 OPD Journey'!$G$2:$G$261,"BLOCKED") | G18: =IF(COUNTIFS('Phase 04 OPD Journey'!$O$2:$O$261,"P4-S03",'Phase 04 OPD Journey'!$G$2:$G$261,"FAIL")>0,"FAIL",IF(COUNTIFS('Phase 04 OPD Journey'!$O$2:$O$261,"P4-S03",'Phase 04 OPD Journey'!$G$2:$G$261,"PASS")=COUNTIF('Phase 04 OPD Journey'!$O$2:$O$261,"P4-S03"),"PASS",IF(COUNTIFS('Phase 04 OPD Journey'!$O$2:$O$261,"P4-S03",'Phase 04 OPD Journey'!$G$2:$G$261,"PASS")+COUNTIFS('Phase 04 OPD Journey'!$O$2:$O$261,"P4-S03",'Phase 04 OPD Journey'!$G$2:$G$261,"BLOCKED")>0,"IN PROGRESS","NOT STARTED")))
A19: P4-S04 | B19: Phase 04 OPD Journey | C19: =COUNTIF('Phase 04 OPD Journey'!$O$2:$O$261,"P4-S04") | D19: =COUNTIFS('Phase 04 OPD Journey'!$O$2:$O$261,"P4-S04",'Phase 04 OPD Journey'!$G$2:$G$261,"PASS") | E19: =COUNTIFS('Phase 04 OPD Journey'!$O$2:$O$261,"P4-S04",'Phase 04 OPD Journey'!$G$2:$G$261,"FAIL") | F19: =COUNTIF('Phase 04 OPD Journey'!$O$2:$O$261,"P4-S04")-COUNTIFS('Phase 04 OPD Journey'!$O$2:$O$261,"P4-S04",'Phase 04 OPD Journey'!$G$2:$G$261,"PASS")-COUNTIFS('Phase 04 OPD Journey'!$O$2:$O$261,"P4-S04",'Phase 04 OPD Journey'!$G$2:$G$261,"FAIL")-COUNTIFS('Phase 04 OPD Journey'!$O$2:$O$261,"P4-S04",'Phase 04 OPD Journey'!$G$2:$G$261,"BLOCKED") | G19: =IF(COUNTIFS('Phase 04 OPD Journey'!$O$2:$O$261,"P4-S04",'Phase 04 OPD Journey'!$G$2:$G$261,"FAIL")>0,"FAIL",IF(COUNTIFS('Phase 04 OPD Journey'!$O$2:$O$261,"P4-S04",'Phase 04 OPD Journey'!$G$2:$G$261,"PASS")=COUNTIF('Phase 04 OPD Journey'!$O$2:$O$261,"P4-S04"),"PASS",IF(COUNTIFS('Phase 04 OPD Journey'!$O$2:$O$261,"P4-S04",'Phase 04 OPD Journey'!$G$2:$G$261,"PASS")+COUNTIFS('Phase 04 OPD Journey'!$O$2:$O$261,"P4-S04",'Phase 04 OPD Journey'!$G$2:$G$261,"BLOCKED")>0,"IN PROGRESS","NOT STARTED")))
A20: P4-S05 | B20: Phase 04 OPD Journey | C20: =COUNTIF('Phase 04 OPD Journey'!$O$2:$O$261,"P4-S05") | D20: =COUNTIFS('Phase 04 OPD Journey'!$O$2:$O$261,"P4-S05",'Phase 04 OPD Journey'!$G$2:$G$261,"PASS") | E20: =COUNTIFS('Phase 04 OPD Journey'!$O$2:$O$261,"P4-S05",'Phase 04 OPD Journey'!$G$2:$G$261,"FAIL") | F20: =COUNTIF('Phase 04 OPD Journey'!$O$2:$O$261,"P4-S05")-COUNTIFS('Phase 04 OPD Journey'!$O$2:$O$261,"P4-S05",'Phase 04 OPD Journey'!$G$2:$G$261,"PASS")-COUNTIFS('Phase 04 OPD Journey'!$O$2:$O$261,"P4-S05",'Phase 04 OPD Journey'!$G$2:$G$261,"FAIL")-COUNTIFS('Phase 04 OPD Journey'!$O$2:$O$261,"P4-S05",'Phase 04 OPD Journey'!$G$2:$G$261,"BLOCKED") | G20: =IF(COUNTIFS('Phase 04 OPD Journey'!$O$2:$O$261,"P4-S05",'Phase 04 OPD Journey'!$G$2:$G$261,"FAIL")>0,"FAIL",IF(COUNTIFS('Phase 04 OPD Journey'!$O$2:$O$261,"P4-S05",'Phase 04 OPD Journey'!$G$2:$G$261,"PASS")=COUNTIF('Phase 04 OPD Journey'!$O$2:$O$261,"P4-S05"),"PASS",IF(COUNTIFS('Phase 04 OPD Journey'!$O$2:$O$261,"P4-S05",'Phase 04 OPD Journey'!$G$2:$G$261,"PASS")+COUNTIFS('Phase 04 OPD Journey'!$O$2:$O$261,"P4-S05",'Phase 04 OPD Journey'!$G$2:$G$261,"BLOCKED")>0,"IN PROGRESS","NOT STARTED")))
A21: P4-S06 | B21: Phase 04 OPD Journey | C21: =COUNTIF('Phase 04 OPD Journey'!$O$2:$O$261,"P4-S06") | D21: =COUNTIFS('Phase 04 OPD Journey'!$O$2:$O$261,"P4-S06",'Phase 04 OPD Journey'!$G$2:$G$261,"PASS") | E21: =COUNTIFS('Phase 04 OPD Journey'!$O$2:$O$261,"P4-S06",'Phase 04 OPD Journey'!$G$2:$G$261,"FAIL") | F21: =COUNTIF('Phase 04 OPD Journey'!$O$2:$O$261,"P4-S06")-COUNTIFS('Phase 04 OPD Journey'!$O$2:$O$261,"P4-S06",'Phase 04 OPD Journey'!$G$2:$G$261,"PASS")-COUNTIFS('Phase 04 OPD Journey'!$O$2:$O$261,"P4-S06",'Phase 04 OPD Journey'!$G$2:$G$261,"FAIL")-COUNTIFS('Phase 04 OPD Journey'!$O$2:$O$261,"P4-S06",'Phase 04 OPD Journey'!$G$2:$G$261,"BLOCKED") | G21: =IF(COUNTIFS('Phase 04 OPD Journey'!$O$2:$O$261,"P4-S06",'Phase 04 OPD Journey'!$G$2:$G$261,"FAIL")>0,"FAIL",IF(COUNTIFS('Phase 04 OPD Journey'!$O$2:$O$261,"P4-S06",'Phase 04 OPD Journey'!$G$2:$G$261,"PASS")=COUNTIF('Phase 04 OPD Journey'!$O$2:$O$261,"P4-S06"),"PASS",IF(COUNTIFS('Phase 04 OPD Journey'!$O$2:$O$261,"P4-S06",'Phase 04 OPD Journey'!$G$2:$G$261,"PASS")+COUNTIFS('Phase 04 OPD Journey'!$O$2:$O$261,"P4-S06",'Phase 04 OPD Journey'!$G$2:$G$261,"BLOCKED")>0,"IN PROGRESS","NOT STARTED")))
A22: P4-S07 | B22: Phase 04 OPD Journey | C22: =COUNTIF('Phase 04 OPD Journey'!$O$2:$O$261,"P4-S07") | D22: =COUNTIFS('Phase 04 OPD Journey'!$O$2:$O$261,"P4-S07",'Phase 04 OPD Journey'!$G$2:$G$261,"PASS") | E22: =COUNTIFS('Phase 04 OPD Journey'!$O$2:$O$261,"P4-S07",'Phase 04 OPD Journey'!$G$2:$G$261,"FAIL") | F22: =COUNTIF('Phase 04 OPD Journey'!$O$2:$O$261,"P4-S07")-COUNTIFS('Phase 04 OPD Journey'!$O$2:$O$261,"P4-S07",'Phase 04 OPD Journey'!$G$2:$G$261,"PASS")-COUNTIFS('Phase 04 OPD Journey'!$O$2:$O$261,"P4-S07",'Phase 04 OPD Journey'!$G$2:$G$261,"FAIL")-COUNTIFS('Phase 04 OPD Journey'!$O$2:$O$261,"P4-S07",'Phase 04 OPD Journey'!$G$2:$G$261,"BLOCKED") | G22: =IF(COUNTIFS('Phase 04 OPD Journey'!$O$2:$O$261,"P4-S07",'Phase 04 OPD Journey'!$G$2:$G$261,"FAIL")>0,"FAIL",IF(COUNTIFS('Phase 04 OPD Journey'!$O$2:$O$261,"P4-S07",'Phase 04 OPD Journey'!$G$2:$G$261,"PASS")=COUNTIF('Phase 04 OPD Journey'!$O$2:$O$261,"P4-S07"),"PASS",IF(COUNTIFS('Phase 04 OPD Journey'!$O$2:$O$261,"P4-S07",'Phase 04 OPD Journey'!$G$2:$G$261,"PASS")+COUNTIFS('Phase 04 OPD Journey'!$O$2:$O$261,"P4-S07",'Phase 04 OPD Journey'!$G$2:$G$261,"BLOCKED")>0,"IN PROGRESS","NOT STARTED")))
A23: P4-S08 | B23: Phase 04 OPD Journey | C23: =COUNTIF('Phase 04 OPD Journey'!$O$2:$O$261,"P4-S08") | D23: =COUNTIFS('Phase 04 OPD Journey'!$O$2:$O$261,"P4-S08",'Phase 04 OPD Journey'!$G$2:$G$261,"PASS") | E23: =COUNTIFS('Phase 04 OPD Journey'!$O$2:$O$261,"P4-S08",'Phase 04 OPD Journey'!$G$2:$G$261,"FAIL") | F23: =COUNTIF('Phase 04 OPD Journey'!$O$2:$O$261,"P4-S08")-COUNTIFS('Phase 04 OPD Journey'!$O$2:$O$261,"P4-S08",'Phase 04 OPD Journey'!$G$2:$G$261,"PASS")-COUNTIFS('Phase 04 OPD Journey'!$O$2:$O$261,"P4-S08",'Phase 04 OPD Journey'!$G$2:$G$261,"FAIL")-COUNTIFS('Phase 04 OPD Journey'!$O$2:$O$261,"P4-S08",'Phase 04 OPD Journey'!$G$2:$G$261,"BLOCKED") | G23: =IF(COUNTIFS('Phase 04 OPD Journey'!$O$2:$O$261,"P4-S08",'Phase 04 OPD Journey'!$G$2:$G$261,"FAIL")>0,"FAIL",IF(COUNTIFS('Phase 04 OPD Journey'!$O$2:$O$261,"P4-S08",'Phase 04 OPD Journey'!$G$2:$G$261,"PASS")=COUNTIF('Phase 04 OPD Journey'!$O$2:$O$261,"P4-S08"),"PASS",IF(COUNTIFS('Phase 04 OPD Journey'!$O$2:$O$261,"P4-S08",'Phase 04 OPD Journey'!$G$2:$G$261,"PASS")+COUNTIFS('Phase 04 OPD Journey'!$O$2:$O$261,"P4-S08",'Phase 04 OPD Journey'!$G$2:$G$261,"BLOCKED")>0,"IN PROGRESS","NOT STARTED")))
A24: P4-S09 | B24: Phase 04 OPD Journey | C24: =COUNTIF('Phase 04 OPD Journey'!$O$2:$O$261,"P4-S09") | D24: =COUNTIFS('Phase 04 OPD Journey'!$O$2:$O$261,"P4-S09",'Phase 04 OPD Journey'!$G$2:$G$261,"PASS") | E24: =COUNTIFS('Phase 04 OPD Journey'!$O$2:$O$261,"P4-S09",'Phase 04 OPD Journey'!$G$2:$G$261,"FAIL") | F24: =COUNTIF('Phase 04 OPD Journey'!$O$2:$O$261,"P4-S09")-COUNTIFS('Phase 04 OPD Journey'!$O$2:$O$261,"P4-S09",'Phase 04 OPD Journey'!$G$2:$G$261,"PASS")-COUNTIFS('Phase 04 OPD Journey'!$O$2:$O$261,"P4-S09",'Phase 04 OPD Journey'!$G$2:$G$261,"FAIL")-COUNTIFS('Phase 04 OPD Journey'!$O$2:$O$261,"P4-S09",'Phase 04 OPD Journey'!$G$2:$G$261,"BLOCKED") | G24: =IF(COUNTIFS('Phase 04 OPD Journey'!$O$2:$O$261,"P4-S09",'Phase 04 OPD Journey'!$G$2:$G$261,"FAIL")>0,"FAIL",IF(COUNTIFS('Phase 04 OPD Journey'!$O$2:$O$261,"P4-S09",'Phase 04 OPD Journey'!$G$2:$G$261,"PASS")=COUNTIF('Phase 04 OPD Journey'!$O$2:$O$261,"P4-S09"),"PASS",IF(COUNTIFS('Phase 04 OPD Journey'!$O$2:$O$261,"P4-S09",'Phase 04 OPD Journey'!$G$2:$G$261,"PASS")+COUNTIFS('Phase 04 OPD Journey'!$O$2:$O$261,"P4-S09",'Phase 04 OPD Journey'!$G$2:$G$261,"BLOCKED")>0,"IN PROGRESS","NOT STARTED")))
A25: P4-S10 | B25: Phase 04 OPD Journey | C25: =COUNTIF('Phase 04 OPD Journey'!$O$2:$O$261,"P4-S10") | D25: =COUNTIFS('Phase 04 OPD Journey'!$O$2:$O$261,"P4-S10",'Phase 04 OPD Journey'!$G$2:$G$261,"PASS") | E25: =COUNTIFS('Phase 04 OPD Journey'!$O$2:$O$261,"P4-S10",'Phase 04 OPD Journey'!$G$2:$G$261,"FAIL") | F25: =COUNTIF('Phase 04 OPD Journey'!$O$2:$O$261,"P4-S10")-COUNTIFS('Phase 04 OPD Journey'!$O$2:$O$261,"P4-S10",'Phase 04 OPD Journey'!$G$2:$G$261,"PASS")-COUNTIFS('Phase 04 OPD Journey'!$O$2:$O$261,"P4-S10",'Phase 04 OPD Journey'!$G$2:$G$261,"FAIL")-COUNTIFS('Phase 04 OPD Journey'!$O$2:$O$261,"P4-S10",'Phase 04 OPD Journey'!$G$2:$G$261,"BLOCKED") | G25: =IF(COUNTIFS('Phase 04 OPD Journey'!$O$2:$O$261,"P4-S10",'Phase 04 OPD Journey'!$G$2:$G$261,"FAIL")>0,"FAIL",IF(COUNTIFS('Phase 04 OPD Journey'!$O$2:$O$261,"P4-S10",'Phase 04 OPD Journey'!$G$2:$G$261,"PASS")=COUNTIF('Phase 04 OPD Journey'!$O$2:$O$261,"P4-S10"),"PASS",IF(COUNTIFS('Phase 04 OPD Journey'!$O$2:$O$261,"P4-S10",'Phase 04 OPD Journey'!$G$2:$G$261,"PASS")+COUNTIFS('Phase 04 OPD Journey'!$O$2:$O$261,"P4-S10",'Phase 04 OPD Journey'!$G$2:$G$261,"BLOCKED")>0,"IN PROGRESS","NOT STARTED")))
A26: P4-S11 | B26: Phase 04 OPD Journey | C26: =COUNTIF('Phase 04 OPD Journey'!$O$2:$O$261,"P4-S11") | D26: =COUNTIFS('Phase 04 OPD Journey'!$O$2:$O$261,"P4-S11",'Phase 04 OPD Journey'!$G$2:$G$261,"PASS") | E26: =COUNTIFS('Phase 04 OPD Journey'!$O$2:$O$261,"P4-S11",'Phase 04 OPD Journey'!$G$2:$G$261,"FAIL") | F26: =COUNTIF('Phase 04 OPD Journey'!$O$2:$O$261,"P4-S11")-COUNTIFS('Phase 04 OPD Journey'!$O$2:$O$261,"P4-S11",'Phase 04 OPD Journey'!$G$2:$G$261,"PASS")-COUNTIFS('Phase 04 OPD Journey'!$O$2:$O$261,"P4-S11",'Phase 04 OPD Journey'!$G$2:$G$261,"FAIL")-COUNTIFS('Phase 04 OPD Journey'!$O$2:$O$261,"P4-S11",'Phase 04 OPD Journey'!$G$2:$G$261,"BLOCKED") | G26: =IF(COUNTIFS('Phase 04 OPD Journey'!$O$2:$O$261,"P4-S11",'Phase 04 OPD Journey'!$G$2:$G$261,"FAIL")>0,"FAIL",IF(COUNTIFS('Phase 04 OPD Journey'!$O$2:$O$261,"P4-S11",'Phase 04 OPD Journey'!$G$2:$G$261,"PASS")=COUNTIF('Phase 04 OPD Journey'!$O$2:$O$261,"P4-S11"),"PASS",IF(COUNTIFS('Phase 04 OPD Journey'!$O$2:$O$261,"P4-S11",'Phase 04 OPD Journey'!$G$2:$G$261,"PASS")+COUNTIFS('Phase 04 OPD Journey'!$O$2:$O$261,"P4-S11",'Phase 04 OPD Journey'!$G$2:$G$261,"BLOCKED")>0,"IN PROGRESS","NOT STARTED")))
A27: P4-S12 | B27: Phase 04 OPD Journey | C27: =COUNTIF('Phase 04 OPD Journey'!$O$2:$O$261,"P4-S12") | D27: =COUNTIFS('Phase 04 OPD Journey'!$O$2:$O$261,"P4-S12",'Phase 04 OPD Journey'!$G$2:$G$261,"PASS") | E27: =COUNTIFS('Phase 04 OPD Journey'!$O$2:$O$261,"P4-S12",'Phase 04 OPD Journey'!$G$2:$G$261,"FAIL") | F27: =COUNTIF('Phase 04 OPD Journey'!$O$2:$O$261,"P4-S12")-COUNTIFS('Phase 04 OPD Journey'!$O$2:$O$261,"P4-S12",'Phase 04 OPD Journey'!$G$2:$G$261,"PASS")-COUNTIFS('Phase 04 OPD Journey'!$O$2:$O$261,"P4-S12",'Phase 04 OPD Journey'!$G$2:$G$261,"FAIL")-COUNTIFS('Phase 04 OPD Journey'!$O$2:$O$261,"P4-S12",'Phase 04 OPD Journey'!$G$2:$G$261,"BLOCKED") | G27: =IF(COUNTIFS('Phase 04 OPD Journey'!$O$2:$O$261,"P4-S12",'Phase 04 OPD Journey'!$G$2:$G$261,"FAIL")>0,"FAIL",IF(COUNTIFS('Phase 04 OPD Journey'!$O$2:$O$261,"P4-S12",'Phase 04 OPD Journey'!$G$2:$G$261,"PASS")=COUNTIF('Phase 04 OPD Journey'!$O$2:$O$261,"P4-S12"),"PASS",IF(COUNTIFS('Phase 04 OPD Journey'!$O$2:$O$261,"P4-S12",'Phase 04 OPD Journey'!$G$2:$G$261,"PASS")+COUNTIFS('Phase 04 OPD Journey'!$O$2:$O$261,"P4-S12",'Phase 04 OPD Journey'!$G$2:$G$261,"BLOCKED")>0,"IN PROGRESS","NOT STARTED")))
A28: P4-S13 | B28: Phase 04 OPD Journey | C28: =COUNTIF('Phase 04 OPD Journey'!$O$2:$O$261,"P4-S13") | D28: =COUNTIFS('Phase 04 OPD Journey'!$O$2:$O$261,"P4-S13",'Phase 04 OPD Journey'!$G$2:$G$261,"PASS") | E28: =COUNTIFS('Phase 04 OPD Journey'!$O$2:$O$261,"P4-S13",'Phase 04 OPD Journey'!$G$2:$G$261,"FAIL") | F28: =COUNTIF('Phase 04 OPD Journey'!$O$2:$O$261,"P4-S13")-COUNTIFS('Phase 04 OPD Journey'!$O$2:$O$261,"P4-S13",'Phase 04 OPD Journey'!$G$2:$G$261,"PASS")-COUNTIFS('Phase 04 OPD Journey'!$O$2:$O$261,"P4-S13",'Phase 04 OPD Journey'!$G$2:$G$261,"FAIL")-COUNTIFS('Phase 04 OPD Journey'!$O$2:$O$261,"P4-S13",'Phase 04 OPD Journey'!$G$2:$G$261,"BLOCKED") | G28: =IF(COUNTIFS('Phase 04 OPD Journey'!$O$2:$O$261,"P4-S13",'Phase 04 OPD Journey'!$G$2:$G$261,"FAIL")>0,"FAIL",IF(COUNTIFS('Phase 04 OPD Journey'!$O$2:$O$261,"P4-S13",'Phase 04 OPD Journey'!$G$2:$G$261,"PASS")=COUNTIF('Phase 04 OPD Journey'!$O$2:$O$261,"P4-S13"),"PASS",IF(COUNTIFS('Phase 04 OPD Journey'!$O$2:$O$261,"P4-S13",'Phase 04 OPD Journey'!$G$2:$G$261,"PASS")+COUNTIFS('Phase 04 OPD Journey'!$O$2:$O$261,"P4-S13",'Phase 04 OPD Journey'!$G$2:$G$261,"BLOCKED")>0,"IN PROGRESS","NOT STARTED")))
A29: P4-S14 | B29: Phase 04 OPD Journey | C29: =COUNTIF('Phase 04 OPD Journey'!$O$2:$O$261,"P4-S14") | D29: =COUNTIFS('Phase 04 OPD Journey'!$O$2:$O$261,"P4-S14",'Phase 04 OPD Journey'!$G$2:$G$261,"PASS") | E29: =COUNTIFS('Phase 04 OPD Journey'!$O$2:$O$261,"P4-S14",'Phase 04 OPD Journey'!$G$2:$G$261,"FAIL") | F29: =COUNTIF('Phase 04 OPD Journey'!$O$2:$O$261,"P4-S14")-COUNTIFS('Phase 04 OPD Journey'!$O$2:$O$261,"P4-S14",'Phase 04 OPD Journey'!$G$2:$G$261,"PASS")-COUNTIFS('Phase 04 OPD Journey'!$O$2:$O$261,"P4-S14",'Phase 04 OPD Journey'!$G$2:$G$261,"FAIL")-COUNTIFS('Phase 04 OPD Journey'!$O$2:$O$261,"P4-S14",'Phase 04 OPD Journey'!$G$2:$G$261,"BLOCKED") | G29: =IF(COUNTIFS('Phase 04 OPD Journey'!$O$2:$O$261,"P4-S14",'Phase 04 OPD Journey'!$G$2:$G$261,"FAIL")>0,"FAIL",IF(COUNTIFS('Phase 04 OPD Journey'!$O$2:$O$261,"P4-S14",'Phase 04 OPD Journey'!$G$2:$G$261,"PASS")=COUNTIF('Phase 04 OPD Journey'!$O$2:$O$261,"P4-S14"),"PASS",IF(COUNTIFS('Phase 04 OPD Journey'!$O$2:$O$261,"P4-S14",'Phase 04 OPD Journey'!$G$2:$G$261,"PASS")+COUNTIFS('Phase 04 OPD Journey'!$O$2:$O$261,"P4-S14",'Phase 04 OPD Journey'!$G$2:$G$261,"BLOCKED")>0,"IN PROGRESS","NOT STARTED")))
A30: P4-S15 | B30: Phase 04 OPD Journey | C30: =COUNTIF('Phase 04 OPD Journey'!$O$2:$O$261,"P4-S15") | D30: =COUNTIFS('Phase 04 OPD Journey'!$O$2:$O$261,"P4-S15",'Phase 04 OPD Journey'!$G$2:$G$261,"PASS") | E30: =COUNTIFS('Phase 04 OPD Journey'!$O$2:$O$261,"P4-S15",'Phase 04 OPD Journey'!$G$2:$G$261,"FAIL") | F30: =COUNTIF('Phase 04 OPD Journey'!$O$2:$O$261,"P4-S15")-COUNTIFS('Phase 04 OPD Journey'!$O$2:$O$261,"P4-S15",'Phase 04 OPD Journey'!$G$2:$G$261,"PASS")-COUNTIFS('Phase 04 OPD Journey'!$O$2:$O$261,"P4-S15",'Phase 04 OPD Journey'!$G$2:$G$261,"FAIL")-COUNTIFS('Phase 04 OPD Journey'!$O$2:$O$261,"P4-S15",'Phase 04 OPD Journey'!$G$2:$G$261,"BLOCKED") | G30: =IF(COUNTIFS('Phase 04 OPD Journey'!$O$2:$O$261,"P4-S15",'Phase 04 OPD Journey'!$G$2:$G$261,"FAIL")>0,"FAIL",IF(COUNTIFS('Phase 04 OPD Journey'!$O$2:$O$261,"P4-S15",'Phase 04 OPD Journey'!$G$2:$G$261,"PASS")=COUNTIF('Phase 04 OPD Journey'!$O$2:$O$261,"P4-S15"),"PASS",IF(COUNTIFS('Phase 04 OPD Journey'!$O$2:$O$261,"P4-S15",'Phase 04 OPD Journey'!$G$2:$G$261,"PASS")+COUNTIFS('Phase 04 OPD Journey'!$O$2:$O$261,"P4-S15",'Phase 04 OPD Journey'!$G$2:$G$261,"BLOCKED")>0,"IN PROGRESS","NOT STARTED")))
A31: P4-S16 | B31: Phase 04 OPD Journey | C31: =COUNTIF('Phase 04 OPD Journey'!$O$2:$O$261,"P4-S16") | D31: =COUNTIFS('Phase 04 OPD Journey'!$O$2:$O$261,"P4-S16",'Phase 04 OPD Journey'!$G$2:$G$261,"PASS") | E31: =COUNTIFS('Phase 04 OPD Journey'!$O$2:$O$261,"P4-S16",'Phase 04 OPD Journey'!$G$2:$G$261,"FAIL") | F31: =COUNTIF('Phase 04 OPD Journey'!$O$2:$O$261,"P4-S16")-COUNTIFS('Phase 04 OPD Journey'!$O$2:$O$261,"P4-S16",'Phase 04 OPD Journey'!$G$2:$G$261,"PASS")-COUNTIFS('Phase 04 OPD Journey'!$O$2:$O$261,"P4-S16",'Phase 04 OPD Journey'!$G$2:$G$261,"FAIL")-COUNTIFS('Phase 04 OPD Journey'!$O$2:$O$261,"P4-S16",'Phase 04 OPD Journey'!$G$2:$G$261,"BLOCKED") | G31: =IF(COUNTIFS('Phase 04 OPD Journey'!$O$2:$O$261,"P4-S16",'Phase 04 OPD Journey'!$G$2:$G$261,"FAIL")>0,"FAIL",IF(COUNTIFS('Phase 04 OPD Journey'!$O$2:$O$261,"P4-S16",'Phase 04 OPD Journey'!$G$2:$G$261,"PASS")=COUNTIF('Phase 04 OPD Journey'!$O$2:$O$261,"P4-S16"),"PASS",IF(COUNTIFS('Phase 04 OPD Journey'!$O$2:$O$261,"P4-S16",'Phase 04 OPD Journey'!$G$2:$G$261,"PASS")+COUNTIFS('Phase 04 OPD Journey'!$O$2:$O$261,"P4-S16",'Phase 04 OPD Journey'!$G$2:$G$261,"BLOCKED")>0,"IN PROGRESS","NOT STARTED")))
A32: P4-S17 | B32: Phase 04 OPD Journey | C32: =COUNTIF('Phase 04 OPD Journey'!$O$2:$O$261,"P4-S17") | D32: =COUNTIFS('Phase 04 OPD Journey'!$O$2:$O$261,"P4-S17",'Phase 04 OPD Journey'!$G$2:$G$261,"PASS") | E32: =COUNTIFS('Phase 04 OPD Journey'!$O$2:$O$261,"P4-S17",'Phase 04 OPD Journey'!$G$2:$G$261,"FAIL") | F32: =COUNTIF('Phase 04 OPD Journey'!$O$2:$O$261,"P4-S17")-COUNTIFS('Phase 04 OPD Journey'!$O$2:$O$261,"P4-S17",'Phase 04 OPD Journey'!$G$2:$G$261,"PASS")-COUNTIFS('Phase 04 OPD Journey'!$O$2:$O$261,"P4-S17",'Phase 04 OPD Journey'!$G$2:$G$261,"FAIL")-COUNTIFS('Phase 04 OPD Journey'!$O$2:$O$261,"P4-S17",'Phase 04 OPD Journey'!$G$2:$G$261,"BLOCKED") | G32: =IF(COUNTIFS('Phase 04 OPD Journey'!$O$2:$O$261,"P4-S17",'Phase 04 OPD Journey'!$G$2:$G$261,"FAIL")>0,"FAIL",IF(COUNTIFS('Phase 04 OPD Journey'!$O$2:$O$261,"P4-S17",'Phase 04 OPD Journey'!$G$2:$G$261,"PASS")=COUNTIF('Phase 04 OPD Journey'!$O$2:$O$261,"P4-S17"),"PASS",IF(COUNTIFS('Phase 04 OPD Journey'!$O$2:$O$261,"P4-S17",'Phase 04 OPD Journey'!$G$2:$G$261,"PASS")+COUNTIFS('Phase 04 OPD Journey'!$O$2:$O$261,"P4-S17",'Phase 04 OPD Journey'!$G$2:$G$261,"BLOCKED")>0,"IN PROGRESS","NOT STARTED")))
A33: P4-S18 | B33: Phase 04 OPD Journey | C33: =COUNTIF('Phase 04 OPD Journey'!$O$2:$O$261,"P4-S18") | D33: =COUNTIFS('Phase 04 OPD Journey'!$O$2:$O$261,"P4-S18",'Phase 04 OPD Journey'!$G$2:$G$261,"PASS") | E33: =COUNTIFS('Phase 04 OPD Journey'!$O$2:$O$261,"P4-S18",'Phase 04 OPD Journey'!$G$2:$G$261,"FAIL") | F33: =COUNTIF('Phase 04 OPD Journey'!$O$2:$O$261,"P4-S18")-COUNTIFS('Phase 04 OPD Journey'!$O$2:$O$261,"P4-S18",'Phase 04 OPD Journey'!$G$2:$G$261,"PASS")-COUNTIFS('Phase 04 OPD Journey'!$O$2:$O$261,"P4-S18",'Phase 04 OPD Journey'!$G$2:$G$261,"FAIL")-COUNTIFS('Phase 04 OPD Journey'!$O$2:$O$261,"P4-S18",'Phase 04 OPD Journey'!$G$2:$G$261,"BLOCKED") | G33: =IF(COUNTIFS('Phase 04 OPD Journey'!$O$2:$O$261,"P4-S18",'Phase 04 OPD Journey'!$G$2:$G$261,"FAIL")>0,"FAIL",IF(COUNTIFS('Phase 04 OPD Journey'!$O$2:$O$261,"P4-S18",'Phase 04 OPD Journey'!$G$2:$G$261,"PASS")=COUNTIF('Phase 04 OPD Journey'!$O$2:$O$261,"P4-S18"),"PASS",IF(COUNTIFS('Phase 04 OPD Journey'!$O$2:$O$261,"P4-S18",'Phase 04 OPD Journey'!$G$2:$G$261,"PASS")+COUNTIFS('Phase 04 OPD Journey'!$O$2:$O$261,"P4-S18",'Phase 04 OPD Journey'!$G$2:$G$261,"BLOCKED")>0,"IN PROGRESS","NOT STARTED")))
A34: P4-S19 | B34: Phase 04 OPD Journey | C34: =COUNTIF('Phase 04 OPD Journey'!$O$2:$O$261,"P4-S19") | D34: =COUNTIFS('Phase 04 OPD Journey'!$O$2:$O$261,"P4-S19",'Phase 04 OPD Journey'!$G$2:$G$261,"PASS") | E34: =COUNTIFS('Phase 04 OPD Journey'!$O$2:$O$261,"P4-S19",'Phase 04 OPD Journey'!$G$2:$G$261,"FAIL") | F34: =COUNTIF('Phase 04 OPD Journey'!$O$2:$O$261,"P4-S19")-COUNTIFS('Phase 04 OPD Journey'!$O$2:$O$261,"P4-S19",'Phase 04 OPD Journey'!$G$2:$G$261,"PASS")-COUNTIFS('Phase 04 OPD Journey'!$O$2:$O$261,"P4-S19",'Phase 04 OPD Journey'!$G$2:$G$261,"FAIL")-COUNTIFS('Phase 04 OPD Journey'!$O$2:$O$261,"P4-S19",'Phase 04 OPD Journey'!$G$2:$G$261,"BLOCKED") | G34: =IF(COUNTIFS('Phase 04 OPD Journey'!$O$2:$O$261,"P4-S19",'Phase 04 OPD Journey'!$G$2:$G$261,"FAIL")>0,"FAIL",IF(COUNTIFS('Phase 04 OPD Journey'!$O$2:$O$261,"P4-S19",'Phase 04 OPD Journey'!$G$2:$G$261,"PASS")=COUNTIF('Phase 04 OPD Journey'!$O$2:$O$261,"P4-S19"),"PASS",IF(COUNTIFS('Phase 04 OPD Journey'!$O$2:$O$261,"P4-S19",'Phase 04 OPD Journey'!$G$2:$G$261,"PASS")+COUNTIFS('Phase 04 OPD Journey'!$O$2:$O$261,"P4-S19",'Phase 04 OPD Journey'!$G$2:$G$261,"BLOCKED")>0,"IN PROGRESS","NOT STARTED")))
A35: P4-S20 | B35: Phase 04 OPD Journey | C35: =COUNTIF('Phase 04 OPD Journey'!$O$2:$O$261,"P4-S20") | D35: =COUNTIFS('Phase 04 OPD Journey'!$O$2:$O$261,"P4-S20",'Phase 04 OPD Journey'!$G$2:$G$261,"PASS") | E35: =COUNTIFS('Phase 04 OPD Journey'!$O$2:$O$261,"P4-S20",'Phase 04 OPD Journey'!$G$2:$G$261,"FAIL") | F35: =COUNTIF('Phase 04 OPD Journey'!$O$2:$O$261,"P4-S20")-COUNTIFS('Phase 04 OPD Journey'!$O$2:$O$261,"P4-S20",'Phase 04 OPD Journey'!$G$2:$G$261,"PASS")-COUNTIFS('Phase 04 OPD Journey'!$O$2:$O$261,"P4-S20",'Phase 04 OPD Journey'!$G$2:$G$261,"FAIL")-COUNTIFS('Phase 04 OPD Journey'!$O$2:$O$261,"P4-S20",'Phase 04 OPD Journey'!$G$2:$G$261,"BLOCKED") | G35: =IF(COUNTIFS('Phase 04 OPD Journey'!$O$2:$O$261,"P4-S20",'Phase 04 OPD Journey'!$G$2:$G$261,"FAIL")>0,"FAIL",IF(COUNTIFS('Phase 04 OPD Journey'!$O$2:$O$261,"P4-S20",'Phase 04 OPD Journey'!$G$2:$G$261,"PASS")=COUNTIF('Phase 04 OPD Journey'!$O$2:$O$261,"P4-S20"),"PASS",IF(COUNTIFS('Phase 04 OPD Journey'!$O$2:$O$261,"P4-S20",'Phase 04 OPD Journey'!$G$2:$G$261,"PASS")+COUNTIFS('Phase 04 OPD Journey'!$O$2:$O$261,"P4-S20",'Phase 04 OPD Journey'!$G$2:$G$261,"BLOCKED")>0,"IN PROGRESS","NOT STARTED")))
A36: P4-S21 | B36: Phase 04 OPD Journey | C36: =COUNTIF('Phase 04 OPD Journey'!$O$2:$O$261,"P4-S21") | D36: =COUNTIFS('Phase 04 OPD Journey'!$O$2:$O$261,"P4-S21",'Phase 04 OPD Journey'!$G$2:$G$261,"PASS") | E36: =COUNTIFS('Phase 04 OPD Journey'!$O$2:$O$261,"P4-S21",'Phase 04 OPD Journey'!$G$2:$G$261,"FAIL") | F36: =COUNTIF('Phase 04 OPD Journey'!$O$2:$O$261,"P4-S21")-COUNTIFS('Phase 04 OPD Journey'!$O$2:$O$261,"P4-S21",'Phase 04 OPD Journey'!$G$2:$G$261,"PASS")-COUNTIFS('Phase 04 OPD Journey'!$O$2:$O$261,"P4-S21",'Phase 04 OPD Journey'!$G$2:$G$261,"FAIL")-COUNTIFS('Phase 04 OPD Journey'!$O$2:$O$261,"P4-S21",'Phase 04 OPD Journey'!$G$2:$G$261,"BLOCKED") | G36: =IF(COUNTIFS('Phase 04 OPD Journey'!$O$2:$O$261,"P4-S21",'Phase 04 OPD Journey'!$G$2:$G$261,"FAIL")>0,"FAIL",IF(COUNTIFS('Phase 04 OPD Journey'!$O$2:$O$261,"P4-S21",'Phase 04 OPD Journey'!$G$2:$G$261,"PASS")=COUNTIF('Phase 04 OPD Journey'!$O$2:$O$261,"P4-S21"),"PASS",IF(COUNTIFS('Phase 04 OPD Journey'!$O$2:$O$261,"P4-S21",'Phase 04 OPD Journey'!$G$2:$G$261,"PASS")+COUNTIFS('Phase 04 OPD Journey'!$O$2:$O$261,"P4-S21",'Phase 04 OPD Journey'!$G$2:$G$261,"BLOCKED")>0,"IN PROGRESS","NOT STARTED")))
A37: P4-S22 | B37: Phase 04 OPD Journey | C37: =COUNTIF('Phase 04 OPD Journey'!$O$2:$O$261,"P4-S22") | D37: =COUNTIFS('Phase 04 OPD Journey'!$O$2:$O$261,"P4-S22",'Phase 04 OPD Journey'!$G$2:$G$261,"PASS") | E37: =COUNTIFS('Phase 04 OPD Journey'!$O$2:$O$261,"P4-S22",'Phase 04 OPD Journey'!$G$2:$G$261,"FAIL") | F37: =COUNTIF('Phase 04 OPD Journey'!$O$2:$O$261,"P4-S22")-COUNTIFS('Phase 04 OPD Journey'!$O$2:$O$261,"P4-S22",'Phase 04 OPD Journey'!$G$2:$G$261,"PASS")-COUNTIFS('Phase 04 OPD Journey'!$O$2:$O$261,"P4-S22",'Phase 04 OPD Journey'!$G$2:$G$261,"FAIL")-COUNTIFS('Phase 04 OPD Journey'!$O$2:$O$261,"P4-S22",'Phase 04 OPD Journey'!$G$2:$G$261,"BLOCKED") | G37: =IF(COUNTIFS('Phase 04 OPD Journey'!$O$2:$O$261,"P4-S22",'Phase 04 OPD Journey'!$G$2:$G$261,"FAIL")>0,"FAIL",IF(COUNTIFS('Phase 04 OPD Journey'!$O$2:$O$261,"P4-S22",'Phase 04 OPD Journey'!$G$2:$G$261,"PASS")=COUNTIF('Phase 04 OPD Journey'!$O$2:$O$261,"P4-S22"),"PASS",IF(COUNTIFS('Phase 04 OPD Journey'!$O$2:$O$261,"P4-S22",'Phase 04 OPD Journey'!$G$2:$G$261,"PASS")+COUNTIFS('Phase 04 OPD Journey'!$O$2:$O$261,"P4-S22",'Phase 04 OPD Journey'!$G$2:$G$261,"BLOCKED")>0,"IN PROGRESS","NOT STARTED")))
A38: P4-S23 | B38: Phase 04 OPD Journey | C38: =COUNTIF('Phase 04 OPD Journey'!$O$2:$O$261,"P4-S23") | D38: =COUNTIFS('Phase 04 OPD Journey'!$O$2:$O$261,"P4-S23",'Phase 04 OPD Journey'!$G$2:$G$261,"PASS") | E38: =COUNTIFS('Phase 04 OPD Journey'!$O$2:$O$261,"P4-S23",'Phase 04 OPD Journey'!$G$2:$G$261,"FAIL") | F38: =COUNTIF('Phase 04 OPD Journey'!$O$2:$O$261,"P4-S23")-COUNTIFS('Phase 04 OPD Journey'!$O$2:$O$261,"P4-S23",'Phase 04 OPD Journey'!$G$2:$G$261,"PASS")-COUNTIFS('Phase 04 OPD Journey'!$O$2:$O$261,"P4-S23",'Phase 04 OPD Journey'!$G$2:$G$261,"FAIL")-COUNTIFS('Phase 04 OPD Journey'!$O$2:$O$261,"P4-S23",'Phase 04 OPD Journey'!$G$2:$G$261,"BLOCKED") | G38: =IF(COUNTIFS('Phase 04 OPD Journey'!$O$2:$O$261,"P4-S23",'Phase 04 OPD Journey'!$G$2:$G$261,"FAIL")>0,"FAIL",IF(COUNTIFS('Phase 04 OPD Journey'!$O$2:$O$261,"P4-S23",'Phase 04 OPD Journey'!$G$2:$G$261,"PASS")=COUNTIF('Phase 04 OPD Journey'!$O$2:$O$261,"P4-S23"),"PASS",IF(COUNTIFS('Phase 04 OPD Journey'!$O$2:$O$261,"P4-S23",'Phase 04 OPD Journey'!$G$2:$G$261,"PASS")+COUNTIFS('Phase 04 OPD Journey'!$O$2:$O$261,"P4-S23",'Phase 04 OPD Journey'!$G$2:$G$261,"BLOCKED")>0,"IN PROGRESS","NOT STARTED")))
A39: P4-S24 | B39: Phase 04 OPD Journey | C39: =COUNTIF('Phase 04 OPD Journey'!$O$2:$O$261,"P4-S24") | D39: =COUNTIFS('Phase 04 OPD Journey'!$O$2:$O$261,"P4-S24",'Phase 04 OPD Journey'!$G$2:$G$261,"PASS") | E39: =COUNTIFS('Phase 04 OPD Journey'!$O$2:$O$261,"P4-S24",'Phase 04 OPD Journey'!$G$2:$G$261,"FAIL") | F39: =COUNTIF('Phase 04 OPD Journey'!$O$2:$O$261,"P4-S24")-COUNTIFS('Phase 04 OPD Journey'!$O$2:$O$261,"P4-S24",'Phase 04 OPD Journey'!$G$2:$G$261,"PASS")-COUNTIFS('Phase 04 OPD Journey'!$O$2:$O$261,"P4-S24",'Phase 04 OPD Journey'!$G$2:$G$261,"FAIL")-COUNTIFS('Phase 04 OPD Journey'!$O$2:$O$261,"P4-S24",'Phase 04 OPD Journey'!$G$2:$G$261,"BLOCKED") | G39: =IF(COUNTIFS('Phase 04 OPD Journey'!$O$2:$O$261,"P4-S24",'Phase 04 OPD Journey'!$G$2:$G$261,"FAIL")>0,"FAIL",IF(COUNTIFS('Phase 04 OPD Journey'!$O$2:$O$261,"P4-S24",'Phase 04 OPD Journey'!$G$2:$G$261,"PASS")=COUNTIF('Phase 04 OPD Journey'!$O$2:$O$261,"P4-S24"),"PASS",IF(COUNTIFS('Phase 04 OPD Journey'!$O$2:$O$261,"P4-S24",'Phase 04 OPD Journey'!$G$2:$G$261,"PASS")+COUNTIFS('Phase 04 OPD Journey'!$O$2:$O$261,"P4-S24",'Phase 04 OPD Journey'!$G$2:$G$261,"BLOCKED")>0,"IN PROGRESS","NOT STARTED")))
A40: P5-S01 | B40: Phase 05 Lab & Radiology | C40: =COUNTIF('Phase 05 Lab & Radiology'!$O$2:$O$25,"P5-S01") | D40: =COUNTIFS('Phase 05 Lab & Radiology'!$O$2:$O$25,"P5-S01",'Phase 05 Lab & Radiology'!$G$2:$G$25,"PASS") | E40: =COUNTIFS('Phase 05 Lab & Radiology'!$O$2:$O$25,"P5-S01",'Phase 05 Lab & Radiology'!$G$2:$G$25,"FAIL") | F40: =COUNTIF('Phase 05 Lab & Radiology'!$O$2:$O$25,"P5-S01")-COUNTIFS('Phase 05 Lab & Radiology'!$O$2:$O$25,"P5-S01",'Phase 05 Lab & Radiology'!$G$2:$G$25,"PASS")-COUNTIFS('Phase 05 Lab & Radiology'!$O$2:$O$25,"P5-S01",'Phase 05 Lab & Radiology'!$G$2:$G$25,"FAIL")-COUNTIFS('Phase 05 Lab & Radiology'!$O$2:$O$25,"P5-S01",'Phase 05 Lab & Radiology'!$G$2:$G$25,"BLOCKED") | G40: =IF(COUNTIFS('Phase 05 Lab & Radiology'!$O$2:$O$25,"P5-S01",'Phase 05 Lab & Radiology'!$G$2:$G$25,"FAIL")>0,"FAIL",IF(COUNTIFS('Phase 05 Lab & Radiology'!$O$2:$O$25,"P5-S01",'Phase 05 Lab & Radiology'!$G$2:$G$25,"PASS")=COUNTIF('Phase 05 Lab & Radiology'!$O$2:$O$25,"P5-S01"),"PASS",IF(COUNTIFS('Phase 05 Lab & Radiology'!$O$2:$O$25,"P5-S01",'Phase 05 Lab & Radiology'!$G$2:$G$25,"PASS")+COUNTIFS('Phase 05 Lab & Radiology'!$O$2:$O$25,"P5-S01",'Phase 05 Lab & Radiology'!$G$2:$G$25,"BLOCKED")>0,"IN PROGRESS","NOT STARTED")))
A41: P5-S02 | B41: Phase 05 Lab & Radiology | C41: =COUNTIF('Phase 05 Lab & Radiology'!$O$2:$O$25,"P5-S02") | D41: =COUNTIFS('Phase 05 Lab & Radiology'!$O$2:$O$25,"P5-S02",'Phase 05 Lab & Radiology'!$G$2:$G$25,"PASS") | E41: =COUNTIFS('Phase 05 Lab & Radiology'!$O$2:$O$25,"P5-S02",'Phase 05 Lab & Radiology'!$G$2:$G$25,"FAIL") | F41: =COUNTIF('Phase 05 Lab & Radiology'!$O$2:$O$25,"P5-S02")-COUNTIFS('Phase 05 Lab & Radiology'!$O$2:$O$25,"P5-S02",'Phase 05 Lab & Radiology'!$G$2:$G$25,"PASS")-COUNTIFS('Phase 05 Lab & Radiology'!$O$2:$O$25,"P5-S02",'Phase 05 Lab & Radiology'!$G$2:$G$25,"FAIL")-COUNTIFS('Phase 05 Lab & Radiology'!$O$2:$O$25,"P5-S02",'Phase 05 Lab & Radiology'!$G$2:$G$25,"BLOCKED") | G41: =IF(COUNTIFS('Phase 05 Lab & Radiology'!$O$2:$O$25,"P5-S02",'Phase 05 Lab & Radiology'!$G$2:$G$25,"FAIL")>0,"FAIL",IF(COUNTIFS('Phase 05 Lab & Radiology'!$O$2:$O$25,"P5-S02",'Phase 05 Lab & Radiology'!$G$2:$G$25,"PASS")=COUNTIF('Phase 05 Lab & Radiology'!$O$2:$O$25,"P5-S02"),"PASS",IF(COUNTIFS('Phase 05 Lab & Radiology'!$O$2:$O$25,"P5-S02",'Phase 05 Lab & Radiology'!$G$2:$G$25,"PASS")+COUNTIFS('Phase 05 Lab & Radiology'!$O$2:$O$25,"P5-S02",'Phase 05 Lab & Radiology'!$G$2:$G$25,"BLOCKED")>0,"IN PROGRESS","NOT STARTED")))
A42: P5-S03 | B42: Phase 05 Lab & Radiology | C42: =COUNTIF('Phase 05 Lab & Radiology'!$O$2:$O$25,"P5-S03") | D42: =COUNTIFS('Phase 05 Lab & Radiology'!$O$2:$O$25,"P5-S03",'Phase 05 Lab & Radiology'!$G$2:$G$25,"PASS") | E42: =COUNTIFS('Phase 05 Lab & Radiology'!$O$2:$O$25,"P5-S03",'Phase 05 Lab & Radiology'!$G$2:$G$25,"FAIL") | F42: =COUNTIF('Phase 05 Lab & Radiology'!$O$2:$O$25,"P5-S03")-COUNTIFS('Phase 05 Lab & Radiology'!$O$2:$O$25,"P5-S03",'Phase 05 Lab & Radiology'!$G$2:$G$25,"PASS")-COUNTIFS('Phase 05 Lab & Radiology'!$O$2:$O$25,"P5-S03",'Phase 05 Lab & Radiology'!$G$2:$G$25,"FAIL")-COUNTIFS('Phase 05 Lab & Radiology'!$O$2:$O$25,"P5-S03",'Phase 05 Lab & Radiology'!$G$2:$G$25,"BLOCKED") | G42: =IF(COUNTIFS('Phase 05 Lab & Radiology'!$O$2:$O$25,"P5-S03",'Phase 05 Lab & Radiology'!$G$2:$G$25,"FAIL")>0,"FAIL",IF(COUNTIFS('Phase 05 Lab & Radiology'!$O$2:$O$25,"P5-S03",'Phase 05 Lab & Radiology'!$G$2:$G$25,"PASS")=COUNTIF('Phase 05 Lab & Radiology'!$O$2:$O$25,"P5-S03"),"PASS",IF(COUNTIFS('Phase 05 Lab & Radiology'!$O$2:$O$25,"P5-S03",'Phase 05 Lab & Radiology'!$G$2:$G$25,"PASS")+COUNTIFS('Phase 05 Lab & Radiology'!$O$2:$O$25,"P5-S03",'Phase 05 Lab & Radiology'!$G$2:$G$25,"BLOCKED")>0,"IN PROGRESS","NOT STARTED")))
A43: P5-S04 | B43: Phase 05 Lab & Radiology | C43: =COUNTIF('Phase 05 Lab & Radiology'!$O$2:$O$25,"P5-S04") | D43: =COUNTIFS('Phase 05 Lab & Radiology'!$O$2:$O$25,"P5-S04",'Phase 05 Lab & Radiology'!$G$2:$G$25,"PASS") | E43: =COUNTIFS('Phase 05 Lab & Radiology'!$O$2:$O$25,"P5-S04",'Phase 05 Lab & Radiology'!$G$2:$G$25,"FAIL") | F43: =COUNTIF('Phase 05 Lab & Radiology'!$O$2:$O$25,"P5-S04")-COUNTIFS('Phase 05 Lab & Radiology'!$O$2:$O$25,"P5-S04",'Phase 05 Lab & Radiology'!$G$2:$G$25,"PASS")-COUNTIFS('Phase 05 Lab & Radiology'!$O$2:$O$25,"P5-S04",'Phase 05 Lab & Radiology'!$G$2:$G$25,"FAIL")-COUNTIFS('Phase 05 Lab & Radiology'!$O$2:$O$25,"P5-S04",'Phase 05 Lab & Radiology'!$G$2:$G$25,"BLOCKED") | G43: =IF(COUNTIFS('Phase 05 Lab & Radiology'!$O$2:$O$25,"P5-S04",'Phase 05 Lab & Radiology'!$G$2:$G$25,"FAIL")>0,"FAIL",IF(COUNTIFS('Phase 05 Lab & Radiology'!$O$2:$O$25,"P5-S04",'Phase 05 Lab & Radiology'!$G$2:$G$25,"PASS")=COUNTIF('Phase 05 Lab & Radiology'!$O$2:$O$25,"P5-S04"),"PASS",IF(COUNTIFS('Phase 05 Lab & Radiology'!$O$2:$O$25,"P5-S04",'Phase 05 Lab & Radiology'!$G$2:$G$25,"PASS")+COUNTIFS('Phase 05 Lab & Radiology'!$O$2:$O$25,"P5-S04",'Phase 05 Lab & Radiology'!$G$2:$G$25,"BLOCKED")>0,"IN PROGRESS","NOT STARTED")))
A44: P5-S05 | B44: Phase 05 Lab & Radiology | C44: =COUNTIF('Phase 05 Lab & Radiology'!$O$2:$O$25,"P5-S05") | D44: =COUNTIFS('Phase 05 Lab & Radiology'!$O$2:$O$25,"P5-S05",'Phase 05 Lab & Radiology'!$G$2:$G$25,"PASS") | E44: =COUNTIFS('Phase 05 Lab & Radiology'!$O$2:$O$25,"P5-S05",'Phase 05 Lab & Radiology'!$G$2:$G$25,"FAIL") | F44: =COUNTIF('Phase 05 Lab & Radiology'!$O$2:$O$25,"P5-S05")-COUNTIFS('Phase 05 Lab & Radiology'!$O$2:$O$25,"P5-S05",'Phase 05 Lab & Radiology'!$G$2:$G$25,"PASS")-COUNTIFS('Phase 05 Lab & Radiology'!$O$2:$O$25,"P5-S05",'Phase 05 Lab & Radiology'!$G$2:$G$25,"FAIL")-COUNTIFS('Phase 05 Lab & Radiology'!$O$2:$O$25,"P5-S05",'Phase 05 Lab & Radiology'!$G$2:$G$25,"BLOCKED") | G44: =IF(COUNTIFS('Phase 05 Lab & Radiology'!$O$2:$O$25,"P5-S05",'Phase 05 Lab & Radiology'!$G$2:$G$25,"FAIL")>0,"FAIL",IF(COUNTIFS('Phase 05 Lab & Radiology'!$O$2:$O$25,"P5-S05",'Phase 05 Lab & Radiology'!$G$2:$G$25,"PASS")=COUNTIF('Phase 05 Lab & Radiology'!$O$2:$O$25,"P5-S05"),"PASS",IF(COUNTIFS('Phase 05 Lab & Radiology'!$O$2:$O$25,"P5-S05",'Phase 05 Lab & Radiology'!$G$2:$G$25,"PASS")+COUNTIFS('Phase 05 Lab & Radiology'!$O$2:$O$25,"P5-S05",'Phase 05 Lab & Radiology'!$G$2:$G$25,"BLOCKED")>0,"IN PROGRESS","NOT STARTED")))
A45: P5-S06 | B45: Phase 05 Lab & Radiology | C45: =COUNTIF('Phase 05 Lab & Radiology'!$O$2:$O$25,"P5-S06") | D45: =COUNTIFS('Phase 05 Lab & Radiology'!$O$2:$O$25,"P5-S06",'Phase 05 Lab & Radiology'!$G$2:$G$25,"PASS") | E45: =COUNTIFS('Phase 05 Lab & Radiology'!$O$2:$O$25,"P5-S06",'Phase 05 Lab & Radiology'!$G$2:$G$25,"FAIL") | F45: =COUNTIF('Phase 05 Lab & Radiology'!$O$2:$O$25,"P5-S06")-COUNTIFS('Phase 05 Lab & Radiology'!$O$2:$O$25,"P5-S06",'Phase 05 Lab & Radiology'!$G$2:$G$25,"PASS")-COUNTIFS('Phase 05 Lab & Radiology'!$O$2:$O$25,"P5-S06",'Phase 05 Lab & Radiology'!$G$2:$G$25,"FAIL")-COUNTIFS('Phase 05 Lab & Radiology'!$O$2:$O$25,"P5-S06",'Phase 05 Lab & Radiology'!$G$2:$G$25,"BLOCKED") | G45: =IF(COUNTIFS('Phase 05 Lab & Radiology'!$O$2:$O$25,"P5-S06",'Phase 05 Lab & Radiology'!$G$2:$G$25,"FAIL")>0,"FAIL",IF(COUNTIFS('Phase 05 Lab & Radiology'!$O$2:$O$25,"P5-S06",'Phase 05 Lab & Radiology'!$G$2:$G$25,"PASS")=COUNTIF('Phase 05 Lab & Radiology'!$O$2:$O$25,"P5-S06"),"PASS",IF(COUNTIFS('Phase 05 Lab & Radiology'!$O$2:$O$25,"P5-S06",'Phase 05 Lab & Radiology'!$G$2:$G$25,"PASS")+COUNTIFS('Phase 05 Lab & Radiology'!$O$2:$O$25,"P5-S06",'Phase 05 Lab & Radiology'!$G$2:$G$25,"BLOCKED")>0,"IN PROGRESS","NOT STARTED")))
A46: P5-S07 | B46: Phase 05 Lab & Radiology | C46: =COUNTIF('Phase 05 Lab & Radiology'!$O$2:$O$25,"P5-S07") | D46: =COUNTIFS('Phase 05 Lab & Radiology'!$O$2:$O$25,"P5-S07",'Phase 05 Lab & Radiology'!$G$2:$G$25,"PASS") | E46: =COUNTIFS('Phase 05 Lab & Radiology'!$O$2:$O$25,"P5-S07",'Phase 05 Lab & Radiology'!$G$2:$G$25,"FAIL") | F46: =COUNTIF('Phase 05 Lab & Radiology'!$O$2:$O$25,"P5-S07")-COUNTIFS('Phase 05 Lab & Radiology'!$O$2:$O$25,"P5-S07",'Phase 05 Lab & Radiology'!$G$2:$G$25,"PASS")-COUNTIFS('Phase 05 Lab & Radiology'!$O$2:$O$25,"P5-S07",'Phase 05 Lab & Radiology'!$G$2:$G$25,"FAIL")-COUNTIFS('Phase 05 Lab & Radiology'!$O$2:$O$25,"P5-S07",'Phase 05 Lab & Radiology'!$G$2:$G$25,"BLOCKED") | G46: =IF(COUNTIFS('Phase 05 Lab & Radiology'!$O$2:$O$25,"P5-S07",'Phase 05 Lab & Radiology'!$G$2:$G$25,"FAIL")>0,"FAIL",IF(COUNTIFS('Phase 05 Lab & Radiology'!$O$2:$O$25,"P5-S07",'Phase 05 Lab & Radiology'!$G$2:$G$25,"PASS")=COUNTIF('Phase 05 Lab & Radiology'!$O$2:$O$25,"P5-S07"),"PASS",IF(COUNTIFS('Phase 05 Lab & Radiology'!$O$2:$O$25,"P5-S07",'Phase 05 Lab & Radiology'!$G$2:$G$25,"PASS")+COUNTIFS('Phase 05 Lab & Radiology'!$O$2:$O$25,"P5-S07",'Phase 05 Lab & Radiology'!$G$2:$G$25,"BLOCKED")>0,"IN PROGRESS","NOT STARTED")))
A47: P5-S08 | B47: Phase 05 Lab & Radiology | C47: =COUNTIF('Phase 05 Lab & Radiology'!$O$2:$O$25,"P5-S08") | D47: =COUNTIFS('Phase 05 Lab & Radiology'!$O$2:$O$25,"P5-S08",'Phase 05 Lab & Radiology'!$G$2:$G$25,"PASS") | E47: =COUNTIFS('Phase 05 Lab & Radiology'!$O$2:$O$25,"P5-S08",'Phase 05 Lab & Radiology'!$G$2:$G$25,"FAIL") | F47: =COUNTIF('Phase 05 Lab & Radiology'!$O$2:$O$25,"P5-S08")-COUNTIFS('Phase 05 Lab & Radiology'!$O$2:$O$25,"P5-S08",'Phase 05 Lab & Radiology'!$G$2:$G$25,"PASS")-COUNTIFS('Phase 05 Lab & Radiology'!$O$2:$O$25,"P5-S08",'Phase 05 Lab & Radiology'!$G$2:$G$25,"FAIL")-COUNTIFS('Phase 05 Lab & Radiology'!$O$2:$O$25,"P5-S08",'Phase 05 Lab & Radiology'!$G$2:$G$25,"BLOCKED") | G47: =IF(COUNTIFS('Phase 05 Lab & Radiology'!$O$2:$O$25,"P5-S08",'Phase 05 Lab & Radiology'!$G$2:$G$25,"FAIL")>0,"FAIL",IF(COUNTIFS('Phase 05 Lab & Radiology'!$O$2:$O$25,"P5-S08",'Phase 05 Lab & Radiology'!$G$2:$G$25,"PASS")=COUNTIF('Phase 05 Lab & Radiology'!$O$2:$O$25,"P5-S08"),"PASS",IF(COUNTIFS('Phase 05 Lab & Radiology'!$O$2:$O$25,"P5-S08",'Phase 05 Lab & Radiology'!$G$2:$G$25,"PASS")+COUNTIFS('Phase 05 Lab & Radiology'!$O$2:$O$25,"P5-S08",'Phase 05 Lab & Radiology'!$G$2:$G$25,"BLOCKED")>0,"IN PROGRESS","NOT STARTED")))
A48: P5-S09 | B48: Phase 05 Lab & Radiology | C48: =COUNTIF('Phase 05 Lab & Radiology'!$O$2:$O$25,"P5-S09") | D48: =COUNTIFS('Phase 05 Lab & Radiology'!$O$2:$O$25,"P5-S09",'Phase 05 Lab & Radiology'!$G$2:$G$25,"PASS") | E48: =COUNTIFS('Phase 05 Lab & Radiology'!$O$2:$O$25,"P5-S09",'Phase 05 Lab & Radiology'!$G$2:$G$25,"FAIL") | F48: =COUNTIF('Phase 05 Lab & Radiology'!$O$2:$O$25,"P5-S09")-COUNTIFS('Phase 05 Lab & Radiology'!$O$2:$O$25,"P5-S09",'Phase 05 Lab & Radiology'!$G$2:$G$25,"PASS")-COUNTIFS('Phase 05 Lab & Radiology'!$O$2:$O$25,"P5-S09",'Phase 05 Lab & Radiology'!$G$2:$G$25,"FAIL")-COUNTIFS('Phase 05 Lab & Radiology'!$O$2:$O$25,"P5-S09",'Phase 05 Lab & Radiology'!$G$2:$G$25,"BLOCKED") | G48: =IF(COUNTIFS('Phase 05 Lab & Radiology'!$O$2:$O$25,"P5-S09",'Phase 05 Lab & Radiology'!$G$2:$G$25,"FAIL")>0,"FAIL",IF(COUNTIFS('Phase 05 Lab & Radiology'!$O$2:$O$25,"P5-S09",'Phase 05 Lab & Radiology'!$G$2:$G$25,"PASS")=COUNTIF('Phase 05 Lab & Radiology'!$O$2:$O$25,"P5-S09"),"PASS",IF(COUNTIFS('Phase 05 Lab & Radiology'!$O$2:$O$25,"P5-S09",'Phase 05 Lab & Radiology'!$G$2:$G$25,"PASS")+COUNTIFS('Phase 05 Lab & Radiology'!$O$2:$O$25,"P5-S09",'Phase 05 Lab & Radiology'!$G$2:$G$25,"BLOCKED")>0,"IN PROGRESS","NOT STARTED")))
A49: P5-S10 | B49: Phase 05 Lab & Radiology | C49: =COUNTIF('Phase 05 Lab & Radiology'!$O$2:$O$25,"P5-S10") | D49: =COUNTIFS('Phase 05 Lab & Radiology'!$O$2:$O$25,"P5-S10",'Phase 05 Lab & Radiology'!$G$2:$G$25,"PASS") | E49: =COUNTIFS('Phase 05 Lab & Radiology'!$O$2:$O$25,"P5-S10",'Phase 05 Lab & Radiology'!$G$2:$G$25,"FAIL") | F49: =COUNTIF('Phase 05 Lab & Radiology'!$O$2:$O$25,"P5-S10")-COUNTIFS('Phase 05 Lab & Radiology'!$O$2:$O$25,"P5-S10",'Phase 05 Lab & Radiology'!$G$2:$G$25,"PASS")-COUNTIFS('Phase 05 Lab & Radiology'!$O$2:$O$25,"P5-S10",'Phase 05 Lab & Radiology'!$G$2:$G$25,"FAIL")-COUNTIFS('Phase 05 Lab & Radiology'!$O$2:$O$25,"P5-S10",'Phase 05 Lab & Radiology'!$G$2:$G$25,"BLOCKED") | G49: =IF(COUNTIFS('Phase 05 Lab & Radiology'!$O$2:$O$25,"P5-S10",'Phase 05 Lab & Radiology'!$G$2:$G$25,"FAIL")>0,"FAIL",IF(COUNTIFS('Phase 05 Lab & Radiology'!$O$2:$O$25,"P5-S10",'Phase 05 Lab & Radiology'!$G$2:$G$25,"PASS")=COUNTIF('Phase 05 Lab & Radiology'!$O$2:$O$25,"P5-S10"),"PASS",IF(COUNTIFS('Phase 05 Lab & Radiology'!$O$2:$O$25,"P5-S10",'Phase 05 Lab & Radiology'!$G$2:$G$25,"PASS")+COUNTIFS('Phase 05 Lab & Radiology'!$O$2:$O$25,"P5-S10",'Phase 05 Lab & Radiology'!$G$2:$G$25,"BLOCKED")>0,"IN PROGRESS","NOT STARTED")))
A50: P5-S11 | B50: Phase 05 Lab & Radiology | C50: =COUNTIF('Phase 05 Lab & Radiology'!$O$2:$O$25,"P5-S11") | D50: =COUNTIFS('Phase 05 Lab & Radiology'!$O$2:$O$25,"P5-S11",'Phase 05 Lab & Radiology'!$G$2:$G$25,"PASS") | E50: =COUNTIFS('Phase 05 Lab & Radiology'!$O$2:$O$25,"P5-S11",'Phase 05 Lab & Radiology'!$G$2:$G$25,"FAIL") | F50: =COUNTIF('Phase 05 Lab & Radiology'!$O$2:$O$25,"P5-S11")-COUNTIFS('Phase 05 Lab & Radiology'!$O$2:$O$25,"P5-S11",'Phase 05 Lab & Radiology'!$G$2:$G$25,"PASS")-COUNTIFS('Phase 05 Lab & Radiology'!$O$2:$O$25,"P5-S11",'Phase 05 Lab & Radiology'!$G$2:$G$25,"FAIL")-COUNTIFS('Phase 05 Lab & Radiology'!$O$2:$O$25,"P5-S11",'Phase 05 Lab & Radiology'!$G$2:$G$25,"BLOCKED") | G50: =IF(COUNTIFS('Phase 05 Lab & Radiology'!$O$2:$O$25,"P5-S11",'Phase 05 Lab & Radiology'!$G$2:$G$25,"FAIL")>0,"FAIL",IF(COUNTIFS('Phase 05 Lab & Radiology'!$O$2:$O$25,"P5-S11",'Phase 05 Lab & Radiology'!$G$2:$G$25,"PASS")=COUNTIF('Phase 05 Lab & Radiology'!$O$2:$O$25,"P5-S11"),"PASS",IF(COUNTIFS('Phase 05 Lab & Radiology'!$O$2:$O$25,"P5-S11",'Phase 05 Lab & Radiology'!$G$2:$G$25,"PASS")+COUNTIFS('Phase 05 Lab & Radiology'!$O$2:$O$25,"P5-S11",'Phase 05 Lab & Radiology'!$G$2:$G$25,"BLOCKED")>0,"IN PROGRESS","NOT STARTED")))
A51: P5-S12 | B51: Phase 05 Lab & Radiology | C51: =COUNTIF('Phase 05 Lab & Radiology'!$O$2:$O$25,"P5-S12") | D51: =COUNTIFS('Phase 05 Lab & Radiology'!$O$2:$O$25,"P5-S12",'Phase 05 Lab & Radiology'!$G$2:$G$25,"PASS") | E51: =COUNTIFS('Phase 05 Lab & Radiology'!$O$2:$O$25,"P5-S12",'Phase 05 Lab & Radiology'!$G$2:$G$25,"FAIL") | F51: =COUNTIF('Phase 05 Lab & Radiology'!$O$2:$O$25,"P5-S12")-COUNTIFS('Phase 05 Lab & Radiology'!$O$2:$O$25,"P5-S12",'Phase 05 Lab & Radiology'!$G$2:$G$25,"PASS")-COUNTIFS('Phase 05 Lab & Radiology'!$O$2:$O$25,"P5-S12",'Phase 05 Lab & Radiology'!$G$2:$G$25,"FAIL")-COUNTIFS('Phase 05 Lab & Radiology'!$O$2:$O$25,"P5-S12",'Phase 05 Lab & Radiology'!$G$2:$G$25,"BLOCKED") | G51: =IF(COUNTIFS('Phase 05 Lab & Radiology'!$O$2:$O$25,"P5-S12",'Phase 05 Lab & Radiology'!$G$2:$G$25,"FAIL")>0,"FAIL",IF(COUNTIFS('Phase 05 Lab & Radiology'!$O$2:$O$25,"P5-S12",'Phase 05 Lab & Radiology'!$G$2:$G$25,"PASS")=COUNTIF('Phase 05 Lab & Radiology'!$O$2:$O$25,"P5-S12"),"PASS",IF(COUNTIFS('Phase 05 Lab & Radiology'!$O$2:$O$25,"P5-S12",'Phase 05 Lab & Radiology'!$G$2:$G$25,"PASS")+COUNTIFS('Phase 05 Lab & Radiology'!$O$2:$O$25,"P5-S12",'Phase 05 Lab & Radiology'!$G$2:$G$25,"BLOCKED")>0,"IN PROGRESS","NOT STARTED")))
A52: P5-S13 | B52: Phase 05 Lab & Radiology | C52: =COUNTIF('Phase 05 Lab & Radiology'!$O$2:$O$25,"P5-S13") | D52: =COUNTIFS('Phase 05 Lab & Radiology'!$O$2:$O$25,"P5-S13",'Phase 05 Lab & Radiology'!$G$2:$G$25,"PASS") | E52: =COUNTIFS('Phase 05 Lab & Radiology'!$O$2:$O$25,"P5-S13",'Phase 05 Lab & Radiology'!$G$2:$G$25,"FAIL") | F52: =COUNTIF('Phase 05 Lab & Radiology'!$O$2:$O$25,"P5-S13")-COUNTIFS('Phase 05 Lab & Radiology'!$O$2:$O$25,"P5-S13",'Phase 05 Lab & Radiology'!$G$2:$G$25,"PASS")-COUNTIFS('Phase 05 Lab & Radiology'!$O$2:$O$25,"P5-S13",'Phase 05 Lab & Radiology'!$G$2:$G$25,"FAIL")-COUNTIFS('Phase 05 Lab & Radiology'!$O$2:$O$25,"P5-S13",'Phase 05 Lab & Radiology'!$G$2:$G$25,"BLOCKED") | G52: =IF(COUNTIFS('Phase 05 Lab & Radiology'!$O$2:$O$25,"P5-S13",'Phase 05 Lab & Radiology'!$G$2:$G$25,"FAIL")>0,"FAIL",IF(COUNTIFS('Phase 05 Lab & Radiology'!$O$2:$O$25,"P5-S13",'Phase 05 Lab & Radiology'!$G$2:$G$25,"PASS")=COUNTIF('Phase 05 Lab & Radiology'!$O$2:$O$25,"P5-S13"),"PASS",IF(COUNTIFS('Phase 05 Lab & Radiology'!$O$2:$O$25,"P5-S13",'Phase 05 Lab & Radiology'!$G$2:$G$25,"PASS")+COUNTIFS('Phase 05 Lab & Radiology'!$O$2:$O$25,"P5-S13",'Phase 05 Lab & Radiology'!$G$2:$G$25,"BLOCKED")>0,"IN PROGRESS","NOT STARTED")))
A53: P5-S14 | B53: Phase 05 Lab & Radiology | C53: =COUNTIF('Phase 05 Lab & Radiology'!$O$2:$O$25,"P5-S14") | D53: =COUNTIFS('Phase 05 Lab & Radiology'!$O$2:$O$25,"P5-S14",'Phase 05 Lab & Radiology'!$G$2:$G$25,"PASS") | E53: =COUNTIFS('Phase 05 Lab & Radiology'!$O$2:$O$25,"P5-S14",'Phase 05 Lab & Radiology'!$G$2:$G$25,"FAIL") | F53: =COUNTIF('Phase 05 Lab & Radiology'!$O$2:$O$25,"P5-S14")-COUNTIFS('Phase 05 Lab & Radiology'!$O$2:$O$25,"P5-S14",'Phase 05 Lab & Radiology'!$G$2:$G$25,"PASS")-COUNTIFS('Phase 05 Lab & Radiology'!$O$2:$O$25,"P5-S14",'Phase 05 Lab & Radiology'!$G$2:$G$25,"FAIL")-COUNTIFS('Phase 05 Lab & Radiology'!$O$2:$O$25,"P5-S14",'Phase 05 Lab & Radiology'!$G$2:$G$25,"BLOCKED") | G53: =IF(COUNTIFS('Phase 05 Lab & Radiology'!$O$2:$O$25,"P5-S14",'Phase 05 Lab & Radiology'!$G$2:$G$25,"FAIL")>0,"FAIL",IF(COUNTIFS('Phase 05 Lab & Radiology'!$O$2:$O$25,"P5-S14",'Phase 05 Lab & Radiology'!$G$2:$G$25,"PASS")=COUNTIF('Phase 05 Lab & Radiology'!$O$2:$O$25,"P5-S14"),"PASS",IF(COUNTIFS('Phase 05 Lab & Radiology'!$O$2:$O$25,"P5-S14",'Phase 05 Lab & Radiology'!$G$2:$G$25,"PASS")+COUNTIFS('Phase 05 Lab & Radiology'!$O$2:$O$25,"P5-S14",'Phase 05 Lab & Radiology'!$G$2:$G$25,"BLOCKED")>0,"IN PROGRESS","NOT STARTED")))
A54: P5-S15 | B54: Phase 05 Lab & Radiology | C54: =COUNTIF('Phase 05 Lab & Radiology'!$O$2:$O$25,"P5-S15") | D54: =COUNTIFS('Phase 05 Lab & Radiology'!$O$2:$O$25,"P5-S15",'Phase 05 Lab & Radiology'!$G$2:$G$25,"PASS") | E54: =COUNTIFS('Phase 05 Lab & Radiology'!$O$2:$O$25,"P5-S15",'Phase 05 Lab & Radiology'!$G$2:$G$25,"FAIL") | F54: =COUNTIF('Phase 05 Lab & Radiology'!$O$2:$O$25,"P5-S15")-COUNTIFS('Phase 05 Lab & Radiology'!$O$2:$O$25,"P5-S15",'Phase 05 Lab & Radiology'!$G$2:$G$25,"PASS")-COUNTIFS('Phase 05 Lab & Radiology'!$O$2:$O$25,"P5-S15",'Phase 05 Lab & Radiology'!$G$2:$G$25,"FAIL")-COUNTIFS('Phase 05 Lab & Radiology'!$O$2:$O$25,"P5-S15",'Phase 05 Lab & Radiology'!$G$2:$G$25,"BLOCKED") | G54: =IF(COUNTIFS('Phase 05 Lab & Radiology'!$O$2:$O$25,"P5-S15",'Phase 05 Lab & Radiology'!$G$2:$G$25,"FAIL")>0,"FAIL",IF(COUNTIFS('Phase 05 Lab & Radiology'!$O$2:$O$25,"P5-S15",'Phase 05 Lab & Radiology'!$G$2:$G$25,"PASS")=COUNTIF('Phase 05 Lab & Radiology'!$O$2:$O$25,"P5-S15"),"PASS",IF(COUNTIFS('Phase 05 Lab & Radiology'!$O$2:$O$25,"P5-S15",'Phase 05 Lab & Radiology'!$G$2:$G$25,"PASS")+COUNTIFS('Phase 05 Lab & Radiology'!$O$2:$O$25,"P5-S15",'Phase 05 Lab & Radiology'!$G$2:$G$25,"BLOCKED")>0,"IN PROGRESS","NOT STARTED")))
A55: P5-S16 | B55: Phase 05 Lab & Radiology | C55: =COUNTIF('Phase 05 Lab & Radiology'!$O$2:$O$25,"P5-S16") | D55: =COUNTIFS('Phase 05 Lab & Radiology'!$O$2:$O$25,"P5-S16",'Phase 05 Lab & Radiology'!$G$2:$G$25,"PASS") | E55: =COUNTIFS('Phase 05 Lab & Radiology'!$O$2:$O$25,"P5-S16",'Phase 05 Lab & Radiology'!$G$2:$G$25,"FAIL") | F55: =COUNTIF('Phase 05 Lab & Radiology'!$O$2:$O$25,"P5-S16")-COUNTIFS('Phase 05 Lab & Radiology'!$O$2:$O$25,"P5-S16",'Phase 05 Lab & Radiology'!$G$2:$G$25,"PASS")-COUNTIFS('Phase 05 Lab & Radiology'!$O$2:$O$25,"P5-S16",'Phase 05 Lab & Radiology'!$G$2:$G$25,"FAIL")-COUNTIFS('Phase 05 Lab & Radiology'!$O$2:$O$25,"P5-S16",'Phase 05 Lab & Radiology'!$G$2:$G$25,"BLOCKED") | G55: =IF(COUNTIFS('Phase 05 Lab & Radiology'!$O$2:$O$25,"P5-S16",'Phase 05 Lab & Radiology'!$G$2:$G$25,"FAIL")>0,"FAIL",IF(COUNTIFS('Phase 05 Lab & Radiology'!$O$2:$O$25,"P5-S16",'Phase 05 Lab & Radiology'!$G$2:$G$25,"PASS")=COUNTIF('Phase 05 Lab & Radiology'!$O$2:$O$25,"P5-S16"),"PASS",IF(COUNTIFS('Phase 05 Lab & Radiology'!$O$2:$O$25,"P5-S16",'Phase 05 Lab & Radiology'!$G$2:$G$25,"PASS")+COUNTIFS('Phase 05 Lab & Radiology'!$O$2:$O$25,"P5-S16",'Phase 05 Lab & Radiology'!$G$2:$G$25,"BLOCKED")>0,"IN PROGRESS","NOT STARTED")))
A56: P5-S18 | B56: Phase 05 Lab & Radiology | C56: =COUNTIF('Phase 05 Lab & Radiology'!$O$2:$O$25,"P5-S18") | D56: =COUNTIFS('Phase 05 Lab & Radiology'!$O$2:$O$25,"P5-S18",'Phase 05 Lab & Radiology'!$G$2:$G$25,"PASS") | E56: =COUNTIFS('Phase 05 Lab & Radiology'!$O$2:$O$25,"P5-S18",'Phase 05 Lab & Radiology'!$G$2:$G$25,"FAIL") | F56: =COUNTIF('Phase 05 Lab & Radiology'!$O$2:$O$25,"P5-S18")-COUNTIFS('Phase 05 Lab & Radiology'!$O$2:$O$25,"P5-S18",'Phase 05 Lab & Radiology'!$G$2:$G$25,"PASS")-COUNTIFS('Phase 05 Lab & Radiology'!$O$2:$O$25,"P5-S18",'Phase 05 Lab & Radiology'!$G$2:$G$25,"FAIL")-COUNTIFS('Phase 05 Lab & Radiology'!$O$2:$O$25,"P5-S18",'Phase 05 Lab & Radiology'!$G$2:$G$25,"BLOCKED") | G56: =IF(COUNTIFS('Phase 05 Lab & Radiology'!$O$2:$O$25,"P5-S18",'Phase 05 Lab & Radiology'!$G$2:$G$25,"FAIL")>0,"FAIL",IF(COUNTIFS('Phase 05 Lab & Radiology'!$O$2:$O$25,"P5-S18",'Phase 05 Lab & Radiology'!$G$2:$G$25,"PASS")=COUNTIF('Phase 05 Lab & Radiology'!$O$2:$O$25,"P5-S18"),"PASS",IF(COUNTIFS('Phase 05 Lab & Radiology'!$O$2:$O$25,"P5-S18",'Phase 05 Lab & Radiology'!$G$2:$G$25,"PASS")+COUNTIFS('Phase 05 Lab & Radiology'!$O$2:$O$25,"P5-S18",'Phase 05 Lab & Radiology'!$G$2:$G$25,"BLOCKED")>0,"IN PROGRESS","NOT STARTED")))
A57: P5-S19 | B57: Phase 05 Lab & Radiology | C57: =COUNTIF('Phase 05 Lab & Radiology'!$O$2:$O$25,"P5-S19") | D57: =COUNTIFS('Phase 05 Lab & Radiology'!$O$2:$O$25,"P5-S19",'Phase 05 Lab & Radiology'!$G$2:$G$25,"PASS") | E57: =COUNTIFS('Phase 05 Lab & Radiology'!$O$2:$O$25,"P5-S19",'Phase 05 Lab & Radiology'!$G$2:$G$25,"FAIL") | F57: =COUNTIF('Phase 05 Lab & Radiology'!$O$2:$O$25,"P5-S19")-COUNTIFS('Phase 05 Lab & Radiology'!$O$2:$O$25,"P5-S19",'Phase 05 Lab & Radiology'!$G$2:$G$25,"PASS")-COUNTIFS('Phase 05 Lab & Radiology'!$O$2:$O$25,"P5-S19",'Phase 05 Lab & Radiology'!$G$2:$G$25,"FAIL")-COUNTIFS('Phase 05 Lab & Radiology'!$O$2:$O$25,"P5-S19",'Phase 05 Lab & Radiology'!$G$2:$G$25,"BLOCKED") | G57: =IF(COUNTIFS('Phase 05 Lab & Radiology'!$O$2:$O$25,"P5-S19",'Phase 05 Lab & Radiology'!$G$2:$G$25,"FAIL")>0,"FAIL",IF(COUNTIFS('Phase 05 Lab & Radiology'!$O$2:$O$25,"P5-S19",'Phase 05 Lab & Radiology'!$G$2:$G$25,"PASS")=COUNTIF('Phase 05 Lab & Radiology'!$O$2:$O$25,"P5-S19"),"PASS",IF(COUNTIFS('Phase 05 Lab & Radiology'!$O$2:$O$25,"P5-S19",'Phase 05 Lab & Radiology'!$G$2:$G$25,"PASS")+COUNTIFS('Phase 05 Lab & Radiology'!$O$2:$O$25,"P5-S19",'Phase 05 Lab & Radiology'!$G$2:$G$25,"BLOCKED")>0,"IN PROGRESS","NOT STARTED")))
A58: P5-S20 | B58: Phase 05 Lab & Radiology | C58: =COUNTIF('Phase 05 Lab & Radiology'!$O$2:$O$25,"P5-S20") | D58: =COUNTIFS('Phase 05 Lab & Radiology'!$O$2:$O$25,"P5-S20",'Phase 05 Lab & Radiology'!$G$2:$G$25,"PASS") | E58: =COUNTIFS('Phase 05 Lab & Radiology'!$O$2:$O$25,"P5-S20",'Phase 05 Lab & Radiology'!$G$2:$G$25,"FAIL") | F58: =COUNTIF('Phase 05 Lab & Radiology'!$O$2:$O$25,"P5-S20")-COUNTIFS('Phase 05 Lab & Radiology'!$O$2:$O$25,"P5-S20",'Phase 05 Lab & Radiology'!$G$2:$G$25,"PASS")-COUNTIFS('Phase 05 Lab & Radiology'!$O$2:$O$25,"P5-S20",'Phase 05 Lab & Radiology'!$G$2:$G$25,"FAIL")-COUNTIFS('Phase 05 Lab & Radiology'!$O$2:$O$25,"P5-S20",'Phase 05 Lab & Radiology'!$G$2:$G$25,"BLOCKED") | G58: =IF(COUNTIFS('Phase 05 Lab & Radiology'!$O$2:$O$25,"P5-S20",'Phase 05 Lab & Radiology'!$G$2:$G$25,"FAIL")>0,"FAIL",IF(COUNTIFS('Phase 05 Lab & Radiology'!$O$2:$O$25,"P5-S20",'Phase 05 Lab & Radiology'!$G$2:$G$25,"PASS")=COUNTIF('Phase 05 Lab & Radiology'!$O$2:$O$25,"P5-S20"),"PASS",IF(COUNTIFS('Phase 05 Lab & Radiology'!$O$2:$O$25,"P5-S20",'Phase 05 Lab & Radiology'!$G$2:$G$25,"PASS")+COUNTIFS('Phase 05 Lab & Radiology'!$O$2:$O$25,"P5-S20",'Phase 05 Lab & Radiology'!$G$2:$G$25,"BLOCKED")>0,"IN PROGRESS","NOT STARTED")))
A59: P5-Setup | B59: Phase 05 Lab & Radiology | C59: =COUNTIF('Phase 05 Lab & Radiology'!$O$2:$O$25,"P5-Setup") | D59: =COUNTIFS('Phase 05 Lab & Radiology'!$O$2:$O$25,"P5-Setup",'Phase 05 Lab & Radiology'!$G$2:$G$25,"PASS") | E59: =COUNTIFS('Phase 05 Lab & Radiology'!$O$2:$O$25,"P5-Setup",'Phase 05 Lab & Radiology'!$G$2:$G$25,"FAIL") | F59: =COUNTIF('Phase 05 Lab & Radiology'!$O$2:$O$25,"P5-Setup")-COUNTIFS('Phase 05 Lab & Radiology'!$O$2:$O$25,"P5-Setup",'Phase 05 Lab & Radiology'!$G$2:$G$25,"PASS")-COUNTIFS('Phase 05 Lab & Radiology'!$O$2:$O$25,"P5-Setup",'Phase 05 Lab & Radiology'!$G$2:$G$25,"FAIL")-COUNTIFS('Phase 05 Lab & Radiology'!$O$2:$O$25,"P5-Setup",'Phase 05 Lab & Radiology'!$G$2:$G$25,"BLOCKED") | G59: =IF(COUNTIFS('Phase 05 Lab & Radiology'!$O$2:$O$25,"P5-Setup",'Phase 05 Lab & Radiology'!$G$2:$G$25,"FAIL")>0,"FAIL",IF(COUNTIFS('Phase 05 Lab & Radiology'!$O$2:$O$25,"P5-Setup",'Phase 05 Lab & Radiology'!$G$2:$G$25,"PASS")=COUNTIF('Phase 05 Lab & Radiology'!$O$2:$O$25,"P5-Setup"),"PASS",IF(COUNTIFS('Phase 05 Lab & Radiology'!$O$2:$O$25,"P5-Setup",'Phase 05 Lab & Radiology'!$G$2:$G$25,"PASS")+COUNTIFS('Phase 05 Lab & Radiology'!$O$2:$O$25,"P5-Setup",'Phase 05 Lab & Radiology'!$G$2:$G$25,"BLOCKED")>0,"IN PROGRESS","NOT STARTED")))
A61: Scenarios for phases not yet written appear once their CSV is added. Full list of ~230 scenarios: docs/qa/JOURNEY_SCENARIOS.md

Sheet Go-Live Readiness
A1: Category | B1: Scenario | C1: What must be true | D1: Status | E1: Evidence / Notes
A2: Patient safety | B2: P4-S11 | C2: Drug allergy prescription is blocked; override is audited
A3: Patient safety | B3: P4-S10 | C3: Drug interaction alert fires
A4: Patient safety | B4: P5-S07 | C4: Critical lab value raises an immediate alert
A5: Patient safety | B5: P5-S06 | C5: Rejected sample re-queues without double-charging
A6: Patient safety | B6: P5-S10 | C6: Dual-validation test cannot be released by one person
A7: Patient safety | B7: P6-S04 | C7: FEFO batch selection picks the earliest expiry
A8: Patient safety | B8: P6-S05 | C8: Expired batch cannot be dispensed
A9: Patient safety | B9: P6-S07 | C9: NDPS dispensing requires dual sign-off
A10: Patient safety | B10: P6-S08 | C10: NDPS with a single signature is blocked
A11: Patient safety | B11: P7-S06 | C11: ICU flowsheet, ventilator and sedation records save
A12: Patient safety | B12: P10-OT | C12: WHO surgical checklist cannot be bypassed
A13: Patient safety | B13: P10-BB | C13: Blood cross-match is traceable donor to recipient
... A56: Regression | B56: R7 | C56: Cross-tenant sweep
A58: VERDICT | C58: All must-pass items green AND zero open P1 defects anywhere | D58: =IF(COUNTIF(D2:D56,"PASS")=55,"READY TO GO LIVE","NOT READY")

Sheet Phase 01 Foundation & Access
A1: TC# | B1: Section | C1: Priority | D1: Test Case | E1: Steps | F1: Expected Result | G1: Status(PASS/FAIL/BLOCKED) | H1: mock data | I1: Cross-Module Link | J1: Settings need to set before entering to the module | K1: Actual Result(What happened) | L1: Console Error(Copy-paste red text) | M1: Screenshot(Y/N) | N1: Notes | O1: Journey Scenario | P1: Why This Exists | Q1: Test Type | R1: Role/Login | S1: Supabase Verify | T1: Playwright Spec | U1: Defect ID | V1: Stages Passed / Total
A2: TC-P1A-001 | B2: 1A Registration | C2: P2 | D2: Registration page loads with step 1 of 5 | E2: 1) Open /register in a fresh incognito window 2) Observe the wizard | F2: Step 1 'Hospital Identity' renders with a 5-step progress bar. No console errors. | G2: Pass | H2: None | J2: None - public route | O2: P1-Setup | P2: A hospital cannot become a customer if it cannot sign up. This is the very first screen anyone outside your company ever sees. | Q2: Positive | R2: Logged out | S2: None | T2: e2e/phase-01-foundation/P1A.registration.spec.ts
A3: TC-P1A-002 | B3: 1A Registration | C3: P2 | D3: Step 1 accepts valid hospital identity | E3: 1) Enter Hospital Name 'Aarogya Multispecialty Hospital' 2) Select Type 'Private Hospital' 3) Select State 'Telangana' 4) Select Bed Count '101-200 beds' 5) Enter Phone 9876500001 6) Click Next | F3: Next is enabled and the wizard advances to step 2. | G3: Pass | H3: Hospital A identity block | J3: None | O3: P1-Setup | P3: Hospital type and bed count drive plan pricing and default module selection - wrong data here mis-prices the customer. | Q3: Positive | R3: Logged out | S3: hospitals - after full signup | T3: e2e/phase-01-foundation/P1A.registration.spec.ts
A4: TC-P1A-003 | B4: 1A Registration | C4: P2 | D4: Step 1 Next is disabled with any field blank | E4: 1) Fill every field except State 2) Observe the Next button | F4: Next stays disabled. No way to advance with incomplete identity. | G4: Pass | H4: Hospital A minus State | J4: None | O4: P1-Setup | P4: A hospital record without a state breaks GST place-of-supply and state scheme eligibility downstream. | Q4: Negative | R4: Logged out | S4: None | T4: e2e/phase-01-foundation/P1A.registration.spec.ts
A5: TC-P1A-004 | B5: 1A Registration | C5: P2 | D5: Phone accepts exactly 10 digits | E5: 1) Enter phone 98765 2) Try Next 3) Enter 98765000011 (11 digits) 4) Try Next 5) Enter 9876500001 6) Try Next | F5: Only the 10-digit value is accepted. Shorter and longer are rejected. | G5: Pass | H5: 9876500001 | J5: None | O5: P1-Setup | P5: Indian mobile numbers are 10 digits. A malformed number means OTP and WhatsApp never reach the customer. | Q5: Boundary | R5: Logged out | S5: None | T5: e2e/phase-01-foundation/P1A.registration.spec.ts
A6: TC-P1A-005 | B6: 1A Registration | C6: P2 | D6: Phone rejects letters and symbols | E6: 1) Type 'abcdefghij' into Phone 2) Type '98765-0001' | F6: Non-numeric input is rejected or stripped. | G6: Pass | H6: abcdefghij | J6: None | O6: P1-Setup | P6: Free-text phone fields are the most common source of unusable contact data. | Q6: Negative | R6: Logged out | S6: None | T6: MANUAL-ONLY
A7: TC-P1A-006 | B7: 1A Registration | C7: P2 | D7: Phone OTP is sent and verifies | E7: 1) Complete step 1 with phone 9876500001 2) Click Verify 3) Retrieve the OTP 4) Enter it 5) Submit | F7: OTP accepted, phone shows verified, and a single-use token is held for the final submit. | G7: Pass | H7: 9876500001 | J7: Platform setting: OTP required toggle (see /platform/settings) | N7: If OTP is not enabled on your platform settings this case is N/A - mark BLOCKED and note it | O7: P1-Setup | P7: OTP is the only thing stopping bulk fake signups from consuming your free trials. | Q7: Positive | R7: Logged out | S7: signup_otp_verifications | T7: MANUAL-ONLY
A8: TC-P1A-007 | B8: 1A Registration | C8: P2 | D8: Wrong OTP is rejected | E8: 1) Request an OTP 2) Enter 000000 3) Submit | F8: Rejected with a clear message. Phone stays unverified. Registration cannot proceed. | G8: Pass | H8: OTP 000000 | J8: OTP required enabled | O8: P1-Setup | P8: An OTP that accepts any value is the same as having no OTP at all. | Q8: Negative | R8: Logged out | S8: signup_otp_verifications | T8: MANUAL-ONLY
A9: TC-P1A-008 | B9: 1A Registration | C9: P2 | D9: Expired OTP is rejected | E9: 1) Request an OTP 2) Wait past the expiry window 3) Enter the correct code 4) Submit | F9: Rejected as expired. A new OTP must be requested. | G9: Pass | H9: valid but stale OTP | J9: OTP required enabled | O9: P1-Setup | P9: An OTP with no expiry can be reused indefinitely if intercepted. | Q9: Negative | R9: Logged out | S9: signup_otp_verifications | T9: MANUAL-ONLY
A10: TC-P1A-009 | B10: 1A Registration | C10: P2 | D10: Step 2 accepts a valid admin account | E10: 1) Enter Full Name 'Dr. Ravi Shankar' 2) Email yeswanthvarma94+qa.admin.a@gmail.com 3) Password TestPass@2026 4) Confirm the same 5) Designation 'Medical Director' 6) Next | F10: Advances to step 3. | G10: Pass | H10: Hospital A admin block | J10: None | O10: P1-Setup | P10: This account becomes the hospital administrator - the only person who can create every other login. | Q10: Positive | R10: Logged out | S10: users after signup | T10: e2e/phase-01-foundation/P1A.registration.spec.ts
A11: TC-P1A-010 | B11: 1A Registration | C11: P2 | D11: Malformed email is rejected | E11: 1) Enter 'notanemail' 2) Then 'a@b' 3) Then 'a@b.c' 4) Observe each | F11: Only a properly formed address with a 2+ char TLD is accepted. | G11: Pass | H11: notanemail / a@b / a@b.c | J11: None | O11: P1-Setup | P11: The admin email is where account recovery goes. Wrong and the customer is locked out permanently. | Q11: Negative | R11: Logged out | S11: None | T11: e2e/phase-01-foundation/P1A.registration.spec.ts
A12: TC-P1A-011 | B12: 1A Registration | C12: P2 | D12: Weak password is rejected | E12: 1) Enter 'pass' (too short) 2) Enter 'password' (no digit) 3) Enter '12345678' (no letter) 4) Enter 'TestPass@2026' | F12: First three rejected. Rule is 8+ characters with at least one letter and one digit. | G12: Pass | H12: pass / password / 12345678 / TestPass@2026 | J12: None | O12: P1-Setup | P12: This account can see every patient record in the hospital. A weak password here is a data breach waiting to happen. | Q12: Negative | R12: Logged out | S12: None | T12: e2e/phase-01-foundation/P1A.registration.spec.ts
A13: TC-P1A-012 | B13: 1A Registration | C13: P2 | D13: Mismatched password confirmation is rejected | E13: 1) Password TestPass@2026 2) Confirm TestPass@2025 3) Next | F13: Rejected with a mismatch message. | G13: Pass | H13: TestPass@2026 / TestPass@2025 | J13: None | O13: P1-Setup | P13: A typo in the password the user never sees means they cannot log in and do not know why. | Q13: Negative | R13: Logged out | S13: None | T13: e2e/phase-01-foundation/P1A.registration.spec.ts
A14: TC-P1A-013 | B14: 1A Registration | C14: P2 | D14: Step 3 accepts hospital details | E14: 1) Address 1 'Plot 42, Road No. 12, Banjara Hills' 2) Pincode 500034 3) City Hyderabad 4) GSTIN 36AABCA1234F1Z5 5) NABH Yes + NABH-QA-A-2026 6) Next | F14: Advances to step 4. | G14: Pass | H14: Hospital A details block | J14: None | O14: P1-Setup | P14: Address and GSTIN print on every bill. NABH status drives empanelment eligibility. | Q14: Positive | R14: Logged out | S14: hospitals | T14: e2e/phase-01-foundation/P1A.registration.spec.ts
A15: TC-P1A-014 | B15: 1A Registration | C15: P2 | D15: Pincode must be exactly 6 digits | E15: 1) Enter 5000 2) Try Next 3) Enter 5000345 4) Try Next 5) Enter 500034 6) Try Next | F15: Only the 6-digit value advances. | G15: Pass | H15: 5000 / 5000345 / 500034 | J15: None | O15: P1-Setup | P15: Indian PIN codes are 6 digits. Wrong length means undeliverable post and wrong state inference. | Q15: Boundary | R15: Logged out | S15: None | T15: e2e/phase-01-foundation/P1A.registration.spec.ts
A16: TC-P1A-015 | B16: 1A Registration | C16: P2 | D16: Malformed GSTIN is caught | E16: 1) Enter '12345' 2) Then 'ABCDEFGHIJKLMNO' 3) Then 36AABCA1234F1Z5 4) Observe | F16: Invalid formats flagged. Valid 15-char GSTIN accepted. NOTE: if any junk value is accepted, log it as a defect. | G16: Pass | H16: 12345 / ABCDEFGHIJKLMNO / 36AABCA1234F1Z5 | I16: Billing - GST invoicing | J16: None | N16: GSTIN format is 2-digit state + 10-char PAN + entity + Z + checksum | O16: P1-Setup | P16: A wrong GSTIN makes every tax invoice the hospital issues legally invalid, and they will not discover it until a GST audit. | Q16: Negative | R16: Logged out | S16: hospitals.gstin | T16: e2e/phase-01-foundation/P1A.registration.spec.ts
A17: TC-P1A-016 | B17: 1A Registration | C17: P2 | D17: GSTIN is optional | E17: 1) Leave GSTIN blank 2) Complete step 3 | F17: Registration proceeds. GSTIN can be added later in Settings. | G17: Pass | H17: GSTIN blank | I17: Billing - HSN block is inactive without GSTIN | J17: None | N17: Small clinics below the GST threshold genuinely have no GSTIN | O17: P1-Setup | P17: Many small nursing homes are below the GST registration threshold. Forcing a GSTIN would block a whole customer segment. | Q17: Positive | R17: Logged out | S17: hospitals.gstin is null | T17: MANUAL-ONLY
A18: TC-P1A-017 | B18: 1A Registration | C18: P2 | D18: Step 4 plan selection | E18: 1) Review Starter, Professional and Enterprise 2) Select Professional 3) Next | F18: Plan captured and shown on the confirm step. Pricing and included modules visible before choosing. | G18: Pass | H18: Professional | I18: Settings - Plan & subscription | J18: None | O18: P1-Setup | P18: The plan decides which of the 69 modules the hospital can even open. Choosing blind causes immediate churn. | Q18: Positive | R18: Logged out | S18: hospital_subscriptions | T18: e2e/phase-01-foundation/P1A.registration.spec.ts
A19: TC-P1A-018 | B19: 1A Registration | C19: P2 | D19: Cannot submit without accepting Terms | E19: 1) Reach step 5 2) Leave Terms unchecked 3) Try to submit | F19: Submission blocked. | G19: Pass | H19: Terms unchecked | J19: None | O19: P1-Setup | P19: Without accepted terms you have no contract with the customer. | Q19: Negative | R19: Logged out | S19: None | T19: e2e/phase-01-foundation/P1A.registration.spec.ts
A20: TC-P1A-019 | B20: 1A Registration | C20: P1 | D20: Cannot submit without DPDP consent | E20: 1) Reach step 5 2) Accept Terms 3) Leave DPDP consent unchecked 4) Try to submit | F20: Submission blocked. | G20: Pass | H20: DPDP consent unchecked | J20: None | O20: P1-Setup | P20: DPDP Act 2023 requires explicit consent for processing personal data. Missing it is a statutory violation from day one. | Q20: Negative | R20: Logged out | S20: hospital_signup_consents | T20: e2e/phase-01-foundation/P1A.registration.spec.ts
A21: TC-P1A-020 | B21: 1A Registration | C21: P1 | D21: Full registration creates the hospital | E21: 1) Complete all 5 steps with Hospital A data 2) Submit 3) Wait for confirmation | F21: Success screen shown and a verification email is triggered. | G21: Pass | H21: Full Hospital A block | I21: All modules | J21: None | O21: P1-Setup | P21: This single action creates the tenant every other test depends on. | Q21: Positive | R21: Logged out | S21: hospitals WHERE name='Aarogya Multispecialty Hospital'; users; hospital_subscriptions; hospital_signup_consents | T21: e2e/phase-01-foundation/P1A.registration.spec.ts
A22: TC-P1A-021 | B22: 1A Registration | C22: P2 | D22: Trial subscription is created | E22: 1) After TC-P1A-020 2) Query hospital_subscriptions for the new hospital_id | F22: A subscription row exists with the chosen plan and a trial state. | G22: Pass | H22: Hospital A | I22: Settings - Plan | J22: None | N22: Seeded by migration 20260616000003_seed_trial_subscription | O22: P1-Setup | P22: Without a subscription row the ModuleGate blocks every route and the customer sees an empty product. | Q22: Positive | R22: Logged out | S22: hospital_subscriptions | T22: e2e/phase-01-foundation/P1A.registration.spec.ts
A23: TC-P1A-022 | B23: 1A Registration | C23: P1 | D23: Default chart of accounts is auto-seeded | E23: 1) After TC-P1A-020 2) Query chart_of_accounts and auto_posting_rules and lab_test_master for the new hospital_id | F23: Rows exist. A DB trigger on hospitals seeds defaults on insert. | G23: Pass | H23: Hospital A | I23: Accounts - journals | J23: None | N23: Trigger from 20260613110000_seed_hospital_defaults | O23: P1-Setup | P23: Without a chart of accounts no billing event can post to the ledger, so the P&L is empty forever. | Q23: Positive | R23: Logged out | S23: chart_of_accounts; auto_posting_rules | T23: e2e/phase-01-foundation/P1A.registration.spec.ts
A24: TC-P1A-023 | B24: 1A Registration | C24: P2 | D24: Duplicate hospital registration is handled | E24: 1) Register Hospital A again with the same GSTIN and email 2) Observe | F24: Rejected with a clear message. NOTE: if a second hospital is created with the same GSTIN, log as P1. | G24: Pass | H24: Hospital A repeated | J24: None | O24: P1-Setup | P24: Two tenants with the same GSTIN means two hospitals issuing invoices under one tax registration - a serious compliance problem. | Q24: Negative | R24: Logged out | S24: hospitals - count by gstin must be 1 | T24: e2e/phase-01-foundation/P1A.registration.spec.ts
A25: TC-P1A-024 | B25: 1A Registration | C25: P3 | D25: Back navigation preserves entered data | E25: 1) Fill steps 1-3 2) Click Back to step 1 3) Click Next twice | F25: All previously entered values are still present. | G25: Pass | H25: Hospital A | J25: None | O25: P1-Setup | P25: Losing a half-filled form makes people abandon signup. It is the single biggest drop-off cause in onboarding. | Q25: Positive | R25: Logged out | S25: None | T25: MANUAL-ONLY
A26: TC-P1A-025 | B26: 1A Registration | C26: P2 | D26: Register Hospital B for isolation testing | E26: 1) Register Sanjeevani General Hospital with the Hospital B block 2) Choose the Starter plan 3) Complete | F26: Second tenant created with its own hospital_id, distinct from Hospital A. | G26: Pass | H26: Full Hospital B block | I26: All - this is the isolation control | J26: None | N26: Required before any Section 1H test can run | O26: P1-Setup | P26: Without a second hospital you cannot prove tenant isolation - and tenant isolation is the thing that ends a company if it fails. | Q26: Positive | R26: Logged out | S26: hospitals - 2 distinct rows | T26: e2e/phase-01-foundation/P1A.registration.spec.ts
A27: TC-P1B-001 | B27: 1B Onboarding | C27: P2 | D27: Onboarding wizard opens after first login | E27: 1) Verify the admin email 2) Log in as +qa.admin.a 3) Observe | F27: Redirected to /setup/onboarding at step 1 Branding. | G27: Pass | H27: Hospital A admin | J27: Registration complete | O27: P1-Setup | P27: A hospital that lands on an empty dashboard with no guidance abandons the product in the first hour. | Q27: Positive | R27: hospital_admin A | S27: hospitals | T27: e2e/phase-01-foundation/P1B.onboarding.spec.ts
A28: TC-P1B-002 | B28: 1B Onboarding | C28: P2 | D28: Wizard shows 14 steps in 6 sections | E28: 1) Open /setup/onboarding 2) Count the steps and section headers | F28: Sections: Hospital (Branding, Departments), Structure (Wards & Beds, Shifts), People (Doctors, Other Staff, OPD Schedules), Services (Fees, Payers, Lab & Radiology, Payments), Integrations (WhatsApp, Modules), Launch (Go Live). | G28: Pass | H28: None | J28: Registration complete | O28: P1-Setup | P28: The wizard order is the dependency order. If it is wrong, a customer configures things that silently fail. | Q28: Positive | R28: hospital_admin A | S28: None | T28: e2e/phase-01-foundation/P1B.onboarding.spec.ts
A29: TC-P1B-003 | B29: 1B Onboarding | C29: P2 | D29: Step 1 Branding saves logo and colour | E29: 1) Upload a logo 2) Set primary colour 3) Next | F29: Saved and reflected in the app header. | G29: Pass | H29: any test image | I29: All - print headers | J29: Registration complete | N29: Branding is marked optional in the wizard | O29: P1-Setup | P29: The hospital's logo on a bill or report is what makes the software feel like theirs rather than yours. | Q29: Positive | R29: hospital_admin A | S29: hospitals.logo_url | T29: MANUAL-ONLY
A30: TC-P1B-004 | B30: 1B Onboarding | C30: P3 | D30: Branding can be skipped | E30: 1) At Branding click Skip | F30: Advances to Departments without saving branding. | G30: Pass | H30: None | J30: Registration complete | O30: P1-Setup | P30: Optional steps must be genuinely optional or the customer is stuck at signup hunting for a logo file. | Q30: Positive | R30: hospital_admin A | S30: None | T30: MANUAL-ONLY
A31: TC-P1B-005 | B31: 1B Onboarding | C31: P2 | D31: Step 2 Departments creates all 10 departments | E31: 1) Add each department from the Mock Data Book 2) Save 3) Next | F31: All 10 saved and listed. | H31: 10 departments from Mock Data Book | I31: OPD IPD Lab Radiology | J31: Registration complete | N31: Use Indian English spellings - Anaesthesiology Gynaecology Orthopaedics Paediatrics | O31: P1-Setup | P31: No departments means no OPD token can be created and no doctor can be assigned. Nothing clinical works. | Q31: Positive | R31: hospital_admin A | S31: departments - 10 rows for hospital A | T31: e2e/phase-01-foundation/P1B.onboarding.spec.ts
A32: TC-P1B-006 | B32: 1B Onboarding | C32: P2 | D32: Departments is a mandatory step | E32: 1) At Departments with none added try Next / Skip | F32: Cannot advance. The step is not optional. | H32: None | J32: Registration complete | O32: P1-Setup | P32: Allowing a hospital past this step guarantees a broken OPD later, with no obvious cause. | Q32: Negative | R32: hospital_admin A | S32: None | T32: e2e/phase-01-foundation/P1B.onboarding.spec.ts
A33: TC-P1B-007 | B33: 1B Onboarding | C33: P2 | D33: Duplicate department name is rejected | E33: 1) Add 'General Medicine' 2) Add 'General Medicine' again | F33: Rejected as duplicate. | H33: General Medicine twice | J33: Registration complete | O33: P1-Setup | P33: Duplicate departments split a doctor's patients across two identical-looking queues. | Q33: Negative | R33: hospital_admin A | S33: departments | T33: MANUAL-ONLY
A34: TC-P1B-008 | B34: 1B Onboarding | C34: P1 | D34: Step 3 creates all 6 wards with rate_per_day | E34: 1) Add each ward from the Mock Data Book with its rate 2) Save | F34: All 6 wards saved WITH rate_per_day populated. | H34: 6 wards from Mock Data Book | I34: IPD - room charge; Billing | J34: Registration complete | N34: CRITICAL - a ward without rate_per_day silently bills Rs 500/day | O34: P1-Setup | P34: Room rent is the largest single line on most inpatient bills. A missing rate means the hospital under-bills every admission and never notices. | Q34: Positive | R34: hospital_admin A | S34: wards - rate_per_day not null on all 6 | T34: e2e/phase-01-foundation/P1B.onboarding.spec.ts
A35: TC-P1B-009 | B35: 1B Onboarding | C35: P1 | D35: Ward saved without rate_per_day is detectable | E35: 1) Add a ward leaving rate_per_day blank 2) Save 3) Check the row | F35: Either the field is mandatory, or the row saves with a null rate. If it saves null, log P1 - this is the Rs 500 silent fallback. | H35: ward with blank rate | I35: IPD room charge | J35: Registration complete | O35: P1-Setup | P35: This is the single most damaging silent failure in the application. It must at minimum be visible. | Q35: Negative | R35: hospital_admin A | S35: wards.rate_per_day | T35: e2e/phase-01-foundation/P1B.onboarding.spec.ts
A36: TC-P1B-010 | B36: 1B Onboarding | C36: P2 | D36: Step 3 creates all 32 beds | E36: 1) Add beds GW-01..10 SP-01..06 PR-01..04 DX-01..02 ICU-01..06 MW-01..04 2) Save | F36: All 32 beds created and linked to their wards with status available. | H36: 32 beds from Mock Data Book | I36: IPD - admission | J36: Registration complete + wards | O36: P1-Setup | P36: With no beds the Admit Patient modal is empty and no patient can ever be admitted. | Q36: Positive | R36: hospital_admin A | S36: beds - 32 rows | T36: e2e/phase-01-foundation/P1B.onboarding.spec.ts
A37: TC-P1B-011 | B37: 1B Onboarding | C37: P2 | D37: Duplicate bed number in the same ward is rejected | E37: 1) Add GW-01 twice to General Ward | F37: Rejected. | H37: GW-01 twice | I37: IPD | J37: Registration + wards | O37: P1-Setup | P37: Two beds with the same number means two patients can be assigned the same physical bed. | Q37: Negative | R37: hospital_admin A | S37: beds | T37: MANUAL-ONLY
A38: TC-P1B-012 | B38: 1B Onboarding | C38: P2 | D38: Step 4 Shifts creates shift master | E38: 1) Add Morning 08:00-16:00, Evening 16:00-00:00, Night 00:00-08:00 2) Save | F38: 3 shifts saved. | H38: 3 standard shifts | I38: HR - roster; Nursing handover | J38: Registration complete | O38: P1-Setup | P38: Hospitals run 24x7 on rotating shifts. Without shift definitions there is no roster and no handover. | Q38: Positive | R38: hospital_admin A | S38: shift_master | T38: e2e/phase-01-foundation/P1B.onboarding.spec.ts
A39: TC-P1B-013 | B39: 1B Onboarding | C39: P1 | D39: Step 5 Doctors creates 3 doctors with fees | E39: 1) Add Dr. Suresh Menon (Gen Medicine, Rs 500, follow-up Rs 0, validity 7d) 2) Dr. Kavitha Rao (Obs&Gynae, Rs 700, follow-up Rs 300, validity 10d) 3) Dr. Arjun Nair (Gen Surgery, Rs 800) 4) Save | F39: All 3 created as users with role doctor, and matching service_master fee rows. | H39: 3 doctors from Mock Data Book | I39: OPD - consultation billing | J39: Registration + departments | N39: Fee precedence is doctor then department then global then hardcoded Rs 500 | O39: P1-Setup | P39: With no consultation fee configured, the app silently bills a hardcoded Rs 500 for every patient regardless of doctor or specialty. | Q39: Positive | R39: hospital_admin A | S39: users WHERE role='doctor'; service_master item_type='consultation' | T39: e2e/phase-01-foundation/P1B.onboarding.spec.ts
A40: TC-P1B-014 | B40: 1B Onboarding | C40: P1 | D40: Follow-up fee and validity days save correctly | E40: 1) On Dr. Menon set follow_up_fee 0 and validity_days 7 2) Save 3) Verify the row | F40: Both values persisted exactly. | H40: Rs 0 / 7 days | I40: OPD - free revisit rule | J40: Registration + departments | N40: Drives scenarios P4-S02 and P4-S03 | O40: P1-Setup | P40: The free-revisit window is a promise the hospital makes to patients. Getting it wrong means either angry patients or lost revenue. | Q40: Positive | R40: hospital_admin A | S40: service_master.follow_up_fee and validity_days | T40: e2e/phase-01-foundation/P1B.onboarding.spec.ts
A41: TC-P1B-015 | B41: 1B Onboarding | C41: P2 | D41: Step 6 Other Staff creates non-doctor staff | E41: 1) Add nurse, receptionist, pharmacist, lab tech, billing exec per the Mock Data Book 2) Save | F41: All created with the correct roles. | H41: Staff list from Mock Data Book | I41: All modules | J41: Registration + departments | O41: P1-Setup | P41: A hospital is not one admin - every role needs its own login for accountability and audit. | Q41: Positive | R41: hospital_admin A | S41: users; staff_profiles | T41: e2e/phase-01-foundation/P1B.onboarding.spec.ts
A42: TC-P1B-016 | B42: 1B Onboarding | C42: P2 | D42: Step 7 OPD Schedules creates doctor slots | E42: 1) Set Dr. Menon Mon-Sat 09:00-13:00, 15 min slots 2) Save | F42: Schedule and slots generated. | H42: Mon-Sat 09:00-13:00 | I42: OPD - appointments | J42: Registration + doctors | O42: P1-Setup | P42: Without slots no appointment can be booked and the hospital is walk-in only. | Q42: Positive | R42: hospital_admin A | S42: doctor_schedules; doctor_slots | T42: e2e/phase-01-foundation/P1B.onboarding.spec.ts
A43: TC-P1B-017 | B43: 1B Onboarding | C43: P1 | D43: Step 8 Fees creates the service master | E43: 1) Add all 10 services from the Mock Data Book with rate, GST and HSN 2) Save | F43: All 10 saved with HSN codes populated. | H43: 10 services from Mock Data Book | I43: Billing OPD IPD | J43: Registration complete | N43: HSN is required or bill finalisation is blocked once GSTIN is set | O43: P1-Setup | P43: Every chargeable thing the hospital does must exist here with a price and a tax code, or it either cannot be billed or the invoice is illegal. | Q43: Positive | R43: hospital_admin A | S43: service_master; service_rates | T43: e2e/phase-01-foundation/P1B.onboarding.spec.ts
A44: TC-P1B-018 | B44: 1B Onboarding | C44: P1 | D44: Fees is a mandatory step | E44: 1) At Fees with no services try to skip | F44: Cannot skip. Step is mandatory. | H44: None | I44: Billing | J44: Registration complete | O44: P1-Setup | P44: Skipping fees is what produces the hardcoded Rs 500 bill later. | Q44: Negative | R44: hospital_admin A | S44: None | T44: e2e/phase-01-foundation/P1B.onboarding.spec.ts
A45: TC-P1B-019 | B45: 1B Onboarding | C45: P2 | D45: Step 9 Payers creates payer masters | E45: 1) Add all 8 payers from the Mock Data Book 2) Save | F45: All 8 saved with their type. | H45: 8 payers from Mock Data Book | I45: IPD admission; Insurance | J45: Registration complete | O45: P1-Setup | P45: Half a private hospital's revenue is insured. With no payers configured every patient is forced to self-pay. | Q45: Positive | R45: hospital_admin A | S45: payer_masters | T45: e2e/phase-01-foundation/P1B.onboarding.spec.ts
A46: TC-P1B-020 | B46: 1B Onboarding | C46: P2 | D46: Step 10 creates lab test master | E46: 1) Add all 15 lab tests with fee, sample type, unit and normal range 2) Save | F46: All 15 saved with fee and normal ranges populated. | H46: 15 lab tests from Mock Data Book | I46: OPD Rx chips; Lab orders; Billing | J46: Registration complete | N46: Missing normal range means no abnormal flag and NO critical alert | O46: P1-Setup | P46: The lab catalogue is what the OPD Rx tab matches prescribed test names against. Tests not in it are silently dropped from the order. | Q46: Positive | R46: hospital_admin A | S46: lab_test_master - 15 rows with fee not null | T46: e2e/phase-01-foundation/P1B.onboarding.spec.ts
A47: TC-P1B-021 | B47: 1B Onboarding | C47: P2 | D47: Step 10 creates radiology modalities then studies | E47: 1) Add modalities X-Ray, Ultrasound, CT, MRI 2) Then add the 7 studies 3) Save | F47: Modalities first, then studies linked to them, all with fees. | H47: 4 modalities + 7 studies | I47: OPD Rx chips; Radiology; PCPNDT | J47: Registration complete | N47: Modalities MUST exist before studies - order matters | O47: P1-Setup | P47: Radiology studies cannot exist without a modality. Getting the order wrong produces 'No studies configured'. | Q47: Positive | R47: hospital_admin A | S47: radiology_modalities; radiology_study_master | T47: e2e/phase-01-foundation/P1B.onboarding.spec.ts
A48: TC-P1B-022 | B48: 1B Onboarding | C48: P2 | D48: Step 11 Payments configures payment modes | E48: 1) Configure the accepted payment modes 2) Save | F48: Saved. | H48: cash/UPI/card/NEFT | I48: Billing - payments | J48: Registration complete | O48: P1-Setup | P48: UPI is how most Indian patients pay now. Not offering it means cash queues at the counter. | Q48: Positive | R48: hospital_admin A | S48: api_configurations | T48: MANUAL-ONLY
A49: TC-P1B-023 | B49: 1B Onboarding | C49: P3 | D49: Step 12 WhatsApp can be skipped | E49: 1) At WhatsApp click Skip | F49: Advances without configuring. | H49: None | I49: Notifications | J49: Registration complete | N49: WARNING - unconfigured WhatsApp makes ALL notifications silently no-op | O49: P1-Setup | P49: WhatsApp is optional to configure but its absence is invisible - nothing errors, messages just never send. | Q49: Positive | R49: hospital_admin A | S49: None | T49: MANUAL-ONLY
A50: TC-P1B-024 | B50: 1B Onboarding | C50: P2 | D50: Step 13 Modules reflects the chosen plan | E50: 1) At Modules observe which are enabled 2) Compare against the Professional plan | F50: Only modules included in the plan are enabled. | H50: Professional plan | I50: All modules | J50: Registration + plan | O50: P1-Setup | P50: A customer seeing modules they did not pay for, or missing ones they did, is an immediate support ticket. | Q50: Positive | R50: hospital_admin A | S50: hospital_module_entitlements | T50: e2e/phase-01-foundation/P1B.onboarding.spec.ts
A51: TC-P1B-025 | B51: 1B Onboarding | C51: P2 | D51: Step 14 Go Live completes onboarding | E51: 1) Review the checklist 2) Complete onboarding | F51: Redirected to /dashboard. Wizard does not reappear on next login. | H51: None | I51: All | J51: All prior steps | O51: P1-Setup | P51: Onboarding that reappears after completion makes the product feel broken. | Q51: Positive | R51: hospital_admin A | S51: hospitals - onboarding flag | T51: e2e/phase-01-foundation/P1B.onboarding.spec.ts
A52: TC-P1B-026 | B52: 1B Onboarding | C52: P2 | D52: Wizard resumes at the correct step after logout | E52: 1) Complete up to step 5 2) Log out 3) Log back in | F52: Resumes at step 6 with earlier data intact. | H52: Partial Hospital A | J52: Registration complete | O52: P1-Setup | P52: Onboarding a hospital takes hours and spans sessions. Losing progress means starting over. | Q52: Positive | R52: hospital_admin A | S52: hospitals | T52: e2e/phase-01-foundation/P1B.onboarding.spec.ts
A53: TC-P1B-027 | B53: 1B Onboarding | C53: P2 | D53: Repeat full onboarding for Hospital B | E53: 1) Log in as +qa.admin.b 2) Complete onboarding with a minimal Hospital B config (2 departments, 1 ward, 4 beds, 1 doctor, 1 service) | F53: Hospital B is usable for isolation testing. | H53: Hospital B minimal set | I53: Isolation testing | J53: Hospital B registered | N53: Only needs enough data to prove isolation | O53: P1-Setup | P53: Hospital B needs real data in it, or a cross-tenant test proves nothing - an empty result is not the same as a blocked one. | Q53: Positive | R53: hospital_admin B | S53: departments/wards/beds for hospital B | T53: e2e/phase-01-foundation/P1B.onboarding.spec.ts
A54: TC-P1C-001 | B54: 1C Login | C54: P2 | D54: Valid login succeeds | E54: 1) Go to /login 2) Enter +qa.admin.a and TestPass@2026 3) Submit | F54: Logged in and redirected to /dashboard. | H54: Hospital A admin | I54: All | J54: Registration + email verified | O54: P1-Setup | P54: If login does not work nothing else matters. | Q54: Positive | R54: hospital_admin A | S54: audit_log action='LOGIN' | T54: e2e/phase-01-foundation/P1C.login.spec.ts
A55: TC-P1C-002 | B55: 1C Login | C55: P2 | D55: Wrong password is rejected | E55: 1) Enter the correct email with password WrongPass@2026 2) Submit | F55: Rejected with a generic message. NOTE: the message must not reveal whether the email exists. | H55: WrongPass@2026 | J55: Registration complete | O55: P1-Setup | P55: A message distinguishing 'wrong password' from 'no such user' lets an attacker enumerate every staff email. | Q55: Negative | R55: Logged out | S55: audit_log | T55: e2e/phase-01-foundation/P1C.login.spec.ts
A56: TC-P1C-003 | B56: 1C Login | C56: P2 | D56: Unknown email is rejected identically | E56: 1) Enter nosuchuser@example.com with any password 2) Compare the message to TC-P1C-002 | F56: The message is identical to the wrong-password message. | H56: nosuchuser@example.com | J56: None | O56: P1-Setup | P56: Same reason as above - differing messages leak your entire user list. | Q56: Negative | R56: Logged out | S56: None | T56: e2e/phase-01-foundation/P1C.login.spec.ts
A57: TC-P1C-004 | B57: 1C Login | C57: P2 | D57: Empty credentials are rejected | E57: 1) Submit with both fields blank | F57: Blocked with validation messages. | H57: blank | J57: None | O57: P1-Setup | P57: Basic input validation - an empty submit should never reach the server. | Q57: Negative | R57: Logged out | S57: None | T57: e2e/phase-01-foundation/P1C.login.spec.ts
A58: TC-P1C-005 | B58: 1C Login | C58: P1 | D58: Unverified email cannot log in | E58: 1) Register a new admin 2) Do NOT click the verification link 3) Try to log in | F58: Login blocked with a verify-your-email message. | H58: fresh unverified account | J58: None | O58: P1-Setup | P58: Unverified accounts let anyone register using someone else's email address. | Q58: Negative | R58: Logged out | S58: auth.users email_confirmed_at | T58: MANUAL-ONLY
A59: TC-P1C-006 | B59: 1C Login | C59: P1 | D59: Deactivated user is signed out | E59: 1) Log in as +qa.nurse.a 2) As admin in another browser set that user is_active=false 3) Refresh the nurse session | F59: Nurse is force signed out. HospitalContext signs out when users.is_active is false. | H59: #NAME? | I59: All | J59: Staff created | O59: P1-Setup | P59: When a staff member is terminated their access must end immediately, not at their next voluntary logout. | Q59: Negative | R59: nurse A | S59: users.is_active | T59: e2e/phase-01-foundation/P1C.login.spec.ts
A60: TC-P1C-007 | B60: 1C Login | C60: P1 | D60: Deactivated user cannot log back in | E60: 1) After TC-P1C-006 try to log in as the nurse | F60: Login refused. | H60: #NAME? | J60: Staff created | O60: P1-Setup | P60: A terminated employee logging back in the next day is a serious security and PHI exposure. | Q60: Negative | R60: Logged out | S60: users.is_active=false | T60: e2e/phase-01-foundation/P1C.login.spec.ts
A61: TC-P1C-008 | B61: 1C Login | C61: P2 | D61: Password reset email is sent | E61: 1) At /login click Forgot Password 2) Enter +qa.doctor.a 3) Submit | F61: Confirmation shown and a reset email arrives. | H61: #NAME? | J61: Staff created | O61: P1-Setup | P61: Staff forget passwords constantly. Without self-service reset every one becomes a support call. | Q61: Positive | R61: Logged out | S61: None | T61: MANUAL-ONLY
A62: TC-P1C-009 | B62: 1C Login | C62: P2 | D62: Password reset link works | E62: 1) Open the reset link 2) Set NewTestPass@2026 3) Log in with it | F62: Password changed and the new one works. | H62: NewTestPass@2026 | J62: Staff created | N62: Reset it back to TestPass@2026 afterwards | O62: P1-Setup | P62: A reset flow that emails a link but does not actually change the password is worse than none. | Q62: Positive | R62: Logged out | S62: None | T62: MANUAL-ONLY
A63: TC-P1C-010 | B63: 1C Login | C63: P2 | D63: Reset link cannot be reused | E63: 1) Use a reset link successfully 2) Open the same link again | F63: Rejected as already used or expired. | H63: used reset link | J63: Staff created | O63: P1-Setup | P63: A reusable reset link in an inbox is a permanent backdoor into that account. | Q63: Negative | R63: Logged out | S63: None | T63: MANUAL-ONLY
A64: TC-P1C-011 | B64: 1C Login | C64: P2 | D64: Session persists across a refresh | E64: 1) Log in 2) Press F5 | F64: Still logged in on the same page. | H64: any login | J64: Staff created | O64: P1-Setup | P64: Being logged out by a page refresh mid-consultation loses the doctor's work. | Q64: Positive | R64: doctor A | S64: None | T64: e2e/phase-01-foundation/P1C.login.spec.ts
A65: TC-P1C-012 | B65: 1C Login | C65: P2 | D65: Session persists across a new tab | E65: 1) Log in 2) Open /dashboard in a new tab | F65: Logged in in the new tab too. | H65: any login | J65: Staff created | O65: P1-Setup | P65: Clinical staff routinely work across several tabs. | Q65: Positive | R65: doctor A | S65: None | T65: MANUAL-ONLY
A66: TC-P1C-013 | B66: 1C Login | C66: P1 | D66: Logout clears the session and context cache | E66: 1) Log in 2) Log out 3) Check sessionStorage for hms_ctx_* keys 4) Press browser Back | F66: Session ended, hms_ctx_* cleared, and Back does not restore an authenticated view. | H66: any login | J66: Staff created | N66: The context cache is only cleared on sign-out - this is why TC-P1H-012 exists | O66: P1-Setup | P66: On a shared nursing-station computer, a session that survives logout exposes the previous user's patients. | Q66: Positive | R66: any | S66: None | T66: e2e/phase-01-foundation/P1C.login.spec.ts
A67: TC-P1C-014 | B67: 1C Login | C67: P1 | D67: Protected route redirects when logged out | E67: 1) Log out 2) Navigate directly to /patients | F67: Redirected to /login. Patient data never renders. | H67: None | I67: Patients | J67: None | O67: P1-Setup | P67: Direct URL entry is the first thing anyone tries. If it works logged out you have no access control at all. | Q67: Negative | R67: Logged out | S67: None | T67: e2e/phase-01-foundation/P1C.login.spec.ts
A68: TC-P1C-015 | B68: 1C Login | C68: P1 | D68: Every protected route redirects when logged out | E68: 1) Logged out, try /dashboard /opd /ipd /billing /lab /radiology /pharmacy /settings /accounts /platform | F68: All redirect to /login. None render data. | H68: None | I68: All | J68: None | O68: P1-Setup | P68: One unguarded route is enough to expose the whole database. | Q68: Negative | R68: Logged out | S68: None | T68: e2e/phase-01-foundation/P1C.login.spec.ts
A69: TC-P1C-016 | B69: 1C Login | C69: P2 | D69: Login audit row is written | E69: 1) Log in as +qa.doctor.a 2) Query audit_log | F69: A LOGIN row exists with the user and timestamp. | H69: #NAME? | I69: Quality - audit trail | J69: Staff created | O69: P1-Setup | P69: NABH and DPDP both require knowing who accessed the system and when. | Q69: Positive | R69: doctor A | S69: audit_log action='LOGIN' | T69: e2e/phase-01-foundation/P1C.login.spec.ts
A70: TC-P1C-017 | B70: 1C Login | C70: P2 | D70: Landing route matches the role | E70: 1) Log in as each of the 16 roles 2) Note where each lands | F70: Each role lands on a route it is permitted to see - never a blank or a 403. | H70: All 16 logins | I70: All | J70: Staff created | N70: Cross-check against the Mock Data Book landing column | O70: P1-Setup | P70: A pharmacist landing on a page they cannot access looks like a broken product on day one. | Q70: Positive | R70: all 16 | S70: None | T70: e2e/phase-01-foundation/P1C.login.spec.ts
A71: TC-P1C-018 | B71: 1C Login | C71: P3 | D71: Login page renders on a tablet | E71: 1) Open /login at 768px width | F71: Usable without horizontal scroll. | H71: None | J71: None | N71: Tablet-first is the design target for nurse stations | O71: P1-Setup | P71: Nurse stations and ward rounds run on tablets, not desktops. | Q71: Positive | R71: Logged out | S71: None | T71: MANUAL-ONLY
A72: TC-P1D-001 | B72: 1D Staff Logins | C72: P2 | D72: Enable Login creates a working account | E72: 1) Settings > Staff 2) Select Dr. Suresh Menon 3) Enable Login with +qa.doctor.a 4) Save 5) Log in as that user | F72: Account created and login succeeds. | H72: #NAME? | I72: All | J72: Staff created | N72: Uses the create-staff-login edge function | O72: P1-Setup | P72: Every clinical action must be attributable to a named person. Shared logins destroy the audit trail and fail NABH. | Q72: Positive | R72: hospital_admin A | S72: users - auth_user_id populated | T72: e2e/phase-01-foundation/P1D.staff-logins.spec.ts
A73: TC-P1D-002 | B73: 1D Staff Logins | C73: P1 | D73: New staff user gets the correct hospital_id | E73: 1) After TC-P1D-001 2) Query the users row | F73: hospital_id matches Hospital A. | H73: #NAME? | I73: All - RLS anchor | J73: Staff created | N73: users.hospital_id is what every RLS policy keys off | O73: P1-Setup | P73: This one column decides everything that user can ever see. Wrong and they either see nothing or see another hospital's patients. | Q73: Positive | R73: hospital_admin A | S73: users.hospital_id | T73: e2e/phase-01-foundation/P1D.staff-logins.spec.ts
A74: TC-P1D-003 | B74: 1D Staff Logins | C74: P2 | D74: Create all 17 Hospital A logins | E74: 1) Enable Login for every staff member in the Mock Data Book Hospital A table | F74: All 17 accounts created and each can log in. | H74: 17 Hospital A logins | I74: All | J74: Staff created | N74: Required before Section 1E can run | O74: P1-Setup | P74: The RBAC matrix cannot be tested without one real login per role. | Q74: Positive | R74: hospital_admin A | S74: users - 17 rows with auth_user_id | T74: e2e/phase-01-foundation/P1D.staff-logins.spec.ts
A75: TC-P1D-004 | B75: 1D Staff Logins | C75: P2 | D75: Create the 3 Hospital B logins | E75: 1) As Hospital B admin enable login for its doctor and receptionist | F75: 3 accounts for Hospital B. | H75: 3 Hospital B logins | I75: Isolation | J75: Hospital B onboarded | O75: P1-Setup | P75: Isolation testing needs a real logged-in user on the other side, not just data. | Q75: Positive | R75: hospital_admin B | S75: users WHERE hospital_id = B | T75: e2e/phase-01-foundation/P1D.staff-logins.spec.ts
A76: TC-P1D-005 | B76: 1D Staff Logins | C76: P2 | D76: Duplicate email is rejected | E76: 1) Try to enable login for a second staff member with +qa.doctor.a | F76: Rejected as already in use. | H76: #NAME? | J76: Staff created | O76: P1-Setup | P76: Two staff sharing one email means one of them can reset the other's password. | Q76: Negative | R76: hospital_admin A | S76: users | T76: e2e/phase-01-foundation/P1D.staff-logins.spec.ts
A77: TC-P1D-006 | B77: 1D Staff Logins | C77: P2 | D77: Role can be changed after creation | E77: 1) Change a staff member's role from nurse to receptionist 2) Have them log in again | F77: New role applies and the visible navigation changes. | H77: #NAME? | I77: All | J77: Staff created | N77: Change it back afterwards | O77: P1-Setup | P77: Staff move between departments. A role that cannot be changed means deleting and recreating the user, losing their audit history. | Q77: Positive | R77: hospital_admin A | S77: users.role | T77: MANUAL-ONLY
A78: TC-P1D-007 | B78: 1D Staff Logins | C78: P2 | D78: Staff can be deactivated | E78: 1) Set a staff member inactive 2) Verify they cannot log in | F78: Deactivation is immediate and effective. | H78: #NAME? | I78: All | J78: Staff created | O78: P1-Setup | P78: Offboarding must actually remove access on the day it happens. | Q78: Positive | R78: hospital_admin A | S78: users.is_active | T78: e2e/phase-01-foundation/P1D.staff-logins.spec.ts
A79: TC-P1D-008 | B79: 1D Staff Logins | C79: P2 | D79: Reactivated staff can log in again | E79: 1) Reactivate the user from TC-P1D-007 2) Log in | F79: Access restored. | H79: #NAME? | J79: Staff created | O79: P1-Setup | P79: Staff return from long leave - reactivation must work without recreating the account. | Q79: Positive | R79: hospital_admin A | S79: users.is_active | T79: MANUAL-ONLY
A80: TC-P1D-009 | B80: 1D Staff Logins | C80: P1 | D80: Staff list is scoped to the hospital | E80: 1) As Hospital A admin open Settings > Staff 2) Search for Hospital B staff names | F80: Only Hospital A staff are listed. No Hospital B user appears. | H80: Dr. Rohan Kulkarni (B) | I80: Isolation | J80: Both hospitals staffed | O80: P1-Setup | P80: Seeing another hospital's staff list is itself a data leak, before you even reach patients. | Q80: Negative | R80: hospital_admin A | S80: users filtered by hospital_id | T80: e2e/phase-01-foundation/P1D.staff-logins.spec.ts
A81: TC-P1D-010 | B81: 1D Staff Logins | C81: P2 | D81: Staff profile fields save | E81: 1) Add qualification, registration number and department to a doctor 2) Save | F81: All fields persisted. | H81: MBBS MD / TSMC-12345 | I81: HR - credentialing | J81: Staff created | O81: P1-Setup | P81: NABH requires proof that the doctor performing a procedure is registered and qualified to do it. | Q81: Positive | R81: hospital_admin A | S81: staff_profiles | T81: MANUAL-ONLY
A82: TC-P1D-011 | B82: 1D Staff Logins | C82: P1 | D82: Doctor creation also creates a consultation fee row | E82: 1) Create a new doctor with a fee of Rs 600 2) Check service_master | F82: A consultation row exists for that doctor at Rs 600. | H82: Rs 600 | I82: OPD billing | J82: Departments created | O82: P1-Setup | P82: A doctor with no fee row causes the hardcoded Rs 500 fallback for every one of their patients. | Q82: Positive | R82: hospital_admin A | S82: service_master WHERE doctor_id | T82: e2e/phase-01-foundation/P1D.staff-logins.spec.ts
A83: TC-P1D-012 | B83: 1D Staff Logins | C83: P2 | D83: Password reset for a staff member | E83: 1) Admin triggers a password reset for a staff member | F83: Reset email sent to that staff member. | H83: #NAME? | J83: Staff created | O83: P1-Setup | P83: Ward staff forget passwords weekly. The admin needs to fix it without calling you. | Q83: Positive | R83: hospital_admin A | S83: None | T83: MANUAL-ONLY
A84: TC-P1D-013 | B84: 1D Staff Logins | C84: P1 | D84: Non-admin cannot open Settings > Staff | E84: 1) Log in as +qa.nurse.a 2) Navigate to /settings/staff | F84: Blocked or redirected. | H84: #NAME? | J84: Staff created | O84: P1-Setup | P84: A nurse who can create logins can create an admin account for themselves. | Q84: RBAC | R84: nurse A | S84: None | T84: e2e/phase-01-foundation/P1D.staff-logins.spec.ts
A85: TC-P1D-014 | B85: 1D Staff Logins | C85: P2 | D85: Staff count reflects the plan limit | E85: 1) Check whether the plan caps user count 2) Attempt to exceed it if capped | F85: Either enforced with a clear message or documented as uncapped. | H85: 17 users | I85: Settings - Plan | J85: Plan set | O85: P1-Setup | P85: If seats are part of your pricing, an unenforced limit is revenue you never collect. | Q85: Boundary | R85: hospital_admin A | S85: hospital_subscriptions | T85: MANUAL-ONLY
A86: TC-P1D-015 | B86: 1D Staff Logins | C86: P2 | D86: Roles offered match the app_role enum | E86: 1) Open the role dropdown when creating a staff member 2) List every option offered | F86: Compare against the 16 enum values in the Mock Data Book. | H86: role dropdown | I86: All | J86: Staff screen | N86: See the Mock Data Book warning - 32 roles are used in routing but are not in the enum | O86: P1-Setup | P86: Modules like Blood Bank and Dialysis name a specialist role as their user, but that role cannot be created. Confirm whether this is intended before logging it. | Q86: Negative | R86: hospital_admin A | S86: SELECT unnest(enum_range(NULL::app_role)) | T86: e2e/phase-01-foundation/P1D.staff-logins.spec.ts
A87: TC-P1D-016 | B87: 1D Staff Logins | C87: P1 | D87: Creating a role outside the enum fails cleanly | E87: 1) If the UI offers a role such as quality_officer, select it and save | F87: Either it saves via a permission blob rather than the enum, or it errors. It must not fail silently leaving a user with no role. | H87: quality_officer | I87: All | J87: Staff screen | N87: Related to TC-P1D-015 | O87: P1-Setup | P87: A user saved with no usable role can log in and see nothing, which looks like a broken product. | Q87: Negative | R87: hospital_admin A | S87: users.role | T87: MANUAL-ONLY
A88: TC-P1E-001 | B88: 1E RBAC | C88: P2 | D88: hospital_admin reaches all core routes | E88: 1) Log in as +qa.admin.a 2) Visit /dashboard /patients /opd /ipd /lab /radiology /pharmacy /billing /accounts /insurance /hr /inventory /settings | F88: All load. hospital_admin is a bypass role. | H88: #NAME? | I88: All | J88: All staff created | N88: BYPASS_ROLES = super_admin, hospital_admin | O88: P1-Setup | P88: The admin is the person who configures everything. Blocking them anywhere makes the hospital unusable. | Q88: Positive | R88: hospital_admin A | S88: None | T88: e2e/phase-01-foundation/P1E.rbac-route-matrix.spec.ts
A89: TC-P1E-002 | B89: 1E RBAC | C89: P2 | D89: doctor reaches clinical routes | E89: 1) Log in as +qa.doctor.a 2) Visit /dashboard /opd /ipd /patients /lab /radiology /schedule | F89: All load. | H89: #NAME? | I89: Clinical | J89: All staff created | O89: P1-Setup | P89: A doctor blocked from the OPD queue cannot see patients. | Q89: Positive | R89: doctor A | S89: None | T89: e2e/phase-01-foundation/P1E.rbac-route-matrix.spec.ts
A90: TC-P1E-003 | B90: 1E RBAC | C90: P1 | D90: doctor is blocked from /hr | E90: 1) As +qa.doctor.a navigate to /hr | F90: Blocked or redirected. Payroll data never renders. | H90: #NAME? | I90: HR | J90: All staff created | O90: P1-Setup | P90: A doctor seeing every colleague's salary is a serious HR incident. | Q90: RBAC | R90: doctor A | S90: None | T90: e2e/phase-01-foundation/P1E.rbac-route-matrix.spec.ts
A91: TC-P1E-004 | B91: 1E RBAC | C91: P1 | D91: doctor is blocked from /accounts | E91: 1) As +qa.doctor.a navigate to /accounts | F91: Blocked or redirected. | H91: #NAME? | I91: Accounts | J91: All staff created | O91: P1-Setup | P91: The hospital's P&L is not clinical information. | Q91: RBAC | R91: doctor A | S91: None | T91: e2e/phase-01-foundation/P1E.rbac-route-matrix.spec.ts
A92: TC-P1E-005 | B92: 1E RBAC | C92: P1 | D92: doctor is blocked from /settings | E92: 1) As +qa.doctor.a navigate to /settings | F92: Blocked. Only /settings/profile is reachable as a core route. | H92: #NAME? | I92: Settings | J92: All staff created | N92: coreRoutes includes /settings/profile for everyone | O92: P1-Setup | P92: A doctor who can change consultation fees or permissions can change their own pay and access. | Q92: RBAC | R92: doctor A | S92: None | T92: e2e/phase-01-foundation/P1E.rbac-route-matrix.spec.ts
A93: TC-P1E-006 | B93: 1E RBAC | C93: P2 | D93: nurse reaches nursing and clinical routes | E93: 1) As +qa.nurse.a visit /dashboard /nursing /ipd /patients | F93: All load. | H93: #NAME? | I93: Clinical | J93: All staff created | O93: P1-Setup | P93: Nurses are the heaviest users of the system. | Q93: Positive | R93: nurse A | S93: None | T93: e2e/phase-01-foundation/P1E.rbac-route-matrix.spec.ts
A94: TC-P1E-007 | B94: 1E RBAC | C94: P1 | D94: nurse is blocked from /billing /accounts /hr | E94: 1) As +qa.nurse.a try each route | F94: All blocked. | H94: #NAME? | I94: Finance HR | J94: All staff created | O94: P1-Setup | P94: Clinical staff must not be able to alter bills - it removes the separation between care and money. | Q94: RBAC | R94: nurse A | S94: None | T94: e2e/phase-01-foundation/P1E.rbac-route-matrix.spec.ts
A95: TC-P1E-008 | B95: 1E RBAC | C95: P2 | D95: receptionist reaches front-desk routes | E95: 1) As +qa.reception.a visit /dashboard /patients /opd /schedule | F95: All load. | H95: #NAME? | I95: Patients OPD | J95: All staff created | O95: P1-Setup | P95: The front desk is the entry point for every patient. | Q95: Positive | R95: receptionist A | S95: None | T95: e2e/phase-01-foundation/P1E.rbac-route-matrix.spec.ts
A96: TC-P1E-009 | B96: 1E RBAC | C96: P1 | D96: receptionist is blocked from /ipd /lab /pharmacy /accounts | E96: 1) As +qa.reception.a try each | F96: All blocked. | H96: #NAME? | I96: Clinical Finance | J96: All staff created | O96: P1-Setup | P96: Front-desk staff have no clinical training and no reason to see ward or lab data. | Q96: RBAC | R96: receptionist A | S96: None | T96: e2e/phase-01-foundation/P1E.rbac-route-matrix.spec.ts
A97: TC-P1E-010 | B97: 1E RBAC | C97: P2 | D97: pharmacist reaches /pharmacy | E97: 1) As +qa.pharmacist.a visit /pharmacy | F97: Loads with both IP and retail modes. | H97: #NAME? | I97: Pharmacy | J97: All staff created | O97: P1-Setup | P97: Pharmacy is the pharmacist's only workplace in the app. | Q97: Positive | R97: pharmacist A | S97: None | T97: e2e/phase-01-foundation/P1E.rbac-route-matrix.spec.ts
A98: TC-P1E-011 | B98: 1E RBAC | C98: P1 | D98: pharmacist is blocked from /ipd /billing /hr | E98: 1) As +qa.pharmacist.a try each | F98: All blocked. | H98: #NAME? | I98: IPD Finance | J98: All staff created | O98: P1-Setup | P98: A pharmacist who can edit bills can adjust the price of what they dispensed. | Q98: RBAC | R98: pharmacist A | S98: None | T98: e2e/phase-01-foundation/P1E.rbac-route-matrix.spec.ts
A99: TC-P1E-012 | B99: 1E RBAC | C99: P2 | D99: lab_technician reaches /lab | E99: 1) As +qa.labtech.a visit /lab | F99: Loads. | H99: #NAME? | I99: Lab | J99: All staff created | O99: P1-Setup | P99: Lab staff need the lab. | Q99: Positive | R99: lab_technician A | S99: None | T99: e2e/phase-01-foundation/P1E.rbac-route-matrix.spec.ts
A100: TC-P1E-013 | B100: 1E RBAC | C100: P2 | D100: lab_tech role also reaches /lab | E100: 1) As +qa.labtech2.a (role lab_tech) visit /lab | F100: Loads. Both lab_tech and lab_technician are permitted. | H100: #NAME? | I100: Lab | J100: All staff created | N100: Two enum values exist for the same job - worth confirming this is deliberate | O100: P1-Setup | P100: Two roles meaning the same thing is a maintenance trap - if one is missed in a permission update, half your lab staff lose access. | Q100: Positive | R100: lab_tech A | S100: None | T100: e2e/phase-01-foundation/P1E.rbac-route-matrix.spec.ts
...

Sheet Phase 02 Settings & Masters
A1: TC# | B1: Section | C1: Priority | D1: Test Case | E1: Steps | F1: Expected Result | G1: Status(PASS/FAIL/BLOCKED) | H1: mock data | I1: Cross-Module Link | J1: Settings need to set before entering to the module | K1: Actual Result(What happened) | L1: Console Error(Copy-paste red text) | M1: Screenshot(Y/N) | N1: Notes | O1: Journey Scenario | P1: Why This Exists | Q1: Test Type | R1: Role/Login | S1: Supabase Verify | T1: Playwright Spec | U1: Defect ID | V1: Stages Passed / Total
A2: TC-P2A-001 | B2: 2A Settings Hub | C2: P2 | D2: Settings hub loads with heading, subtitle and search box | E2: 1) Log in as hospital_admin (Hospital A) 2) Open /settings 3) Observe the header | F2: Heading "Settings" and subtitle "Configure your hospital system" render, with a search box placeholdered "Search settings or a module…". No red console errors. | G2: PASS | H2: Staff logins — hospital_admin (Hospital A) | I2: All modules | J2: Tier 0: hospital_admin can reach /settings (Phase 1 §1E) | K2: Automated: passed. | M2: N | O2: P2-Setup | P2: The hub is the only doorway to all 50 configuration screens. If it fails to render, a hospital cannot configure anything and go-live stops dead. | Q2: Positive | R2: hospital_admin (Hospital A) | S2: None — pure UI render | T2: e2e/phase-02-settings/P2A.hub.spec.ts
A3: TC-P2A-002 | B3: 2A Settings Hub | C3: P1 | D3: Every routable /settings/* route has a catalogue entry | E3: 1) Open /settings 2) Compare the rendered card routes against the 50 settings routes registered in src/App.tsx | F3: All 50 App.tsx /settings/* routes appear in the catalogue. Zero routes are reachable only by typing the URL. | G3: PASS | H3: settings.helpers.ts SETTINGS_SCREENS (50 routes) | I3: All modules | J3: None | K3: Automated: passed. | M3: N | O3: P2-Setup | P3: settingsCatalog.ts exists because six settings routes once had no card and were unreachable by browsing OR search. A screen a hospital cannot find is a screen it never configures, and every silent-fallback defect downstream starts there. | Q3: Cross-Module | R3: hospital_admin (Hospital A) | S3: None — compares App.tsx routes to the rendered catalogue | T3: e2e/phase-02-settings/P2A.hub.spec.ts
A4: TC-P2A-003 | B4: 2A Settings Hub | C4: P3 | D4: Two alias cards point at a route another card already owns | E4: 1) Open /settings 2) Count the rendered cards 3) Locate "Self-Service Kiosk" and "WhatsApp / WATI" | F4: 52 cards render for 50 distinct routes. "Self-Service Kiosk" opens /settings/tv-display and "WhatsApp / WATI" opens /settings/whatsapp — the same routes as "TV Queue Display" and "WhatsApp Bot". | G4: FAIL | H4: settings.helpers.ts ALIAS_CARDS | I4: TV Display, CRM | J4: None | K4: Automated: FAILED. Error: Alias card "Self-Service Kiosk" is missing from the hub expect(received).toContain(expected) // indexOf Expected value: "Self-Service Kiosk" Received array: [] | M4: Y | O4: P2-Setup | P4: One route legitimately serves two jobs, so a receptionist searching "kiosk" still lands somewhere useful. Recorded deliberately so a future card count of 52 against 50 routes is not mistaken for a duplicate-registration bug. | Q4: Positive | R4: hospital_admin (Hospital A) | S4: None — pure UI render | T4: e2e/phase-02-settings/P2A.hub.spec.ts
A5: TC-P2A-004 | B5: 2A Settings Hub | C5: P3 | D5: Groups render in the declared SETTINGS_GROUP_ORDER | E5: 1) Open /settings 2) Read the group headings top to bottom | F5: Groups appear in order: Identity, Plan & Modules, Structure, People & Access, Clinical, Queue Display & Kiosk, Workflows, Integrations, Inventory & Stores, Audit & Compliance, Go-Live & Migration. | G5: FAIL | H5: settingsCatalog.ts SETTINGS_GROUP_ORDER | I5: All modules | J5: None | K5: Automated: FAILED. Error: Group heading(s) missing from the hub: Identity, Plan & Modules, Structure, People & Access, Queue Display & Kiosk, Workflows, Inventory & Stores, Audit & Compliance, Go-Live & Migration expect(received).toEqual(expected) // deep equality - Expected - 1 + Received + 11 - Array [] + Array [ + "Identity", + "Plan & Modules", + "Structure", + "People & Access", + "Queue Display & Kiosk", + "Workflows", + "Inventory & Stores", + "Audit & Compliance", + "Go-Live & Migration", + ] | M5: Y | O5: P2-Setup | P5: The order is the configuration order — Identity and Structure must come before Clinical, or an administrator works the grid top to bottom and hits prerequisites that do not exist yet. | Q5: Positive | R5: hospital_admin (Hospital A) | S5: None — pure UI render | T5: e2e/phase-02-settings/P2A.hub.spec.ts
A6: TC-P2A-005 | B6: 2A Settings Hub | C6: P2 | D6: Clicking the Departments card navigates to /settings/departments | E6: 1) Open /settings 2) Click the "Departments" card | F6: The browser lands on /settings/departments and the Departments screen renders. | G6: PASS | H6: settings.helpers.ts SETTINGS_SCREENS — /settings/departments | I6: OPD, IPD, HR | J6: None | K6: Automated: passed. | M6: N | O6: P2-Setup | P6: Cards are buttons, not links, so navigation is JavaScript. If a card stops navigating there is no href fallback and the screen becomes unreachable by browsing. | Q6: Positive | R6: hospital_admin (Hospital A) | S6: None — client-side navigation | T6: e2e/phase-02-settings/P2A.hub.spec.ts
A7: TC-P2A-006 | B7: 2A Settings Hub | C7: P2 | D7: Searching "pharmacy" surfaces the pages that actually configure Pharmacy | E7: 1) Open /settings 2) Type "pharmacy" into the search box | F7: Drug Formulary appears under direct matches, and cross-cutting pages that configure pharmacy (Configurable Dropdowns, Staff, IPD Ancillary Payment, Store Locations) appear in the separate "Also configures" bucket. | G7: PASS | H7: settingsCatalog.ts MODULE_ALIASES — pharmacy | I7: Pharmacy | J7: None | K7: Automated: passed. | M7: N | O7: P2-Setup | P7: Module-name search was rewritten because "pharmacy" used to return almost nothing — the word appears in none of the relevant card titles. An administrator who cannot find the drug route dropdown reports "OPD prescribing is broken" instead. | Q7: Positive | R7: hospital_admin (Hospital A) | S7: None — pure UI search | T7: e2e/phase-02-settings/P2A.hub.spec.ts
A8: TC-P2A-007 | B8: 2A Settings Hub | C8: P2 | D8: Searching the alias "pathology" surfaces Lab Test Master | E8: 1) Open /settings 2) Type "pathology" into the search box | F8: Lab Test Master appears in the results even though the word "pathology" is in neither its title nor its description. | G8: PASS | H8: settingsCatalog.ts MODULE_ALIASES — lab | I8: Lab | J8: None | K8: Automated: passed. | M8: N | O8: P2-Setup | P8: Indian hospitals say pathology, not laboratory. Matching only the product's own vocabulary means the people who need the screen cannot find it. | Q8: Positive | R8: hospital_admin (Hospital A) | S8: None — pure UI search | T8: e2e/phase-02-settings/P2A.hub.spec.ts
A9: TC-P2A-008 | B9: 2A Settings Hub | C9: P2 | D9: Searching the alias "theatre" surfaces the OT Checklist | E9: 1) Open /settings 2) Type "theatre" into the search box | F9: OT Checklist appears in the results. The Indian English spelling "theatre" matches, not only "theater". | G9: PASS | H9: settingsCatalog.ts MODULE_ALIASES — ot | I9: OT, Anaesthesia | J9: None | K9: Automated: passed. | M9: N | O9: P2-Setup | P9: Indian English is the house style for this product. A search that only answers to the American spelling fails the users it was written for. | Q9: Positive | R9: hospital_admin (Hospital A) | S9: None — pure UI search | T9: e2e/phase-02-settings/P2A.hub.spec.ts
A10: TC-P2A-009 | B10: 2A Settings Hub | C10: P2 | D10: Searching the alias "x-ray" surfaces Radiology Modalities | E10: 1) Open /settings 2) Type "x-ray" into the search box | F10: Radiology Modalities appears in the results. The hyphenated form matches. | G10: PASS | H10: settingsCatalog.ts MODULE_ALIASES — radiology | I10: Radiology | J10: None | K10: Automated: passed. | M10: N | O10: P2-Setup | P10: Radiology modalities must be created before studies, or the module shows "No studies configured". Users search for the machine name they know, not the word "modality". | Q10: Positive | R10: hospital_admin (Hospital A) | S10: None — pure UI search | T10: e2e/phase-02-settings/P2A.hub.spec.ts
A11: TC-P2A-010 | B11: 2A Settings Hub | C11: P2 | D11: Searching the alias "TPA" surfaces Payer Masters | E11: 1) Open /settings 2) Type "TPA" into the search box | F11: Payer Masters appears in the results, matched case-insensitively on the insurance alias. | G11: PASS | H11: settingsCatalog.ts MODULE_ALIASES — insurance | I11: Insurance, Billing | J11: None | K11: Automated: passed. | M11: N | O11: P2-Setup | P11: Without a payer master there is no insurance selection at admission, so every insured patient is booked as cash. Billing staff search "TPA" — that is the only word they use. | Q11: Positive | R11: hospital_admin (Hospital A) | S11: None — pure UI search | T11: e2e/phase-02-settings/P2A.hub.spec.ts
A12: TC-P2A-011 | B12: 2A Settings Hub | C12: P2 | D12: Searching the alias "ayushman" surfaces the PMJAY-related pages | E12: 1) Open /settings 2) Type "ayushman" into the search box | F12: Payer Masters and Configurable Dropdowns (government_schemes) appear in the results. | G12: PASS | H12: settingsCatalog.ts MODULE_ALIASES — pmjay | I12: PMJAY, Insurance, Billing | J12: None | K12: Automated: passed. | M12: N | O12: P2-Setup | P12: PMJAY empanelment is a common sales trigger, and Ayushman Bharat is the name every Indian hospital uses. Missing it means a new customer cannot configure the scheme that made them buy. | Q12: Positive | R12: hospital_admin (Hospital A) | S12: None — pure UI search | T12: e2e/phase-02-settings/P2A.hub.spec.ts
A13: TC-P2A-012 | B13: 2A Settings Hub | C13: P2 | D13: Searching the alias "payroll" surfaces the HR-related settings | E13: 1) Open /settings 2) Type "payroll" into the search box | F13: Staff Members and Shifts appear in the results via the HR alias. | G13: PASS | H13: settingsCatalog.ts MODULE_ALIASES — hr | I13: HR | J13: None | K13: Automated: passed. | M13: N | O13: P2-Setup | P13: Salary fields live on the Staff screen, not on a page called Payroll. Without the alias an HR manager cannot find where to enter them. | Q13: Positive | R13: hospital_admin (Hospital A) | S13: None — pure UI search | T13: e2e/phase-02-settings/P2A.hub.spec.ts
... A33: TC-P2B-012 | B33: 2B Identity | C33: P1 | D33: Hospital A's language settings are invisible to Hospital B | E33: 1) Sign in as the Hospital B administrator 2) Open /settings/language as Hospital B 3) Query hospital_settings through the API with no hospital filter | F33: Not one Hospital A hospital_settings row is returned, including the language_region key. | G33: PASS | H33: MOCK_DATA_BOOK Hospitals — Hospital A (Aarogya) and Hospital B (Sanjeevani) | I33: Multi-tenancy, all modules | J33: Both QA tenants seeded | K33: Automated: passed. | M33: N | O33: P2-Setup | P33: hospital_settings has no per-role RLS — any authenticated user of a hospital can write any key via PostgREST. Tenant isolation is therefore the only protection this table has, and it must be proven rather than assumed. | Q33: Cross-Module | R33: hospital_admin (Hospital B) | S33: hospital_settings queried as the Hospital B admin → zero rows with hospital_id = A | T33: e2e/phase-02-settings/P2B.identity.language.spec.ts
A34: TC-P2B-013 | B34: 2B Identity | C34: P1 | D34: A nurse cannot reach the Language & Region screen | E34: 1) Log in as nurse (Hospital A) 2) Navigate directly to /settings/language | F34: The route is blocked — redirected away, or an explicit access-denied message. | G34: FAIL | H34: MOCK_DATA_BOOK Staff logins — nurse (Hospital A), Sr. Mary Thomas | I34: All modules | J34: Tier 0 roles configured (Phase 1 §1E) | K34: Automated: FAILED. Error: A nurse reached /settings/language. Changing the date format changes how every date in the hospital renders, and the route guard is the only control here because hospital_settings has no per-role RLS. expect(received).toBeTruthy() Received: false | L34: Fetch user data error: JSON object requested, multiple (or no) rows returned Fetch user data error: JSON object requested, multiple (or no) rows returned Fetch user data error: JSON object requested, multiple (or no) rows returned | M34: Y | O34: P2-Setup | P34: Changing the date format changes how every date in the hospital renders. The route guard is the only control on this screen, because hospital_settings itself has no per-role RLS. | Q34: RBAC | R34: nurse (Hospital A) | S34: None — route guard behaviour | T34: e2e/phase-02-settings/P2B.identity.language.spec.ts
A35: TC-P2B-014 | B35: 2B Identity | C35: P2 | D35: Stored settings are loaded back into the form on open | E35: 1) Set Time Format to 24-hour and save 2) Navigate away to /settings 3) Return to /settings/language | F35: Time Format shows 24-hour on load — the form is populated from hospital_settings, not reset to the defaults. | G35: PASS | H35: phase2.entry./settings/language — timeFormat 24 | I35: All modules | J35: Tier 0: hospital profile created; hospital_admin can reach /settings | K35: Automated: passed. | M35: N | O35: P2-Setup | P35: A screen that saves but never reads back looks broken in a subtler way: the administrator sets the value, returns, sees the default, and sets it again — never knowing which one is live. | Q35: Positive | R35: hospital_admin (Hospital A) | S35: hospital_settings where hospital_id = A and key = 'language_region' → value.timeFormat = '24' | T35: e2e/phase-02-settings/P2B.identity.language.spec.ts
A36: TC-P2B-015 | B36: 2B Identity | C36: P2 | D36: A partially stored config merges with the shipped defaults | E36: 1) Store a language_region value containing only timeFormat 2) Open /settings/language 3) Read every control | F36: Time Format shows the stored value while the other five controls show their Indian defaults. No control renders blank or undefined. | G36: PASS | H36: src/lib/languageRegion.ts DEFAULT_LANGUAGE_REGION merged over a partial stored value | I36: All modules | J36: Tier 0: hospital profile created; hospital_admin can reach /settings | K36: Automated: passed. | M36: N | O36: P2-Setup | P36: A config saved before a new setting shipped will lack that key. Rendering it blank rather than defaulting means a hospital silently loses its currency or timezone on the next release. | Q36: Boundary | R36: hospital_admin (Hospital A) | S36: hospital_settings where hospital_id = A and key = 'language_region' → partial value merges without blanks | T36: e2e/phase-02-settings/P2B.identity.language.spec.ts
A37: TC-P2B-016 | B37: 2B Identity | C37: P1 | D37: Currency INR renders amounts with the rupee symbol | E37: 1) Open /settings/language 2) Confirm Currency is ₹ Indian Rupee (INR) 3) Open /settings/wards 4) Read a ward rate | F37: Ward rates render as ₹3,500.00 — the rupee symbol, not a bare number and not a dollar sign. | G37: FAIL | H37: MOCK_DATA_BOOK Wards — General Ward ₹1,500/day | I37: Billing, Accounts, IPD | J37: Tier 0: hospital profile created; hospital_admin can reach /settings | K37: Automated: FAILED. Error: No rupee symbol rendered on the Wards screen. Currency is chosen here and consumed by formatCurrency() everywhere else — if the two disconnect, a hospital sets INR and still sees unsymbolised numbers on every bill. expect(received).toBeTruthy() Received: false | M37: Y | O37: P2-Setup | P37: Currency is chosen here and consumed by formatCurrency() everywhere else. If the two disconnect, a hospital sets INR and still sees unsymbolised numbers on every bill. | Q37: Cross-Module | R37: hospital_admin (Hospital A) | S37: hospital_settings language_region value.currency = 'INR', and money renders with ₹ | T37: e2e/phase-02-settings/P2B.identity.language.spec.ts
A38: TC-P2B-017 | B38: 2B Identity | C38: P1 | D38: Number Format Indian renders lakh grouping | E38: 1) Open /settings/language 2) Confirm Number Format is Indian (1,00,000) 3) Open a screen showing an amount above ₹1,00,000 | F38: The amount renders as ₹1,25,000 — Indian grouping — not ₹125,000. | G38: PASS | H38: MOCK_DATA_BOOK Values used across many tests — ₹1,25,000 example | I38: Billing, Accounts | J38: Tier 0: hospital profile created; hospital_admin can reach /settings | K38: Automated: passed. | M38: N | O38: P2-Setup | P38: MOCK_DATA_BOOK states this explicitly: a screen that renders ₹125,000 instead of ₹1,25,000 is a defect. An Indian accountant reads the comma position, and the wrong one shifts the apparent value by an order of magnitude. | Q38: Cross-Module | R38: hospital_admin (Hospital A) | S38: hospital_settings language_region value.numberFormat = 'indian', and amounts group as 1,25,000 | T38: e2e/phase-02-settings/P2B.identity.language.spec.ts
A39: TC-P2B-018 | B39: 2B Identity | C39: P1 | D39: Language & region settings survive a reload | E39: 1) Open /settings/language 2) Set Interface Language to Telugu, Time Format to 24-hour and Currency to INR 3) Click "Save Changes" 4) Hard-reload the page 5) Read every control | F39: All three chosen values are still selected after the reload, having been read back from hospital_settings. | G39: PASS | H39: phase2.entry./settings/language — timeFormat 24, dateFormat DD/MM/YYYY, numberFormat indian | I39: All modules, Billing, MRD | J39: Tier 0: hospital profile created; hospital_admin can reach /settings | K39: Automated: passed. | M39: N | O39: P2-Setup | P39: REGRESSION LOCK for BUG-P2-004. This is the case MOCK_DATA_BOOK names for this screen: every field was enterable and selectable, the toast said saved, and none of it survived a reload. A hospital in Hyderabad could set Telugu and 24-hour time, be told it worked, and find English and 12-hour back the next morning. | Q39: Positive | R39: hospital_admin (Hospital A) | S39: hospital_settings where hospital_id = A and key = 'language_region' → value.language = 'te', timeFormat = '24', currency = 'INR' | T39: e2e/phase-02-settings/P2B.identity.language.spec.ts
A40: TC-P2B-019 | B40: 2B Identity | C40: P2 | D40: Interface Language "English" saves and survives a reload | E40: 1) Open /settings/language 2) Set Interface Language to "English" 3) Click "Save Changes" 4) Reload the page | F40: hospital_settings language_region value.language = 'en' and the dropdown still shows "English" after the reload. | G40: PASS | H40: phase2.dropdowns.interfaceLanguage — "English" (stored as 'en') | I40: All modules | J40: Tier 0: hospital profile created; hospital_admin can reach /settings | K40: Automated: passed. | M40: N | O40: P2-Setup | P40: Every language is tested individually because the visible label and the stored code differ — "English" stores as 'en', so a mapping error affects one language and not the others. This one matters as the default every other language falls back to. | Q40: Positive | R40: hospital_admin (Hospital A) | S40: hospital_settings where hospital_id = A and key = 'language_region' → value.language = 'en' | T40: e2e/phase-02-settings/P2B.identity.language.spec.ts
A41: TC-P2B-020 | B41: 2B Identity | C41: P2 | D41: Interface Language "Hindi (हिन्दी)" saves and survives a reload | E41: 1) Open /settings/language 2) Set Interface Language to "Hindi (हिन्दी)" 3) Click "Save Changes" 4) Reload the page | F41: hospital_settings language_region value.language = 'hi' and the dropdown still shows "Hindi (हिन्दी)" after the reload. | G41: PASS | H41: phase2.dropdowns.interfaceLanguage — "Hindi (हिन्दी)" (stored as 'hi') | I41: All modules | J41: Tier 0: hospital profile created; hospital_admin can reach /settings | K41: Automated: passed. | M41: N | O41: P2-Setup | P41: Every language is tested individually because the visible label and the stored code differ — "Hindi (हिन्दी)" stores as 'hi', so a mapping error affects one language and not the others. This one matters as the largest patient population outside the south. | Q41: Positive | R41: hospital_admin (Hospital A) | S41: hospital_settings where hospital_id = A and key = 'language_region' → value.language = 'hi' | T41: e2e/phase-02-settings/P2B.identity.language.spec.ts
A42: TC-P2B-021 | B42: 2B Identity | C42: P2 | D42: Interface Language "Telugu (తెలుగు)" saves and survives a reload | E42: 1) Open /settings/language 2) Set Interface Language to "Telugu (తెలుగు)" 3) Click "Save Changes" 4) Reload the page | F42: hospital_settings language_region value.language = 'te' and the dropdown still shows "Telugu (తెలుగు)" after the reload. | G42: PASS | H42: phase2.dropdowns.interfaceLanguage — "Telugu (తెలుగు)" (stored as 'te') | I42: All modules | J42: Tier 0: hospital profile created; hospital_admin can reach /settings | K42: Automated: passed. | M42: N | O42: P2-Setup | P42: Every language is tested individually because the visible label and the stored code differ — "Telugu (తెలుగు)" stores as 'te', so a mapping error affects one language and not the others. This one matters as the local language of Hospital A in Hyderabad. | Q42: Positive | R42: hospital_admin (Hospital A) | S42: hospital_settings where hospital_id = A and key = 'language_region' → value.language = 'te' | T42: e2e/phase-02-settings/P2B.identity.language.spec.ts
A43: TC-P2B-022 | B43: 2B Identity | C43: P2 | D43: Interface Language "Tamil (தமிழ்)" saves and survives a reload | E43: 1) Open /settings/language 2) Set Interface Language to "Tamil (தமிழ்)" 3) Click "Save Changes" 4) Reload the page | F43: hospital_settings language_region value.language = 'ta' and the dropdown still shows "Tamil (தமிழ்)" after the reload. | G43: PASS | H43: phase2.dropdowns.interfaceLanguage — "Tamil (தமிழ்)" (stored as 'ta') | I43: All modules | J43: Tier 0: hospital profile created; hospital_admin can reach /settings | K43: Automated: passed. | M43: N | O43: P2-Setup | P43: Every language is tested individually because the visible label and the stored code differ — "Tamil (தமிழ்)" stores as 'ta', so a mapping error affects one language and not the others. This one matters as Tamil Nadu, where MLC reporting differs from Maharashtra. | Q43: Positive | R43: hospital_admin (Hospital A) | S43: hospital_settings where hospital_id = A and key = 'language_region' → value.language = 'ta' | T43: e2e/phase-02-settings/P2B.identity.language.spec.ts
A44: TC-P2B-023 | B44: 2B Identity | C44: P2 | D44: Interface Language "Kannada (ಕನ್ನಡ)" saves and survives a reload | E44: 1) Open /settings/language 2) Set Interface Language to "Kannada (ಕನ್ನಡ)" 3) Click "Save Changes" 4) Reload the page | F44: hospital_settings language_region value.language = 'kn' and the dropdown still shows "Kannada (ಕನ್ನಡ)" after the reload. | G44: PASS | H44: phase2.dropdowns.interfaceLanguage — "Kannada (ಕನ್ನಡ)" (stored as 'kn') | I44: All modules | J44: Tier 0: hospital profile created; hospital_admin can reach /settings | K44: Automated: passed. | M44: N | O44: P2-Setup | P44: Every language is tested individually because the visible label and the stored code differ — "Kannada (ಕನ್ನಡ)" stores as 'kn', so a mapping error affects one language and not the others. This one matters as Karnataka, where the Arogya scheme applies. | Q44: Positive | R44: hospital_admin (Hospital A) | S44: hospital_settings where hospital_id = A and key = 'language_region' → value.language = 'kn' | T44: e2e/phase-02-settings/P2B.identity.language.spec.ts
A45: TC-P2B-024 | B45: 2B Identity | C45: P2 | D45: Interface Language "Malayalam (മലയാളം)" saves and survives a reload | E45: 1) Open /settings/language 2) Set Interface Language to "Malayalam (മലയാളം)" 3) Click "Save Changes" 4) Reload the page | F45: hospital_settings language_region value.language = 'ml' and the dropdown still shows "Malayalam (മലയാളം)" after the reload. | G45: PASS | H45: phase2.dropdowns.interfaceLanguage — "Malayalam (മലയാളം)" (stored as 'ml') | I45: All modules | J45: Tier 0: hospital profile created; hospital_admin can reach /settings | K45: Automated: passed. | M45: N | O45: P2-Setup | P45: Every language is tested individually because the visible label and the stored code differ — "Malayalam (മലയാളം)" stores as 'ml', so a mapping error affects one language and not the others. This one matters as Kerala, with the highest health literacy expectations. | Q45: Positive | R45: hospital_admin (Hospital A) | S45: hospital_settings where hospital_id = A and key = 'language_region' → value.language = 'ml' | T45: e2e/phase-02-settings/P2B.identity.language.spec.ts
A46: TC-P2B-025 | B46: 2B Identity | C46: P2 | D46: Interface Language "Marathi (मराठी)" saves and survives a reload | E46: 1) Open /settings/language 2) Set Interface Language to "Marathi (मराठी)" 3) Click "Save Changes" 4) Reload the page | F46: hospital_settings language_region value.language = 'mr' and the dropdown still shows "Marathi (मराठी)" after the reload. | G46: PASS | H46: phase2.dropdowns.interfaceLanguage — "Marathi (मराठी)" (stored as 'mr') | I46: All modules | J46: Tier 0: hospital profile created; hospital_admin can reach /settings | K46: Automated: passed. | M46: N | O46: P2-Setup | P46: Every language is tested individually because the visible label and the stored code differ — "Marathi (मराठी)" stores as 'mr', so a mapping error affects one language and not the others. This one matters as Maharashtra, the state Hospital B operates in. | Q46: Positive | R46: hospital_admin (Hospital A) | S46: hospital_settings where hospital_id = A and key = 'language_region' → value.language = 'mr' | T46: e2e/phase-02-settings/P2B.identity.language.spec.ts
... A129: TC-P2B-108 | B129: 2B Identity | C129: P1 | D129: Hospital A's white-label settings are invisible to Hospital B | E129: 1) Sign in as the Hospital B administrator 2) Open /settings/white-label as Hospital B 3) Read the custom domain | F129: Hospital B sees no trace of Hospital A's domain or theme. | G129: PASS | H129: MOCK_DATA_BOOK Hospitals — Hospital A (Aarogya) and Hospital B (Sanjeevani) | I129: Multi-tenancy, Patient Portal | J129: Both QA tenants seeded | K129: Automated: passed. | M129: N | O129: P2-Setup | P129: A custom domain is a routing instruction. One tenant reading or writing another's could redirect a hospital's patient portal traffic to a domain it does not control. | Q129: Cross-Module | R129: hospital_admin (Hospital B) | S129: hospitals queried as the Hospital B admin → zero rows for Hospital A | T129: e2e/phase-02-settings/P2B.identity.brand-support.spec.ts
A130: TC-P2B-109 | B130: 2B Identity | C130: P2 | D130: A receptionist cannot reach the White-Label screen | E130: 1) Log in as receptionist (Hospital A) 2) Navigate directly to /settings/white-label | F130: The route is blocked — redirected away, or an explicit access-denied message. | G130: PASS | H130: MOCK_DATA_BOOK Staff logins — receptionist (Hospital A), Ms. Divya Sharma | I130: Patient Portal | J130: Tier 0 roles configured (Phase 1 §1E) | K130: Automated: passed. | L130: Warning: Encountered two children with the same key, `%s`. Keys should be unique so that components maintain their identity across updates. Non-unique keys may cause children to be duplicated and/or omitted — the behavior is unsupported and could change in a future version.%s Nephrology Ward at div at div at BedOccupancy (http://localhost:8080/src/components/dashboard/BedOccupancy.tsx:21:28) at div at div at Dashboard (http://localhost:8080/src/pages/Dashboard.tsx:107:56) at ModuleErrorBoundary (http://localhost:8080/src/components/auth/ModuleErrorBoundary.tsx:4:1) …(truncated) | M130: N | O130: P2-Setup | P130: Changing the custom domain changes where patients are sent. That is an infrastructure decision, not a front-desk one. | Q130: RBAC | R130: receptionist (Hospital A) | S130: None — route guard behaviour | T130: e2e/phase-02-settings/P2B.identity.brand-support.spec.ts
A131: TC-P2B-110 | B131: 2B Identity | C131: P2 | D131: The White-Label screen loads with no red console errors | E131: 1) Open DevTools → Console 2) Open /settings/white-label 3) Save the theme and the domain 4) Read the console | F131: No red console text from either save path. | G131: FAIL | H131: phase2.entry./settings/white-label — customDomain aarogya-qa.example.in | I131: Patient Portal | J131: Tier 0: hospital profile created (Settings → Hospital Profile) | K131: Automated: FAILED. Error: Could not find a control for the label "Custom Domain" on /settings/white-label. This is a FRAMEWORK failure, not a product defect — the label text in settings-forms.ts no longer matches what the page renders. Fix the label there; do not log it as a bug against the app (docs/qa/README.md). | M131: Y | O131: P2-Setup | P131: Both saves write to hospitals through an `as any` cast, so a column that does not exist produces a PostgREST error that never reaches the UI and appears only in the console. | Q131: Positive | R131: hospital_admin (Hospital A) | S131: None — console observation | T131: e2e/phase-02-settings/P2B.identity.brand-support.spec.ts
A132: TC-P2B-111 | B132: 2B Identity | C132: P3 | D132: Support screen loads with the ticket form and existing tickets | E132: 1) Open /settings/support 2) Read the page | F132: Subject, Category and "Describe the issue" render, along with any existing tickets for this hospital. No red console errors. | G132: FAIL | H132: phase2.entry./settings/support — subject "QA Phase 2 smoke" | I132: Platform | J132: Tier 0: hospital profile created (Settings → Hospital Profile) | K132: Automated: FAILED. Error: "Describe the issue" is missing expect(locator).toBeVisible() failed Locator: getByText('Describe the issue').first() Expected: visible Timeout: 15000ms Error: element(s) not found Call log: - "Describe the issue" is missing with timeout 15000ms - waiting for getByText('Describe the issue').first() | M132: Y | O132: P2-Setup | P132: This is the hospital's only in-product route to the vendor. If it will not load, a hospital in trouble has no way to reach anyone from inside the system. | Q132: Positive | R132: hospital_admin (Hospital A) | S132: platform_support_tickets where hospital_id = A → matches the tickets displayed | T132: e2e/phase-02-settings/P2B.identity.brand-support.spec.ts
A133: TC-P2B-112 | B133: 2B Identity | C133: P2 | D133: A support ticket submits and is stored | E133: 1) Open /settings/support 2) Enter Subject "QA Phase 2 smoke" 3) Select a Category 4) Enter the description 5) Submit | F133: A "Support ticket submitted" toast appears and a platform_support_tickets row exists for Hospital A with that subject. | G133: FAIL | H133: phase2.entry./settings/support — subject "QA Phase 2 smoke", body "Raised by the Phase 2 data-entry suite. Safe to close." | I133: Platform | J133: Tier 0: hospital profile created (Settings → Hospital Profile) | K133: Automated: FAILED. Error: Could not find a control for the label "Subject" on /settings/support. This is a FRAMEWORK failure, not a product defect — the label text in settings-forms.ts no longer matches what the page renders. Fix the label there; do not log it as a bug against the app (docs/qa/README.md). | M133: Y | O133: P2-Setup | P133: A ticket that appears to submit and writes nothing is worse than no support form: the hospital believes help is coming and waits. | Q133: Positive | R133: hospital_admin (Hospital A) | S133: platform_support_tickets where hospital_id = A and subject = 'QA Phase 2 smoke' → 1 row | T133: e2e/phase-02-settings/P2B.identity.brand-support.spec.ts
A134: TC-P2B-113 | B134: 2B Identity | C134: P3 | D134: A ticket cannot be submitted without a subject | E134: 1) Open /settings/support 2) Leave Subject blank 3) Enter a description 4) Submit | F134: The submission is refused and no platform_support_tickets row is written. | G134: FAIL | H134: None — deliberately omits the required Subject | I134: Platform | J134: Tier 0: hospital profile created (Settings → Hospital Profile) | K134: Automated: FAILED. Error: Could not find a control for the label "Describe the issue" on /settings/support. This is a FRAMEWORK failure, not a product defect — the label text in settings-forms.ts no longer matches what the page renders. Fix the label there; do not log it as a bug against the app (docs/qa/README.md). | M134: Y | O134: P2-Setup | P134: A subjectless ticket cannot be triaged or prioritised, so it sits at the bottom of the queue while the hospital waits. | Q134: Negative | R134: hospital_admin (Hospital A) | S134: platform_support_tickets where hospital_id = A and (subject is null or subject = '') → 0 rows | T134: e2e/phase-02-settings/P2B.identity.brand-support.spec.ts
A135: TC-P2B-114 | B135: 2B Identity | C135: P3 | D135: A ticket cannot be submitted without a description | E135: 1) Open /settings/support 2) Enter a Subject 3) Leave "Describe the issue" blank 4) Submit | F135: The submission is refused and no row is written. | G135: FAIL | H135: None — deliberately omits the required description | I135: Platform | J135: Tier 0: hospital profile created (Settings → Hospital Profile) | K135: Automated: FAILED. Error: Could not find a control for the label "Subject" on /settings/support. This is a FRAMEWORK failure, not a product defect — the label text in settings-forms.ts no longer matches what the page renders. Fix the label there; do not log it as a bug against the app (docs/qa/README.md). | M135: Y | O135: P2-Setup | P135: A ticket with only a subject forces a round trip before anyone can even begin, which doubles the time to resolution on an issue that may be blocking clinical work. | Q135: Negative | R135: hospital_admin (Hospital A) | S135: platform_support_tickets where hospital_id = A and body is null → 0 rows | T135: e2e/phase-02-settings/P2B.identity.brand-support.spec.ts
A136: TC-P2B-115 | B136: 2B Identity | C136: P3 | D136: Support ticket category "Billing" saves | E136: 1) Open /settings/support 2) Enter a Subject and description 3) Select Category "Billing" 4) Submit | F136: A platform_support_tickets row is written with category = 'billing'. | G136: FAIL | H136: The Category options on SettingsSupportPage — "billing" | I136: Platform | J136: Tier 0: hospital profile created (Settings → Hospital Profile) | K136: Automated: FAILED. Error: Could not find a control for the label "Subject" on /settings/support. This is a FRAMEWORK failure, not a product defect — the label text in settings-forms.ts no longer matches what the page renders. Fix the label there; do not log it as a bug against the app (docs/qa/README.md). | M136: Y | O136: P2-Setup | P136: Category is what routes a ticket to the right team and sets its urgency. Each value is tested because one failing to save silently sends every such ticket to the default queue. This one covers a disputed invoice or a subscription question. | Q136: Positive | R136: hospital_admin (Hospital A) | S136: platform_support_tickets where hospital_id = A → category = 'billing' | T136: e2e/phase-02-settings/P2B.identity.brand-support.spec.ts
A137: TC-P2B-116 | B137: 2B Identity | C137: P3 | D137: Support ticket category "Technical" saves | E137: 1) Open /settings/support 2) Enter a Subject and description 3) Select Category "Technical" 4) Submit | F137: A platform_support_tickets row is written with category = 'technical'. | G137: FAIL | H137: The Category options on SettingsSupportPage — "technical" | I137: Platform | J137: Tier 0: hospital profile created (Settings → Hospital Profile) | K137: Automated: FAILED. Error: Could not find a control for the label "Subject" on /settings/support. This is a FRAMEWORK failure, not a product defect — the label text in settings-forms.ts no longer matches what the page renders. Fix the label there; do not log it as a bug against the app (docs/qa/README.md). | M137: Y | O137: P2-Setup | P137: Category is what routes a ticket to the right team and sets its urgency. Each value is tested because one failing to save silently sends every such ticket to the default queue. This one covers the system being down, which is the most time-critical category. | Q137: Positive | R137: hospital_admin (Hospital A) | S137: platform_support_tickets where hospital_id = A → category = 'technical' | T137: e2e/phase-02-settings/P2B.identity.brand-support.spec.ts
A138: TC-P2B-117 | B138: 2B Identity | C138: P3 | D138: Support ticket category "Clinical Workflow" saves | E138: 1) Open /settings/support 2) Enter a Subject and description 3) Select Category "Clinical Workflow" 4) Submit | F138: A platform_support_tickets row is written with category = 'clinical_workflow'. | G138: FAIL | H138: The Category options on SettingsSupportPage — "clinical_workflow" | I138: Platform | J138: Tier 0: hospital profile created (Settings → Hospital Profile) | K138: Automated: FAILED. Error: Could not find a control for the label "Subject" on /settings/support. This is a FRAMEWORK failure, not a product defect — the label text in settings-forms.ts no longer matches what the page renders. Fix the label there; do not log it as a bug against the app (docs/qa/README.md). | M138: Y | O138: P2-Setup | P138: Category is what routes a ticket to the right team and sets its urgency. Each value is tested because one failing to save silently sends every such ticket to the default queue. This one covers a workflow that does not match how the hospital actually works. | Q138: Positive | R138: hospital_admin (Hospital A) | S138: platform_support_tickets where hospital_id = A → category = 'clinical_workflow' | T138: e2e/phase-02-settings/P2B.identity.brand-support.spec.ts
A139: TC-P2B-118 | B139: 2B Identity | C139: P3 | D139: Support ticket category "Training" saves | E139: 1) Open /settings/support 2) Enter a Subject and description 3) Select Category "Training" 4) Submit | F139: A platform_support_tickets row is written with category = 'training'. | G139: FAIL | H139: The Category options on SettingsSupportPage — "training" | I139: Platform | J139: Tier 0: hospital profile created (Settings → Hospital Profile) | K139: Automated: FAILED. Error: Could not find a control for the label "Subject" on /settings/support. This is a FRAMEWORK failure, not a product defect — the label text in settings-forms.ts no longer matches what the page renders. Fix the label there; do not log it as a bug against the app (docs/qa/README.md). | M139: Y | O139: P2-Setup | P139: Category is what routes a ticket to the right team and sets its urgency. Each value is tested because one failing to save silently sends every such ticket to the default queue. This one covers a staff member who cannot use a screen. | Q139: Positive | R139: hospital_admin (Hospital A) | S139: platform_support_tickets where hospital_id = A → category = 'training' | T139: e2e/phase-02-settings/P2B.identity.brand-support.spec.ts
A140: TC-P2B-119 | B140: 2B Identity | C140: P3 | D140: A submitted ticket appears in the hospital's ticket list | E140: 1) Open /settings/support 2) Submit a ticket 3) Reload the page 4) Read the ticket list | F140: The ticket is listed with its subject and status after the reload. | G140: FAIL | H140: phase2.entry./settings/support — subject "QA Phase 2 smoke" | I140: Platform | J140: Tier 0: hospital profile created (Settings → Hospital Profile) | K140: Automated: FAILED. Error: Could not find a control for the label "Subject" on /settings/support. This is a FRAMEWORK failure, not a product defect — the label text in settings-forms.ts no longer matches what the page renders. Fix the label there; do not log it as a bug against the app (docs/qa/README.md). | M140: Y | O140: P2-Setup | P140: Without a visible list the hospital cannot tell whether a ticket was raised, and submits it again — creating duplicates that slow the queue for everyone. | Q140: Positive | R140: hospital_admin (Hospital A) | S140: platform_support_tickets where hospital_id = A and subject = 'QA Phase 2 smoke' → visible in the list | T140: e2e/phase-02-settings/P2B.identity.brand-support.spec.ts
A141: TC-P2B-120 | B141: 2B Identity | C141: P3 | D141: A reply can be added to an existing ticket | E141: 1) Open /settings/support 2) Open an existing ticket 3) Enter a reply 4) Send | F141: A "Reply sent" confirmation appears and the reply is stored against the ticket. | G141: FAIL | H141: phase2.entry./settings/support — a reply on the "QA Phase 2 smoke" ticket | I141: Platform | J141: Tier 0: hospital profile created (Settings → Hospital Profile) | K141: Automated: FAILED. Error: Could not find a control for the label "Subject" on /settings/support. This is a FRAMEWORK failure, not a product defect — the label text in settings-forms.ts no longer matches what the page renders. Fix the label there; do not log it as a bug against the app (docs/qa/README.md). | M141: Y | O141: P2-Setup | P141: Support is a conversation. A reply that is not stored means the vendor never sees the extra detail and asks for it again by email, outside the system. | Q141: Positive | R141: hospital_admin (Hospital A) | S141: the ticket replies table → 1 reply row against the QA ticket | T141: e2e/phase-02-settings/P2B.identity.brand-support.spec.ts
A142: TC-P2B-121 | B142: 2B Identity | C142: P2 | D142: A submitted ticket survives a hard reload | E142: 1) Open /settings/support 2) Submit a ticket 3) Hard-reload the page | F142: The ticket is still listed after the reload. | G142: FAIL | H142: phase2.entry./settings/support — subject "QA Phase 2 smoke" | I142: Platform | J142: Tier 0: hospital profile created (Settings → Hospital Profile) | K142: Automated: FAILED. Error: Could not find a control for the label "Subject" on /settings/support. This is a FRAMEWORK failure, not a product defect — the label text in settings-forms.ts no longer matches what the page renders. Fix the label there; do not log it as a bug against the app (docs/qa/README.md). | M142: Y | O142: P2-Setup | P142: A green toast is not a save. On a support form specifically, a false success means the hospital stops chasing an issue that nobody has received. | Q142: Positive | R142: hospital_admin (Hospital A) | S142: platform_support_tickets where hospital_id = A and subject = 'QA Phase 2 smoke' → 1 row | T142: e2e/phase-02-settings/P2B.identity.brand-support.spec.ts
... A150: TC-P2B-129 | B150: 2B Identity | C150: P3 | D150: The Training screen offers no save action | E150: 1) Open /settings/training 2) Look for a Save control | F150: No Save button renders — the screen is read-only, and the video library is platform-managed. | G150: PASS | H150: None — asserts the absence of a save control | I150: LMS | J150: Tier 0: hospital profile created (Settings → Hospital Profile) | K150: Automated: passed. | M150: N | O150: P2-Setup | P150: The library belongs to the vendor, not the hospital. A save control here would imply a hospital can edit content it cannot, which is a promise the screen must not make. | Q150: Boundary | R150: hospital_admin (Hospital A) | S150: None — asserts no write path exists | T150: e2e/phase-02-settings/P2B.identity.brand-support.spec.ts
A151: TC-P2B-130 | B151: 2B Identity | C151: P3 | D151: A training video can be opened | E151: 1) Open /settings/training 2) Click a video | F151: The video opens in a player or a new tab without a console error. | G151: FAIL | H151: platform_training_videos — the first seeded video | I151: LMS | J151: Tier 0: hospital profile created (Settings → Hospital Profile) | K151: Automated: FAILED. Error: Opening a video produced console errors: `DialogContent` requires a `DialogTitle` for the component to be accessible for screen reader users. If you want to hide the `DialogTitle`, you can wrap it with our VisuallyHidden component. For more information, see https://radix-ui.com/primitives/docs/components/dialog A library that lists videos nobody can play is worse than no library. expect(received).toHaveLength(expected) Expected length: 0 Received length: 1 Received array: ["`DialogContent` requires a `DialogTitle` for the component to be accessible for screen reader users.· If you want to hide the `DialogTitle`, you can wrap it with our VisuallyHidden component.· For more information, see https://radix-ui.com/primitives/docs/components/dialog"] | L151: `DialogContent` requires a `DialogTitle` for the component to be accessible for screen reader users. If you want to hide the `DialogTitle`, you can wrap it with our VisuallyHidden component. For more information, see https://radix-ui.com/primitives/docs/components/dialog | M151: Y | O151: P2-Setup | P151: A library that lists videos nobody can play is worse than no library — the hospital concludes training does not exist and stops checking. | Q151: Positive | R151: hospital_admin (Hospital A) | S151: None — playback interaction | T151: e2e/phase-02-settings/P2B.identity.brand-support.spec.ts
A152: TC-P2B-131 | B152: 2B Identity | C152: P3 | D152: Videos carry the role they are aimed at | E152: 1) Open /settings/training 2) Read the video metadata | F152: Videos indicate the role or module they cover, so a nurse can find nursing content. | G152: PASS | H152: platform_training_videos — role metadata on the seeded library | I152: LMS, HR | J152: Tier 0: hospital profile created (Settings → Hospital Profile) | K152: Automated: passed. | M152: N | O152: P2-Setup | P152: The catalogue promises "short how-to videos for every role". Without role metadata a pharmacist has to watch billing videos to find out they are not relevant. | Q152: Positive | R152: hospital_admin (Hospital A) | S152: platform_training_videos → role or module metadata is present | T152: e2e/phase-02-settings/P2B.identity.brand-support.spec.ts
A153: TC-P2B-132 | B153: 2B Identity | C153: P2 | D153: The training library is shared platform content, not tenant data | E153: 1) Open /settings/training as Hospital A and note the videos 2) Sign in as the Hospital B administrator 3) Open /settings/training as Hospital B | F153: Both hospitals see the same platform-managed library. No hospital-specific rows leak between them. | G153: PASS | H153: MOCK_DATA_BOOK Hospitals — Hospital A (Aarogya) and Hospital B (Sanjeevani) | I153: Multi-tenancy, LMS | J153: Both QA tenants seeded | K153: Automated: passed. | M153: N | O153: P2-Setup | P153: This table is deliberately shared, which makes it the one place where seeing the same rows in both tenants is correct. Recorded explicitly so it is never "fixed" into a tenant-scoped table by mistake. | Q153: Cross-Module | R153: hospital_admin (Hospital B) | S153: platform_training_videos → identical rows visible to both tenants | T153: e2e/phase-02-settings/P2B.identity.brand-support.spec.ts
A154: TC-P2B-133 | B154: 2B Identity | C154: P3 | D154: The Training screen is reachable by hospital_admin | E154: 1) Log in as hospital_admin (Hospital A) 2) Navigate to /settings/training | F154: The screen loads and videos are listed. | G154: PASS | H154: MOCK_DATA_BOOK Staff logins — hospital_admin (Hospital A), Dr. Ravi Shankar | I154: LMS | J154: Tier 0 roles configured (Phase 1 §1E) | K154: Automated: passed. | M154: N | O154: P2-Setup | P154: Training is read-only vendor content with no patient data in it, so the gate here should be permissive. A gate that is too tight blocks the adoption the videos exist to drive. | Q154: RBAC | R154: hospital_admin (Hospital A) | S154: None — route guard behaviour | T154: e2e/phase-02-settings/P2B.identity.brand-support.spec.ts
A155: TC-P2B-134 | B155: 2B Identity | C155: P2 | D155: The Training screen loads with no red console errors | E155: 1) Open DevTools → Console 2) Open /settings/training 3) Search and open a video 4) Read the console | F155: No red console text, including from the video embed. | G155: PASS | H155: phase2.entry./settings/training — search term OPD | I155: LMS | J155: Tier 0: hospital profile created (Settings → Hospital Profile) | K155: Automated: passed. | M155: N | O155: P2-Setup | P155: Video embeds pull from an external host. A blocked embed shows as an empty player with the real cause visible only in the console. | Q155: Positive | R155: hospital_admin (Hospital A) | S155: None — console observation | T155: e2e/phase-02-settings/P2B.identity.brand-support.spec.ts
A156: TC-P2C-001 | B156: 2C Plan & Entitlement | C156: P2 | D156: Plan & Billing screen loads | E156: 1) Log in as hospital_admin (Hospital A) 2) Open /settings/plan 3) Read the page | F156: The current plan, usage statistics and invoice history render. No red console errors. | G156: FAIL | H156: MOCK_DATA_BOOK Hospital A — Professional plan | I156: All modules, Billing | J156: Tier 0: hospital profile created; a subscription row exists for the tenant | K156: Automated: FAILED. Error: Console errors: Failed to load resource: the server responded with a status of 404 () Failed to load resource: the server responded with a status of 404 () expect(received).toHaveLength(expected) Expected length: 0 Received length: 2 Received array: ["Failed to load resource: the server responded with a status of 404 ()", "Failed to load resource: the server responded with a status of 404 ()"] | L156: Failed to load resource: the server responded with a status of 404 () Failed to load resource: the server responded with a status of 404 () | M156: Y | O156: P2-Setup | P156: The plan determines which of the 39 modules exist at all. If this screen will not load, a hospital cannot see what it is paying for or discover why a module is missing. | Q156: Positive | R156: hospital_admin (Hospital A) | S156: hospital_subscriptions where hospital_id = A → 1 row matching the plan displayed | T156: e2e/phase-02-settings/P2C.plan-entitlement.spec.ts
A157: TC-P2C-002 | B157: 2C Plan & Entitlement | C157: P1 | D157: The current plan shown matches the subscription row | E157: 1) Open /settings/plan 2) Read the plan name 3) Compare against hospital_subscriptions | F157: The screen shows the Professional plan, matching hospital_subscriptions for Hospital A. | G157: FAIL | H157: MOCK_DATA_BOOK Hospital A — Professional plan | I157: All modules | J157: Tier 0: hospital profile created; a subscription row exists for the tenant | K157: Automated: FAILED. Error: Hospital A ("Aarogya Multispecialty Hospital") does not exist. Run: node scripts/qa-seed.mjs | L157: Failed to load resource: the server responded with a status of 404 () Failed to load resource: the server responded with a status of 404 () | M157: Y | O157: P2-Setup | P157: SETTINGS_PREREQ_MATRIX puts the plan in Tier 0 because whole sections of the app disappear without it. A screen showing a different plan from the one enforced means every access denial looks like a bug. | Q157: Positive | R157: hospital_admin (Hospital A) | S157: hospital_subscriptions where hospital_id = A → plan matches 'Professional' | T157: e2e/phase-02-settings/P2C.plan-entitlement.spec.ts
A158: TC-P2C-003 | B158: 2C Plan & Entitlement | C158: P2 | D158: Staff usage is counted against the plan | E158: 1) Open /settings/plan 2) Read the staff usage figure 3) Compare against the active users for Hospital A | F158: The staff count matches the number of active users in the tenant. | G158: FAIL | H158: MOCK_DATA_BOOK Staff logins — 17 Hospital A accounts | I158: HR, Plan gating | J158: Tier 0: hospital profile created; a subscription row exists for the tenant | K158: Automated: FAILED. Error: Hospital A ("Aarogya Multispecialty Hospital") does not exist. Run: node scripts/qa-seed.mjs | L158: Failed to load resource: the server responded with a status of 404 () Failed to load resource: the server responded with a status of 404 () | M158: Y | O158: P2-Setup | P158: Staff count drives seat billing. A figure that drifts from reality means the hospital is either over-charged or silently exceeding what it pays for. | Q158: Positive | R158: hospital_admin (Hospital A) | S158: users where hospital_id = A and is_active = true → count matches the displayed figure | T158: e2e/phase-02-settings/P2C.plan-entitlement.spec.ts
A159: TC-P2C-004 | B159: 2C Plan & Entitlement | C159: P1 | D159: Bed usage is counted against the plan bed limit | E159: 1) Open /settings/wards and note the total beds 2) Open /settings/plan 3) Read the bed usage figure | F159: The bed usage matches the count of beds rows for Hospital A, and is shown against the plan maximum. | G159: FAIL | H159: MOCK_DATA_BOOK Wards & beds — 32 seeded beds across six wards | I159: IPD, Plan gating | J159: Tier 0: hospital profile created; a subscription row exists for the tenant | K159: Automated: FAILED. Error: Hospital A ("Aarogya Multispecialty Hospital") does not exist. Run: node scripts/qa-seed.mjs | L159: Failed to load resource: the server responded with a status of 404 () Failed to load resource: the server responded with a status of 404 () | M159: Y | O159: P2-Setup | P159: The bed limit is enforced when creating a ward (TC-P2D-054). If the count shown here disagrees with the count the gate uses, a hospital is blocked from adding a bed while this screen says it has room. | Q159: Cross-Module | R159: hospital_admin (Hospital A) | S159: beds where hospital_id = A → count matches the displayed bed usage | T159: e2e/phase-02-settings/P2C.plan-entitlement.spec.ts
A160: TC-P2C-005 | B160: 2C Plan & Entitlement | C160: P2 | D160: Encounter usage for the billing cycle renders | E160: 1) Open /settings/plan 2) Read the encounter usage figure | F160: Encounter usage for the current billing cycle renders from hospital_encounter_usage without error. | G160: FAIL | H160: hospital_encounter_usage — the current cycle for Hospital A | I160: OPD, IPD, Billing | J160: Tier 0: hospital profile created; a subscription row exists for the tenant | K160: Automated: FAILED. Error: Hospital A ("Aarogya Multispecialty Hospital") does not exist. Run: node scripts/qa-seed.mjs | L160: Failed to load resource: the server responded with a status of 404 () Failed to load resource: the server responded with a status of 404 () | M160: Y | O160: P2-Setup | P160: Encounter volume is the metered dimension on usage-based plans. A hospital that cannot see it has no warning before an overage lands on the invoice. | Q160: Positive | R160: hospital_admin (Hospital A) | S160: hospital_encounter_usage where hospital_id = A → matches the displayed figure | T160: e2e/phase-02-settings/P2C.plan-entitlement.spec.ts
A161: TC-P2C-006 | B161: 2C Plan & Entitlement | C161: P2 | D161: AI usage for the calendar month renders as observability only | E161: 1) Open /settings/plan 2) Locate the AI usage figure 3) Confirm it is presented as information, not as a gate | F161: AI spend for the current calendar month renders. It is labelled as observability and does not itself block anything. | G161: PASS | H161: ai_cost_daily — the current month for Hospital A | I161: AI Suite | J161: Tier 0: hospital profile created; a subscription row exists for the tenant | K161: Automated: passed. | L161: Failed to load resource: the server responded with a status of 404 () Failed to load resource: the server responded with a status of 404 () | M161: N | O161: P2-Setup | P161: AI budget is enforced separately in hospital_ai_wallet. Presenting this figure as a limit would make an administrator think AI is blocked when the real gate is elsewhere — SETTINGS_PREREQ_MATRIX warns there are three independent AI gates. | Q161: Positive | R161: hospital_admin (Hospital A) | S161: ai_cost_daily where hospital_id = A → matches the displayed spend | T161: e2e/phase-02-settings/P2C.plan-entitlement.spec.ts
A162: TC-P2C-007 | B162: 2C Plan & Entitlement | C162: P3 | D162: Storage usage renders from the per-tenant RPC | E162: 1) Open /settings/plan 2) Read the storage usage figure | F162: Storage usage renders as a size, without a console error from the get_storage_usage RPC. | G162: PASS | H162: get_storage_usage RPC for Hospital A | I162: MRD, Radiology | J162: Tier 0: hospital profile created; a subscription row exists for the tenant | K162: Automated: passed. | L162: Failed to load resource: the server responded with a status of 404 () Failed to load resource: the server responded with a status of 404 () | M162: N | O162: P2-Setup | P162: Storage fills up with scanned records and DICOM images. A hospital that cannot see the figure gets no warning before uploads start failing mid-clinic. | Q162: Positive | R162: hospital_admin (Hospital A) | S162: get_storage_usage RPC returns a value for Hospital A | T162: e2e/phase-02-settings/P2C.plan-entitlement.spec.ts
A163: TC-P2C-008 | B163: 2C Plan & Entitlement | C163: P2 | D163: The upgrade dialog opens | E163: 1) Open /settings/plan 2) Click the upgrade action 3) Observe the dialog | F163: The upgrade dialog opens listing the plans available above the current one. | G163: FAIL | H163: subscription_plans — the plans above Professional | I163: Plan gating, Billing | J163: Tier 0: hospital profile created; a subscription row exists for the tenant | K163: Automated: FAILED. Error: Every plan gate in the product points here. A gate that leads to a dialog that will not open turns a sales opportunity into a dead end. expect(locator).toBeVisible() failed Locator: getByRole('dialog').first() Expected: visible Timeout: 15000ms Error: element(s) not found Call log: - Every plan gate in the product points here. A gate that leads to a dialog that will not open turns a sales opportunity into a dead end. with timeout 15000ms - waiting for getByRole('dialog').first() | L163: Failed to load resource: the server responded with a status of 404 () Failed to load resource: the server responded with a status of 404 () | M163: Y | O163: P2-Setup | P163: Every plan gate elsewhere in the product points the user here. A gate that leads to a dialog that will not open turns a sales opportunity into a dead end. | Q163: Positive | R163: hospital_admin (Hospital A) | S163: subscription_plans → the plans offered match what the dialog lists | T163: e2e/phase-02-settings/P2C.plan-entitlement.spec.ts
A164: TC-P2C-009 | B164: 2C Plan & Entitlement | C164: P3 | D164: Other available plans are listed for comparison | E164: 1) Open /settings/plan 2) Read the plan comparison section | F164: Plans other than the current one are listed with their prices. | G164: PASS | H164: subscription_plans — the full plan catalogue | I164: Plan gating | J164: Tier 0: hospital profile created; a subscription row exists for the tenant | K164: Automated: passed. | L164: Failed to load resource: the server responded with a status of 404 () Failed to load resource: the server responded with a status of 404 () | M164: N | O164: P2-Setup | P164: A hospital deciding whether to upgrade needs to see what it would get. Showing only the current plan makes the upgrade decision impossible without contacting sales. | Q164: Positive | R164: hospital_admin (Hospital A) | S164: subscription_plans → more than one plan is listed | T164: e2e/phase-02-settings/P2C.plan-entitlement.spec.ts
A165: TC-P2C-010 | B165: 2C Plan & Entitlement | C165: P2 | D165: The add-on catalogue lists purchasable add-ons | E165: 1) Open /settings/plan 2) Read the add-on section | F165: Add-ons from addon_skus render with their names and monthly prices. | G165: PASS | H165: addon_skus — the platform add-on catalogue | I165: Plan gating, AI Suite | J165: Tier 0: hospital profile created; a subscription row exists for the tenant | K165: Automated: passed. | L165: Failed to load resource: the server responded with a status of 404 () Failed to load resource: the server responded with a status of 404 () | M165: N | O165: P2-Setup | P165: Add-ons carry the ai_feature_keys that unlock AI features. SETTINGS_PREREQ_MATRIX names plan entitlement as the first of three gates on any AI button — if the catalogue does not render, the hospital cannot buy the entitlement it needs. | Q165: Positive | R165: hospital_admin (Hospital A) | S165: addon_skus → the catalogue rows match what is displayed | T165: e2e/phase-02-settings/P2C.plan-entitlement.spec.ts
A166: TC-P2C-011 | B166: 2C Plan & Entitlement | C166: P2 | D166: Add-ons the hospital already owns are distinguished from the catalogue | E166: 1) Open /settings/plan 2) Compare the add-on list against hospital_addons for Hospital A | F166: Owned add-ons are marked as owned and are not offered for purchase again. | G166: FAIL | H166: hospital_addons — the add-ons granted to Hospital A | I166: Plan gating, AI Suite | J166: Tier 0: hospital profile created; a subscription row exists for the tenant | K166: Automated: FAILED. Error: Hospital A ("Aarogya Multispecialty Hospital") does not exist. Run: node scripts/qa-seed.mjs | M166: Y | O166: P2-Setup | P166: Offering an add-on the hospital already pays for invites a duplicate purchase, and a duplicate grant makes the entitlement calculation ambiguous. | Q166: Positive | R166: hospital_admin (Hospital A) | S166: hospital_addons where hospital_id = A → each owned SKU is marked owned in the UI | T166: e2e/phase-02-settings/P2C.plan-entitlement.spec.ts
A167: TC-P2C-012 | B167: 2C Plan & Entitlement | C167: P2 | D167: Add-on prices render in en-IN grouping with the rupee symbol | E167: 1) Open /settings/plan 2) Read an add-on monthly price | F167: Prices render as ₹ amounts with Indian digit grouping, via formatCurrency(). | G167: PASS | H167: addon_skus — price_monthly on the catalogue rows | I167: Billing, Accounts | J167: Tier 0: hospital profile created; a subscription row exists for the tenant | K167: Automated: passed. | L167: Failed to load resource: the server responded with a status of 404 () Failed to load resource: the server responded with a status of 404 () | M167: N | O167: P2-Setup | P167: This is a purchase decision screen. A price rendered as a bare number or with international grouping misstates what the hospital is committing to. | Q167: Positive | R167: hospital_admin (Hospital A) | S167: addon_skus.price_monthly → rendered with ₹ and Indian grouping | T167: e2e/phase-02-settings/P2C.plan-entitlement.spec.ts
A168: TC-P2C-013 | B168: 2C Plan & Entitlement | C168: P2 | D168: Subscription invoices are listed | E168: 1) Open /settings/plan 2) Read the invoice history | F168: Rows from subscription_invoices render with their dates and amounts, or an empty state if there are none. | G168: FAIL | H168: subscription_invoices — the invoice history for Hospital A | I168: Accounts, Billing | J168: Tier 0: hospital profile created; a subscription row exists for the tenant | K168: Automated: FAILED. Error: Hospital A ("Aarogya Multispecialty Hospital") does not exist. Run: node scripts/qa-seed.mjs | L168: Failed to load resource: the server responded with a status of 404 () Failed to load resource: the server responded with a status of 404 () | M168: Y | O168: P2-Setup | P168: The hospital's finance team reconciles the software spend against these invoices. Missing history means the spend cannot be verified at audit. | Q168: Positive | R168: hospital_admin (Hospital A) | S168: subscription_invoices where hospital_id = A → match the rows displayed | T168: e2e/phase-02-settings/P2C.plan-entitlement.spec.ts
A169: TC-P2C-014 | B169: 2C Plan & Entitlement | C169: P3 | D169: An invoice can be downloaded | E169: 1) Open /settings/plan 2) Click download on an invoice 3) Observe the result | F169: An invoice document is produced, or a clear message explains why it is unavailable. No unhandled error. | G169: N/A | H169: subscription_invoices — the most recent invoice for Hospital A | I169: Accounts | J169: Tier 0: hospital profile created; a subscription row exists for the tenant | K169: Automated: skipped — precondition not met (see spec skip reason). | M169: N | O169: P2-Setup | P169: The invoice is a tax document the hospital needs for its own books. A download that fails silently forces a support ticket for something that should be self-service. | Q169: Positive | R169: hospital_admin (Hospital A) | S169: None — download interaction | T169: e2e/phase-02-settings/P2C.plan-entitlement.spec.ts
A170: TC-P2C-015 | B170: 2C Plan & Entitlement | C170: P3 | D170: Payment history renders | E170: 1) Open /settings/plan 2) Read the payment history table | F170: Past payments render with dates and amounts, or an empty state. | G170: PASS | H170: subscription_invoices — payment records for Hospital A | I170: Accounts, Payments | J170: Tier 0: hospital profile created; a subscription row exists for the tenant | K170: Automated: passed. | M170: N | O170: P2-Setup | P170: A hospital disputing a charge needs to see what was actually taken and when. Without it the conversation starts with the vendor's word against theirs. | Q170: Positive | R170: hospital_admin (Hospital A) | S170: None — reads the payment history table | T170: e2e/phase-02-settings/P2C.plan-entitlement.spec.ts
